Workbook
Name D.ACESS.SOBRE_TOT.PROD: #REF!
Name DESP.ACESS.: #REF!
Name ICMS_ST_DO_TOTAL_DOS_PRODUTOS: #REF!
Name PERCENT_ICMS_ST_DO_TOTAL_DOS_PRODUTOS: #REF!
Name QT.A: #REF!
Name QT.B: #REF!
Name QT.C: #REF!
Name QT.D: #REF!
Name QTD._A: #REF!
Name QTD._B: #REF!
Name QTD._C: #REF!
Name QTD.A: #REF!
Name QTD.B: #REF!
Name QTD.C: #REF!
Name QTD.D: #REF!
Name TOT_NF: #REF!
Name TOT_PROD: #REF!
Name VALOR_DO_ICMS_ST: #REF!
Name VALOR_TOTAL_DA_NOTA: #REF!
Name VALOR_TOTAL_DOS_PRODUTOS: #REF!
Name VLR.TOTAL_A: #REF!
Name VLR.TOTAL_B: #REF!
Name VLR.TOTAL_C: #REF!
Name VLR.TOTAL_D: #REF!
Name VR.TOT.A: #REF!
Name VR.TOT.B: #REF!
Name VR.TOT.C: #REF!

Sheet ORIENTAÇÕES E CONF.
A1: CONFERÊNCIAS (ELABORAÇÃO INICIADA EM 03/11/2025) | B1: SEM ALTERAÇÃO | C1: (NÃO É FÓRMULA) | D1: AS EXPRESSÕES
A2: SITUAÇÃO: : | B2: A PREENCHER | C2: (NÃO É FÓRMULA) | D2: "CONFERIDO"
B3: EM EXECUÇÃO | C3: (NÃO É FÓRMULA) | D3: E
A4: CONDOMÍNIO E FUNDO DE RESERVA COM VENCIMENTO EM: | B4: CONFERIR PREENCHTº | C4: (NÃO É FÓRMULA) | D4: "PENDENTE"
A5: 46113 | B5: JÁ CONFERIDO | C5: (NÃO É FÓRMULA) | D5: SÃO FÓRMULAS! | F5: INÍCIO | G5: TÉRMINO
A6: ITEM | B6: SITUAÇÃO | C6: OBS. 1 | D6: OBS. 2 | F6: 05/01,28/01
A7: TABELA "GÁS" DA PLANILHA "MEDIÇÕES E TABELAS" | B7: SEM ALTERAÇÃO | C7: FALTA ALTERAR FÓRMULA DA COLUNA "VALOR" DO GÁS DA TABELA 2 DA PLANILHA "MEDIÇÕES E TABELAS" | F7: 05/01,28/01
A8: TABELA "COPASA NFFS" DA PLANILHA "MEDIÇÕES E TABELAS" (MENSALMENTE: ELIMINAR DESTA TABELA A 1ª LINHA; COPIAR/COLAR A ÚLTIMA LINHA NA TABELA IDÊNTICA DA PLANILHA "MEDIÇÕES E COPASA HISTÓRICO") | B8: EM EXECUÇÃO | C8: VERIFICAR SE FOI RETIRADA (DA CONTA DA LEITURA DE 25/02/26, QUE VENCE EM 15/04/26) A MULTA POR ATRASO DE PAGAMENTO (PROTOCOLO 20260304870368, DE 04/03/26), REF. À CONTA DA LEITURA DE 29/12/25, QUE PAGUEI NO DIA 18/02/26: VENCEU NO DIA 15/02/26, UM DOMINGO, E OS DIAS 16 E 17 FORAM DEFINIDOS COMO FERIADOS BANCÁRIOS. PREVISÃO DE ATENDIMENTO: ATÉ 18/03/26.
A9: LEITURA DE ÁGUA E GÁS | B9: JÁ CONFERIDO
A10: TABELA 1 DA PLANILHA "MEDIÇÕES E TABELAS" (MENSALMENTE: ELIMINAR DA "TABELA 1" A 1ª LINHA DE ÁGUA E A 1ª DE GÁS; COPIAR/COLAR A ÚLTIMA LINHA DE CADA ITEM NA TABELA IDÊNTICA DA PLANILHA "MEDIÇÕES E COPASA HISTÓRICO". CONFERIR NA LINHA "A (-) B" DA LEITURA ATUAL SE HÁ CONSUMO ANORMAL DE ÁGUA E AVISAR AO CONDÔMINO SE HOUVER) | B10: JÁ CONFERIDO | C10: FALTA VERIFICAR SE HOUVE CONSUMO ANORMAL DE ÁGUA: APTºS 401 (IGUAL AO MÊS ANTERIOR), 501 E 602, JÁ AVISADOS +- EM 01/03/26
A11: TABELA 2 DA PLANILHA "MEDIÇÕES E TABELAS" (PROCEDIMENTOS: 1- SEMPRE ATUALIZAR OS DADOS DO CABEÇALHO DA TABELA; 2- SELECIONAR AS CORRESPONDENTES COLUNAS DA TABELA 2 E SUBSTITUIR O Nº DA LINHA ANTERIOR PELA LINHA ATUAL, COM DADOS DA TABELA 1) | B11: JÁ CONFERIDO
A12: TABELA "% DO CONSUMO TOTAL", À DIREITA DA TABELA 2 DA PLANILHA "MEDIÇÕES E TABELAS" (MENSALMENTE: ELIMINAR DESTA TABELA A 1ª COLUNA DATADA; COPIAR/COLAR A ÚLTIMA COLUNA NA TABELA IDÊNTICA DA PLANILHA "MEDIÇÕES E COPASA HISTÓRICO") | B12: JÁ CONFERIDO
A13: TABELA "RATEIOS DE COPASA E SÍNDICO", À DIREITA DA TABELA 2 DA PLANILHA "MEDIÇÕES E TABELAS" (MENSALMENTE: ELIMINAR DESTA TABELA A 1ª LINHA; COPIAR/COLAR A ÚLTIMA LINHA NA TABELA IDÊNTICA DA PLANILHA "MEDIÇÕES E COPASA HISTÓRICO") | B13: JÁ CONFERIDO | C13: FALTA OBTER O VALOR NA PLANILHA LANÇTºS DA FÓRMULA DA CÉLULA AT42
A14: TABELA 3 DA PLANILHA "MEDIÇÕES E TABELAS" COINCIDE COM IGUAL TABELA DA PLANILHA "PLAN P COND" (SEMPRE ATUALIZAR OS DADOS DO CABEÇALHO DA TABELA. ATUALIZAR TAMBÉM OS DADOS DE SALDO DA LINHA DO APTº 801) | B14: =IF('MEDIÇÕES E TABELAS'!G135,"CONFERIDO","PENDENTE") -> CONFERIDO | C14: EM EXECUÇÃO
A15: TABELA 3, DA PLANILHA "MEDIÇÕES E TABELAS": PREENCHER AS 5 COLUNAS À DIREITA DA 2ª COLUNA INTITULADA "TOTAL A PAGAR" | B15: EM EXECUÇÃO
A16: TABELA 3 DA PLANILHA "MEDIÇÕES E TABELAS", COLUNA "RATEIO" | B16: JÁ CONFERIDO
A17: TABELA ABAIXO DA TABELA 3, DA PLANILHA "MEDIÇÕES E TABELAS" (A SER COLADA EM TABELA IDÊNTICA EXISTENTE NA PLANILHA "VRS. DEVIDOS E OUTROS") | B17: JÁ CONFERIDO
A18: PLANILHA "LANÇTºS" COINCIDE COM OS LANÇAMENTOS DA PLANILHA "PLAN P COND" (BUSCAR DADOS DE DESPESAS NO ARQUIVO "Adm" E NOS DEMAIS ARQUIVOS DA PASTA "H\Outr\Condomínio Neápolis") | B18: =IF(LANÇTºS!AQ37,"CONFERIDO","PENDENTE") -> CONFERIDO | C18: EM EXECUÇÃO
A19: PLANILHA "LANÇTºS": ATUALIZAR AS FÓRMULAS DA LINHA "PAGAMENTO SERVIÇO DO SÍNDICO" | B19: JÁ CONFERIDO
A20: PLANILHA "LANÇTºS": ATUALIZAR AS FÓRMULAS DAS 2 LINHAS "CONTA DE ÁGUA DO CONDOMÍNIO" - DEPOIS DE PRONTA: COPIAR/COLAR A TABELA TODA ABAIXO DA EXISTENTE, E A SEGUIR COPIAR/COLAR ESPECIAL TEXTO A TABELA TODA EM CIMA DA QUE JÁ FOI COLADA (ASSIM OS VALORES SERÃO FIXADOS CONFORME OS EXISTENTES NA TABELA ORIGINAL, MAS SEM FÓRMULAS) - CONFERIR FÓRMULA "VERDADEIRO" | B20: EM EXECUÇÃO
A21: TABELA "VALORES DEVIDOS POR UNIDADE" DA PLANILHA "VRS. DEVIDOS E OUTROS": COLAR/TRANSPOR PARA LÁ OS DADOS DA TABELA ABAIXO DA TABELA 3 DA PLANILHA "MEDIÇÕES E TABELAS"
A22: TABELA "VALORES DEVIDOS POR UNIDADE" DA PLANILHA "VRS. DEVIDOS E OUTROS", 1ª LINHA DE CONFERÊNCIA | B22: =IF('VRS. DEVIDOS E OUTROS'!R87,"CONFERIDO","PENDENTE") -> CONFERIDO | C22: FALTA ANALISAR CONSUMO ANORMAL DE ÁGUA (APTº 401: EXCESSO) E TOTAL A PAGAR
A23: TABELA "VALORES DEVIDOS POR UNIDADE" DA PLANILHA "VRS. DEVIDOS E OUTROS", 2ª LINHA DE CONFERÊNCIA - DEPOIS DE PRONTA: 1) COPIAR/COLAR A TABELA TODA À DIREITA DA EXISTENTE, E A SEGUIR COPIAR/COLAR ESPECIAL TEXTO A TABELA TODA EM CIMA DA QUE JÁ FOI COLADA (ASSIM OS VALORES SERÃO FIXADOS CONFORME OS EXISTENTES NA TABELA ORIGINAL, MAS SEM FÓRMULAS) - CONFERIR FÓRMULA "VERDADEIRO"; 2) ANALISAR SE HÁ CONSUMO ANORMAL DE ÁGUA E AVISAR AO CONDÔMINO SE HOUVER | B23: =IF('VRS. DEVIDOS E OUTROS'!R88,"CONFERIDO","PENDENTE") -> CONFERIDO | C23: EM EXECUÇÃO
A24: TABELA "RATEIO MENSAL" DA PLANILHA "VRS. DEVIDOS E OUTROS" COINCIDE COM O QUE CONSTA NA PLANILHA "PLAN P COND" (ATUALIZAR VALORES DA COLUNA "RATEIO" DA TABELA 3 DA PLANILHA "MEDIÇÕES E TABELAS") - DEPOIS DE PRONTA: COPIAR/COLAR A TABELA TODA À DIREITA DA EXISTENTE, E A SEGUIR COPIAR/COLAR ESPECIAL TEXTO A TABELA TODA EM CIMA DA QUE JÁ FOI COLADA (ASSIM OS VALORES SERÃO FIXADOS CONFORME OS EXISTENTES NA TABELA ORIGINAL, MAS SEM FÓRMULAS) - CONFERIR FÓRMULA "VERDADEIRO" | B24: =IF('VRS. DEVIDOS E OUTROS'!F103,"CONFERIDO","PENDENTE") -> CONFERIDO | C24: EM EXECUÇÃO
A25: TABELA "APTº 801" DA PLANILHA "VRS. DEVIDOS E OUTROS" - DEPOIS DE PRONTA: COPIAR/COLAR A TABELA TODA À DIREITA DA EXISTENTE, E A SEGUIR COPIAR/COLAR ESPECIAL TEXTO A TABELA TODA EM CIMA DA QUE JÁ FOI COLADA (ASSIM OS VALORES SERÃO FIXADOS CONFORME OS EXISTENTES NA TABELA ORIGINAL, MAS SEM FÓRMULAS) - CONFERIR FÓRMULA "VERDADEIRO" | B25: =IF('VRS. DEVIDOS E OUTROS'!H109,"CONFERIDO","PENDENTE") -> CONFERIDO | C25: EM EXECUÇÃO
A26: TABELA "APTº 201" (E TEXTO CORRESPONDENTE) DA PLANILHA "VRS. DEVIDOS E OUTROS" - DEPOIS DE PRONTA: COPIAR/COLAR A TABELA TODA À DIREITA DA EXISTENTE, E A SEGUIR COPIAR/COLAR ESPECIAL TEXTO A TABELA TODA EM CIMA DA QUE JÁ FOI COLADA (ASSIM OS VALORES SERÃO FIXADOS CONFORME OS EXISTENTES NA TABELA ORIGINAL, MAS SEM FÓRMULAS)
A27: TABELA "APTº 601" (E TEXTO CORRESPONDENTE) DA PLANILHA "VRS. DEVIDOS E OUTROS" - DEPOIS DE PRONTA: COPIAR/COLAR A TABELA TODA À DIREITA DA EXISTENTE, E A SEGUIR COPIAR/COLAR ESPECIAL TEXTO A TABELA TODA EM CIMA DA QUE JÁ FOI COLADA (ASSIM OS VALORES SERÃO FIXADOS CONFORME OS EXISTENTES NA TABELA ORIGINAL, MAS SEM FÓRMULAS)
A28: TABELA "FUNDO DE RESERVA" DA PLANILHA "VRS. DEVIDOS E OUTROS": SALDO ATUAL COINCIDE COM O QUE ESTÁ NA PLANILHA "PLAN P COND" (ÚLTIMA COLUNA: ADICIONAR VALOR DA COLUNA "SALDO ATUAL CONF. BANCO (B)"DO ARQUIVO "EXTRATO". A SEGUIR: ATUALIZAR VALOR DA COLUNA "FUNDO DE RESERVA" DO ARQUIVO "EXTRATO") - DEPOIS DE PRONTA: COPIAR/COLAR A TABELA TODA À DIREITA DA EXISTENTE, E A SEGUIR COPIAR/COLAR ESPECIAL TEXTO A TABELA TODA EM CIMA DA QUE JÁ FOI COLADA (ASSIM OS VALORES SERÃO FIXADOS CONFORME OS EXISTENTES NA TABELA ORIGINAL, MAS SEM FÓRMULAS) - CONFERIR FÓRMULA "VERDADEIRO" | B28: =IF('VRS. DEVIDOS E OUTROS'!U172,"CONFERIDO","PENDENTE") -> CONFERIDO | C28: EM EXECUÇÃO
A29: PLANILHA "DADOS DO PAGTº" (PREENCHER COM DADOS DA TABELA 3 DA PLANILHA "MEDIÇÕES E TABELAS", SOMENTE APÓS TEREM SIDO ENVIADOS TODOS OS RECIBOS AOS CONDÔMINOS - BLOQUEAR CÉLULAS APÓS CADA PREENCHIMENTO)
A30: PLANILHA P COND (EXCEL E PDF, VERIFICAR DIVERSAS FÓRMULAS NELA) E CÓPIA DELA NO ARQUIVO "Planilha p condôm 202302 em diante" SEM FÓRMULAS
A31: PLANILHA P COND (EXCEL E PDF), APTº 201
A32: PLANILHA P COND (EXCEL E PDF), APTº 601
A33: RECIBOS (ARQ. "Recibos 202511 em diante", NA PASTA "H\Outr\Condomínio Neápolis\Condôminos recibos", EXCEL E PDF - PREENCHTº AUTOMÁTICO POR FÓRMULAS (CONFERIR), EXCETO ALGUMAS PARTES DO RECIBO DO APTº 801, A ATUALIZAR
A34: PASTA "Banco Inter e outros": BAIXAR E SALVAR EM PDF NO MÊS SEGUINTE O EXTRATO DA CONTA CORRENTE DO MÊS ANTERIOR (A EXEMPLO DO ARQUIVO "Extrato 202509", DE 13/10/2025) | B34: A PREENCHER
A35: PASTA "Banco Inter e outros": BAIXAR E SALVAR EM PDF NO MÊS SEGUINTE O EXTRATO DA CONTA CORRENTE DO PERÍODO DE 01/2025 ATÉ O MÊS ANTERIOR, SUBSTITUINDO O ARQUIVO JÁ EXISTENTE (QUE EM 13/10/2025 ERA "Extrato 202501-202509") | B35: A PREENCHER
A36: PASTA "Banco Inter e outros": BAIXAR E SALVAR EM PDF NO MÊS SEGUINTE O EXTRATO DA "POSIÇÃO DE RENDA FIXA" DO ÚLTIMO DIA DO MÊS ANTERIOR, (A EXEMPLO DO ARQUIVO "extrato-posicao-renda-fixa 20250930", DE 13/10/2025) | B36: A PREENCHER
A37: ARQ. "Extrato", NA PASTA "Banco Inter e outros": PARA O ÚLTIMO DIA DE CADA MÊS, COPIAR/COLAR LINHA DO ÚLTIMO DIA DO MÊS ANTERIOR, ATUALIZANDO OS VALORES DAS COLUNAS "SALDO ATUAL CONF. BANCO (B)" (OBTIDO VIA ARQUIVO MAIS RECENTE DO "EXTRATO DA POSIÇÃO DE RENDA FIXA") E "FUNDO DE RESERVA" (OBTIDO NA PLANILHA "VRS. DEVIDOS E OUTROS" DO ARQUIVO "PLANILHAS MENSAIS 202508 EM DIANTE RASCUNHO EM USO", TABELA "FUNDO DE RESERVA") | B37: A PREENCHER
A38: ARQ. "Extrato", NA PASTA "Banco Inter e outros": ATUALIZÁ-LO DIARIAMENTE COM ENTRADAS E SAÍDAS , CONFERIR SEMPRE COM O EXTRATO DO APLICATIVO DO BANCO INTER | B38: EM EXECUÇÃO
A41: ORIENTAÇÕES (INICIADAS EM 13/08/2025, 4ª F.; ÚLTIMA ALTERAÇÃO: 06/11/2025, 5ª F.):
A43: EM TODAS AS PLANILHAS: AO ACRESCENTAR LINHA OU COLUNA, USAR "COPIAR" LINHA OU COLUNA / "INSERIR" CÉLULAS COPIADAS, PARA QUE NÃO SEJA ALTERADO O RESULTADO DAS DIVERSAS FÓRMULAS JÁ EXISTENTES.
A45: NA PLANILHA "MEDIÇÕES E TABELAS":
A46: ATUALIZAR TABELA REFERENTE AO GÁS, SEMPRE QUE HOUVER ABASTECIMENTO.
A47: CONTA DA COPASA (NO ATO DO RECEBIMENTO): CONFERIR SE A LEITURA NELA REGISTRADA ESTÁ PRÓXIMA DA QUE CONSTA NO HIDRÔMETRO; PREENCHER DADOS DA TABELA "COPASA NFFS".
A48: PROCEDER À LEITURA DE ÁGUA E GÁS NO DIA 28 DE CADA MÊS, USANDO O ARQUIVO "ÁGUA E GÁS LEITURAS" DO ONE DRIVE.
A49: PREENCHER DADOS DA TABELA 1 ("LEITURA DOS MEDIDORES DE ÁGUA E GÁS"). QUANTO ÀS LINHAS "DIF. C/LEIT. ANT." E "% DO CONSUMO TOTAL" DE ÁGUA E "DIF. C/LEIT. ANT." DE GÁS DA TABELA 1, COPIAR/COLAR TEXTO - COPIAR/COLAR ESPECIAL (TRANSPOR) NA TABELA 2, À DIREITA DESTA. OS DADOS DESTA ÚLTIMA IRÃO ATRAVÉS DE FÓRMULA PARA A TABELA 3 ("VALORES DEVIDOS POR UNIDADE"). OS DADOS DA TABELA 3 ("VALORES DEVIDOS POR UNIDADE") IRÃO ATRAVÉS DE FÓRMULA PARA A TABELA DE MESMO NOME NA PLANILHA "PLAN P COND".
A50: PREENCHER/ATUALIZAR DEMAIS DADOS DA TABELA 2.
A51: PREENCHER/ATUALIZAR DADOS DA TABELA "RATEIOS DE COPASA E SÍNDICO", QUE ESTÁ À DIREITA DA TABELA "COPASA NFFS". OS DADOS IRÃO ATRAVÉS DE FÓRMULA PARA A TABELA DA PLANILHA "LANÇTºS".
A52: ATUALIZAR A TABELA 3 ("VALORES DEVIDOS POR UNIDADE") QUANTO À COLUNA "RATEIO" E QUANTO ÀS 5 COLUNAS EXISTENTES À DIREITA DA 2ª COLUNA INTITULADA "TOTAL A PAGAR" (OS DADOS DAS COLUNAS À ESQUERDA JÁ SÃO PREENCHIDOS POR FÓRMULAS, REFERENTES AOS DADOS DA TABELA 2).
A53: COPIAR/COLAR TEXTO (ATÉ A COLUNA REFERENTE AO APTº 802) OS NÚMEROS DA TABELA 3 ("VALORES DEVIDOS POR UNIDADE"), NA TABELA QUE ESTÁ LOGO ABAIXO DA TABELA ORIGINAL, EM CIMA DO TEXTO ANTERIOR JÁ EXISTENTE. ESSES DADOS SERÃO OBJETO DE COPIAR/COLAR ESPECIAL (TRANSPOR) PARA TABELA IDÊNTICA EXISTENTE NA PLANILHA "VRS. DEVIDOS E OUTROS".
A54: CONFERIR A ANOTAÇÃO QUE ESTÁ ACIMA DA TABELA 3 ("VALORES DEVIDOS POR UNIDADE"), CUJA FÓRMULA DEVE APRESENTAR O RESULTADO "VERDADEIRO" ("'A TABELA ABAIXO COINCIDE COM IGUAL TABELA DA PLANILHA "PLAN P COND'"), TOMANDO ANTES O CUIDADO DE VERIFICAR SE A COLUNA "RATEIO" JÁ FOI ATUALIZADA.
... A140: TABELA "VALORES DEVIDOS POR UNIDADE": COLAR/TRANSPOR DADOS DA TABELA ABAIXO DA TABELA 3 DA PLANILHA "MEDIÇÕES E TABELAS"

Sheet MEDIÇÕES E COPASA HISTÓRICO
A1: TABELA 1 | AJ1: RATEIOS DE COPASA E SÍNDICO | AP1: COPASA NFFS | BA1: XXXXX | BB1: TARIFAS DA LEITURA DE 22/07/2025 (A QUE ESTAVA INCORRETA ATÉ 27/08/25) | BK1: TARIFAS DA LEITURA DE 22/08/2025 | BS1: XXXXX | BU1: GÁS (1KG COMPRADO É IGUAL A 2,5M3 CONSUMIDOS)
A2: LEITURA DOS MEDIDORES DE ÁGUA E GÁS (DIA 28 DE CADA MÊS) | AJ2: MÊS DO LANÇTº | AK2: COPASA DO COND. A RATEAR (R$) | AL2: COPASA DO COND. A RATEAR - SÓ FÓRMULA | AM2: PARTE DO SÍNDICO A RATEAR (COPASA, GÁS E DESPESAS, EM R$) | AN2: PARTE DO SÍNDICO A RATEAR - SÓ FÓRMULA | AP2: DATAS E CONSUMO | AU2: PARTE REF. À ÁGUA (R$) | AX2: PARTE REF. AO ESGOTO (R$) | BA2: COLUNAS OCULTAS (TABELAS COM SIMULAÇÃO DAS TARIFAS DAS LEITURAS DE 22/07 E 22/08/2025 ANTES DAS CORREÇÕES QUE A COPASA FEZ) | BB2: FX. CONSUMO M3 | BC2: CONSUMO DA FX. EM M3 | BD2: VOLUME TOTAL | BE2: R$/M3 DE ÁGUA | BF2: VR. DA ÁGUA | BG2: R$/M3 DE ESGOTO | BH2: VR. DO ESGOTO | BI2: SUBTOTAL | BK2: FX. CONSUMO M3 | BL2: CONSUMO DA FX. EM M3 | BM2: VOLUME TOTAL | BN2: R$/M3 DE ÁGUA | BO2: VR. DA ÁGUA | BP2: R$/M3 DE ESGOTO | BQ2: VR. DO ESGOTO | BR2: SUBTOTAL | BS2: COLUNAS OCULTAS (TABELAS COM SIMULAÇÃO DAS TARIFAS DAS LEITURAS DE 22/07 E 22/08/2025 ANTES DAS CORREÇÕES QUE A COPASA FEZ) | BU2: DATA ABASTECTº | BV2: QUANT. (KG) | BW2: PREÇO/KG (= NF) | BX2: TOTAL (R$) | BY2: PREÇO/KG ARREDOND. | BZ2: EQUIV. KG PARA M3 | CA2: CUSTO POR M3 (R$)
A3: DATA | B3: ITEM | C3: 201 | D3: 201 GÁS PISC. | E3: 202 | F3: 301 | G3: 302 | H3: 401 | I3: 402 | J3: 501 | K3: 502 | L3: 601 | M3: 602 | N3: 701 | O3: 702 | P3: 801 | Q3: 802 | R3: TOTAL | U3: % DO CONSUMO TOTAL, PARA CÁLCULO DO VALOR DO ESGOTO A SER | V3: UNIDADE / DATA DA LEITURA | W3: 45866 | X3: 45897 | Y3: 45928 | Z3: 45958 | AA3: 45988 | AB3: 46019 | AC3: 46050 | AD3: 46081 | AE3: 46109 | AP3: LEITURA | AQ3: VENCTº | AR3: QUITAÇÃO | AS3: CONSUMO TOTAL (M3) | AT3: TOTAL DA CONTA (R$) | AU3: ABASTECTº | AV3: USO DE REC. HÍDR. | AW3: PREÇO/M3 ARREDOND. | AX3: ESG. DINÂM. COLETA E TRATº | AY3: USO DE REC. HÍDR. | AZ3: OBS. | BB3: FIXA | BF3: 316.4 | BH3: 233.94 | BI3: =BF3+BH3 -> 550.34 | BK3: FIXA | BO3: 316.4 | BQ3: 233.94 | BR3: =BO3+BQ3 -> 550.34 | BU3: 2022 | BW3: 14.276 | BY3: 14.27 | BZ3: 2.5 | CA3: =BY3*BZ3 -> 35.675
A4: 44893 | B4: ÁGUA | C4: 2234.305 | D4: 0 | E4: 5533.646 | F4: 3691.878 | G4: 1620.994 | H4: 1650.543 | I4: 3784.605 | J4: 2565.364 | K4: 2088.147 | L4: 1940.531 | M4: 1841.097 | N4: 2711.44 | O4: 841.528 | P4: 5163.824 | Q4: 3048.163 | R4: =SUM(C4:Q4)-D4 -> 38716.065 | U4: COBRADO POR | V4: CONDOM. | W4: 0 | X4: 0.025 | Y4: 0.131 | Z4: 0.204 | AA4: 0.147 | AB4: 0 | AC4: 0 | AD4: 0 | AE4: 0.08 | AJ4: XXX | AK4: XXX | AL4: XXX | AM4: XXX | AN4: XXX | AP4: 44915 | AQ4: 44972 | AR4: 44937 | AS4: 225 | AT4: =AU4+AV4+AX4+AY4 -> 2077.63 | AU4: 1190.9 | AV4: 4.75 | AW4: =ROUNDUP((AU4+AV4)/AS4,2) -> 5.32 | AX4: 881.49 | AY4: 0.49 | BB4: 0 A 5 | BC4: 1.42857 | BD4: 20 | BE4: 2.34 | BF4: =ROUND(BD4*BE4,2) -> 46.8 | BG4: 1.73 | BH4: =BD4*BG4 -> 34.6 | BI4: =BF4+BH4 -> 81.4 | BK4: 0 A 5 | BL4: 5 | BM4: 70 | BN4: 2.34 | BO4: =ROUND(BM4*BN4,2) -> 163.8 | BP4: 1.73 | BQ4: =BM4*BP4 -> 121.1 | BR4: =BO4+BQ4 -> 284.9 | BU4: 44930 | BV4: =90.43+80.67 -> 171.1 | BW4: 13.315824 | BX4: =ROUND(BV4*BW4,2) -> 2278.34 | BY4: =ROUND(BW4,2) -> 13.32 | BZ4: 2.5 | CA4: =BY4*BZ4 -> 33.3
A5: 44923 | B5: ÁGUA | C5: 2251.956 | D5: 0 | E5: 5574.727 | F5: 3711.687 | G5: 1629.279 | H5: 1664.855 | I5: 3803.942 | J5: 2576.638 | K5: 2100.981 | L5: 1946.449 | M5: 1851.446 | N5: 2718.365 | O5: 845.468 | P5: 5175.426 | Q5: 3067.475 | R5: =SUM(C5:Q5) -> 38918.694 | U5: AP (COLAR AQUI | V5: 201 | W5: 0.051 | X5: 0.074 | Y5: 0.069 | Z5: 0.068 | AA5: 0.072 | AB5: 0.082 | AC5: 0.076 | AD5: 0.084 | AE5: 0.096 | AJ5: XXX | AK5: XXX | AL5: XXX | AM5: XXX | AN5: XXX | AP5: 44944 | AQ5: 45000 | AR5: 45000 | AS5: 226 | AT5: =AU5+AV5+AX5+AY5 -> 2295.67 | AU5: 1316.08 | AV5: 5.19 | AW5: =ROUND((AU5+AV5)/AS5,2) -> 5.85 | AX5: 973.87 | AY5: 0.53 | BB5: 5 A 10 | BK5: 5 A 10 | BL5: 5 | BM5: 70 | BN5: 4.987 | BO5: =ROUND(BM5*BN5,2) -> 349.09 | BP5: 3.69 | BQ5: =BM5*BP5 -> 258.3 | BR5: =BO5+BQ5 -> 607.39 | BU5: 45098 | BV5: 300.73 | BW5: 12.741595 | BX5: =ROUND(BV5*BW5,2) -> 3831.78 | BY5: =ROUND(BW5,2) -> 12.74 | BZ5: 2.5 | CA5: =BY5*BZ5 -> 31.85
A6: 44954 | B6: ÁGUA | C6: 2272.897 | D6: 0 | E6: 5608.529 | F6: 3732.161 | G6: 1640.201 | H6: 1685.537 | I6: 3827.285 | J6: 2587.655 | K6: 2114.097 | L6: 1951.375 | M6: 1855.796 | N6: 2727.694 | O6: 850.335 | P6: 5182.372 | Q6: 3087.528 | R6: =SUM(C6:Q6) -> 39123.462 | U6: O TEXTO DA COLUNA DA TABELA 2) | V6: 201 (ESPAÇO "201 GÁS PISC." DA TABELA DE LEITURAS, ZERADO) | W6: 0 | X6: 0 | Y6: 0 | Z6: 0 | AA6: 0 | AB6: 0 | AC6: 0 | AD6: 0 | AE6: 0 | AJ6: XXX | AK6: XXX | AL6: XXX | AM6: XXX | AN6: XXX | AP6: 44972 | AQ6: 45033 | AR6: 45033 | AS6: 218 | AT6: 2287.06 | AU6: 1311.45 | AV6: 4.82 | AW6: =ROUND((AU6+AV6)/AS6,2) -> 6.04 | AX6: 970.3 | AY6: 0.49 | BB6: 10 A 15 | BK6: 10 A 15 | BL6: 5 | BM6: 70 | BN6: 7.727 | BO6: =ROUND(BM6*BN6,2) -> 540.89 | BP6: 5.718 | BQ6: =BM6*BP6 -> 400.26 | BR6: =BO6+BQ6 -> 941.15 | BU6: 45296 | BV6: 280.22 | BW6: 12,809293 | BX6: =ROUND(BV6*BW6,2) -> 3589.42 | BY6: =ROUND(BW6,2) -> 12.81 | BZ6: 2.5 | CA6: =BY6*BZ6 -> 32.025
A7: 44985 | B7: ÁGUA | C7: 2291.597 | D7: 0 | E7: 5642.302 | F7: 3753.569 | G7: 1649.999 | H7: 1703.015 | I7: 3846.37 | J7: 2599.048 | K7: 2127.744 | L7: 1956.14 | M7: 1862.272 | N7: 2739.303 | O7: 855.383 | P7: 5194.27 | Q7: 3109.158 | R7: =SUM(C7:Q7) -> 39330.17 | V7: 202 | W7: 0.105 | X7: 0.081 | Y7: 0.093 | Z7: 0.035 | AA7: 0.078 | AB7: 0.101 | AC7: 0.11 | AD7: 0.097 | AE7: 0.073 | AJ7: XXX | AK7: XXX | AL7: XXX | AM7: XXX | AN7: XXX | AP7: 45005 | AQ7: 45061 | AR7: 45061 | AS7: 271 | AT7: 3164.51 | AU7: 1815.59 | AV7: 5.04 | AW7: =ROUND((AU7+AV7)/AS7,2) -> 6.72 | AX7: 1343.37 | AY7: 0.51 | BB7: 15 A 20 | BK7: 15 A 20 | BL7: 5 | BM7: 70 | BN7: 10.549 | BO7: =ROUND(BM7*BN7,2) -> 738.43 | BP7: 7.806 | BQ7: =BM7*BP7 -> 546.42 | BR7: =BO7+BQ7 -> 1284.85 | BU7: 45477 | BV7: 271.38 | BW7: 13.550888 | BX7: =ROUND(BV7*BW7,2) -> 3677.44 | BY7: =ROUND(BW7,2) -> 13.55 | BZ7: 2.5 | CA7: =BY7*BZ7 -> 33.875
A8: 45013 | B8: ÁGUA | C8: 2309.167 | D8: 0 | E8: 5681.365 | F8: 3770.995 | G8: 1659.162 | H8: 1713.004 | I8: 3861.947 | J8: 2608.132 | K8: 2139.578 | L8: 1959.986 | M8: 1866.638 | N8: 2746.466 | O8: 860.005 | P8: 5207.21 | Q8: 3127.691 | R8: =SUM(C8:Q8) -> 39511.346 | V8: 301 | W8: 0.066 | X8: 0.076 | Y8: 0.072 | Z8: 0.063 | AA8: 0.068 | AB8: 0.086 | AC8: 0.093 | AD8: 0.086 | AE8: 0.086 | AJ8: XXX | AK8: XXX | AL8: XXX | AM8: XXX | AN8: XXX | AP8: 45034 | AQ8: 45092 | AR8: 45092 | AS8: 219 | AT8: 2304.01 | AU8: 1320.97 | AV8: 5.17 | AW8: =ROUND((AU8+AV8)/AS8,2) -> 6.06 | AX8: 977.34 | AY8: 0.53 | BB8: 20 A 40 | BK8: 20 A 40 | BL8: 20 | BM8: 280 | BN8: 13.418 | BO8: =ROUND(BM8*BN8,2) -> 3757.04 | BP8: 9.929 | BQ8: =BM8*BP8 -> 2780.12 | BR8: =BO8+BQ8 -> 6537.16 | BU8: 45645 | BV8: 300.56 | BW8: 13.889373 | BX8: =ROUND(BV8*BW8,2) -> 4174.59 | BY8: =ROUND(BW8,2) -> 13.89 | BZ8: 2.5 | CA8: =BY8*BZ8 -> 34.725
A9: 45044 | B9: ÁGUA | C9: 2323.159 | D9: 0 | E9: 5724.987 | F9: 3788.481 | G9: 1673.075 | H9: 1726.402 | I9: 3879.6 | J9: 2619.173 | K9: 2149.099 | L9: 1967.14 | M9: 1873.535 | N9: 2756.556 | O9: 864.363 | P9: 5215.245 | Q9: 3149.161 | R9: =SUM(C9:Q9) -> 39709.976 | V9: 302 | W9: 0.096 | X9: 0.1 | Y9: 0.11 | Z9: 0.114 | AA9: 0.115 | AB9: 0.109 | AC9: 0.09 | AD9: 0.07 | AE9: 0.087 | AJ9: XXX | AK9: XXX | AL9: XXX | AM9: XXX | AN9: XXX | AP9: 45064 | AQ9: 45124 | AR9: 45124 | AS9: 238 | AT9: 2618.81 | AU9: 1501.7 | AV9: 5.47 | AW9: =ROUND((AU9+AV9)/AS9,2) -> 6.33 | AX9: 1111.08 | AY9: 0.56 | BB9: 40 A 60 | BK9: 40 A 60 | BL9: 5.42857 | BM9: 76 | BN9: 16.371 | BO9: =ROUND(BM9*BN9,2) -> 1244.2 | BP9: 12.112 | BQ9: =BM9*BP9 -> 920.512 | BR9: =BO9+BQ9 -> 2164.712 | BU9: 45815 | BV9: 283.91 | BW9: 15.065302 | BX9: =ROUND(BV9*BW9,2) -> 4277.19 | BY9: =ROUND(BW9,2) -> 15.07 | BZ9: 2.5 | CA9: =BY9*BZ9 -> 37.675
A10: 45074 | B10: ÁGUA | C10: 2343.659 | D10: 0 | E10: 5772.038 | F10: 3804.161 | G10: 1681.868 | H10: 1744.873 | I10: 3895.201 | J10: 2632.161 | K10: 2161.866 | L10: 1973.59 | M10: 1881.343 | N10: 2765.982 | O10: 868.777 | P10: 5221.618 | Q10: 3160.195 | R10: =SUM(C10:Q10) -> 39907.332 | V10: 401 | W10: 0.095 | X10: 0.101 | Y10: 0.113 | Z10: 0.117 | AA10: 0.127 | AB10: 0.127 | AC10: 0.141 | AD10: 0.136 | AE10: 0.112 | AJ10: XXX | AK10: XXX | AL10: XXX | AM10: XXX | AN10: XXX | AP10: 45096 | AQ10: 45153 | AR10: 45153 | AS10: 263 | AT10: 3031.13 | AU10: 1739.5 | AV10: 4.11 | AW10: =ROUND((AU10+AV10)/AS10,2) -> 6.63 | AX10: 1287.06 | AY10: 0.46 | BB10: SOMA | BC10: =SUM(BC4:BC8) -> 1.42857 | BD10: =SUM(BD4:BD8) -> 20 | BF10: =SUM(BF3:BF8) -> 363.2 | BH10: =SUM(BH3:BH8) -> 268.54 | BI10: =SUM(BI3:BI8) -> 631.74 | BK10: SOMA | BL10: =SUM(BL4:BL9) -> 45.42857 | BM10: =SUM(BM4:BM9) -> 636 | BO10: =SUM(BO3:BO9) -> 7109.85 | BQ10: =SUM(BQ3:BQ9) -> 5260.652 | BR10: =SUM(BR3:BR9) -> 12370.502 | BU10: 46025 | BV10: 320 | BW10: 15.145313 | BX10: =ROUND(BV10*BW10,2) -> 4846.5 | BY10: =ROUND(BW10,2) -> 15.15 | BZ10: 2.5 | CA10: =BY10*BZ10 -> 37.875
A11: 45105 | B11: ÁGUA | C11: 2361.768 | D11: 0 | E11: 5827.643 | F11: 3822.973 | G11: 1695.446 | H11: 1763.177 | I11: 3911.762 | J11: 2644.027 | K11: 2174.502 | L11: 1981.599 | M11: 1899.927 | N11: 2775.917 | O11: 873.956 | P11: 5229.375 | Q11: 3177.429 | R11: =SUM(C11:Q11) -> 40139.501 | V11: 402 | W11: 0.196 | X11: 0.201 | Y11: 0.076 | Z11: 0.074 | AA11: 0.078 | AB11: 0.073 | AC11: 0.086 | AD11: 0.094 | AE11: 0.104 | AJ11: XXX | AK11: XXX | AL11: XXX | AM11: XXX | AN11: XXX | AP11: 45126 | AQ11: 45185 | AR11: 45185 | AS11: 274 | AT11: 3213.33 | AU11: 1844.13 | AV11: 4.23 | AW11: =ROUND((AU11+AV11)/AS11,2) -> 6.75 | AX11: 1364.49 | AY11: 0.48 | BB11: USO REC. HÍDR. ÁGUA | BI11: 15.61 | BK11: USO REC. HÍDR. ÁGUA | BR11: 15.28
A12: 45138 | B12: ÁGUA | C12: 2376.043 | D12: 0 | E12: 5881.028 | F12: 3839.238 | G12: 1709.97 | H12: 1780.795 | I12: 3933.364 | J12: 2655.586 | K12: 2189.083 | L12: 1992.42 | M12: 1929.111 | N12: 2786.031 | O12: 877.042 | P12: 5236.806 | Q12: 3193.116 | R12: =SUM(C12:Q12) -> 40379.633 | V12: 501 | W12: 0.053 | X12: 0.054 | Y12: 0.054 | Z12: 0.048 | AA12: 0.049 | AB12: 0.06 | AC12: 0.128 | AD12: 0.185 | AE12: 0.111 | AJ12: XXX | AK12: XXX | AL12: XXX | AM12: XXX | AN12: XXX | AP12: 45159 | AQ12: 45215 | AR12: 45215 | AS12: 261 | AT12: 2998.76 | AU12: 1720.47 | AV12: 4.77 | AW12: =ROUND((AU12+AV12)/AS12,2) -> 6.61 | AX12: 1272.98 | AY12: 0.54 | BB12: USO REC. HÍDR. ESGOTO | BI12: 3.43 | BK12: USO REC. HÍDR. ESGOTO | BR12: 3.36 | BU12: GÁS: HÁ 2 TANQUES DE 200 KG CADA. 1KG COMPRADO É IGUAL A 2,5M3 CONSUMIDOS. ESSE VALOR É CORRIGIDO A CADA ABASTECIMENTO. 2ª VARIÁVEL DA FÓRMULA (COLUNA "CONSUMO M3"): VALOR É IGUAL A 2,5 X O PREÇO UNITÁRIO DO QUILO, QUE SERÁ VERIFICADO NO ÚLTIMO ABASTECIMENTO FEITO
A13: 45166 | B13: ÁGUA | C13: 2396.08 | D13: 0 | E13: 5923.725 | F13: 3855.312 | G13: 1721.456 | H13: 1799.713 | I13: 3950.691 | J13: 2666.401 | K13: 2201.556 | L13: 2001.809 | M13: 1933.433 | N13: 2795.101 | O13: 879.561 | P13: 5244.122 | Q13: 3209.97 | R13: =SUM(C13:Q13) -> 40578.93 | V13: 502 | W13: 0.051 | X13: 0.047 | Y13: 0.051 | Z13: 0.045 | AA13: 0.047 | AB13: 0.056 | AC13: 0.069 | AD13: 0.057 | AE13: 0.059 | AJ13: XXX | AK13: XXX | AL13: XXX | AM13: XXX | AN13: XXX | AP13: 45189 | AQ13: 45245 | AR13: 45245 | AS13: 242 | AT13: =AU13+AV13+AX13+AY13 -> 2684.4 | AU13: 1539.74 | AV13: 4.87 | AW13: =ROUND((AU13+AV13)/AS13,2) -> 6.38 | AX13: 1139.24 | AY13: 0.55 | BB13: TOTAL | BI13: =BI10+BI11+BI12 -> 650.78 | BK13: TOTAL | BR13: =BR10+BR11+BR12 -> 12389.142 | BU13: GÁS DO 201: TEM UM MEDIDOR A PARTE. NO APTº A MEDIÇÃO GERALMENTE É ZERO, PORQUE TEM FOGÃO ELÉTRICO
A14: 45197 | B14: ÁGUA | C14: 2416.782 | D14: 0 | E14: 5955.074 | F14: 3872.337 | G14: 1736.355 | H14: 1818.171 | I14: 3967.667 | J14: 2678.981 | K14: 2211.822 | L14: 2017.308 | M14: 1938.571 | N14: 2804.456 | O14: 882.839 | P14: 5251.34 | Q14: 3227.372 | R14: =SUM(C14:Q14) -> 40779.075 | V14: 601 | W14: 0.013 | X14: 0.016 | Y14: 0.014 | Z14: 0.011 | AA14: 0.011 | AB14: 0.022 | AC14: 0.025 | AD14: 0.014 | AE14: 0.017 | AJ14: XXX | AK14: XXX | AL14: XXX | AM14: XXX | AN14: XXX | AP14: 45222 | AQ14: 45275 | AR14: 45275 | AS14: 239 | AT14: =AU14+AV14+AX14+AY14 -> 2634.49 | AU14: 1511.21 | AV14: 4.64 | AW14: =ROUND((AU14+AV14)/AS14,2) -> 6.34 | AX14: 1118.12 | AY14: 0.52 | BB14: LEITURA ERRADA QUE FOI FEITA EM 22/07/25: | BH14: 5021 | BI14: M3 | BK14: LEITURA ATUAL, VERIFIQUEI QUE ESTÁ CORRETA: | BQ14: 5657 | BR14: M3 | BU14: ÁGUA/ESGOTO DA LEITURA DE 20/12/22, MODELO, 3ª VARIÁVEL DA FÓRMULA (COLUNA "CONSUMO M3"): IGUAL AO ESGOTO DINÂMICO ($881,49) MAIS RECURSOS HÍDRICOS ESGOTO ($0,49), ISSO DIVIDIDO POR 15 (CONDÔMINOS + CONDOMÍNIO), TUDO NA CONTA, IGUAL A $58,798, ARREDOND. P/$58,80
A15: 45227 | B15: ÁGUA | C15: 2436.831 | D15: 0 | E15: 5972.821 | F15: 3892.028 | G15: 1750.664 | H15: 1835.107 | I15: 3987.57 | J15: 2690.956 | K15: 2223.174 | L15: 2028.352 | M15: 1943.757 | N15: 2814.368 | O15: 885.629 | P15: 5260.244 | Q15: 3243.387 | R15: =SUM(C15:Q15) -> 40964.888 | V15: 602 | W15: 0.045 | X15: 0.076 | Y15: 0.075 | Z15: 0.087 | AA15: 0.059 | AB15: 0.093 | AC15: 0.006 | AD15: 0.021 | AE15: 0.003 | AJ15: XXX | AK15: XXX | AL15: XXX | AM15: XXX | AN15: XXX | AP15: 45253 | AQ15: 45306 | AR15: 45306 | AS15: 246 | AT15: =AU15+AV15+AX15+AY15 -> 2749.91 | AU15: 1577.79 | AV15: 4.25 | AW15: =ROUND((AU15+AV15)/AS15,2) -> 6.43 | AX15: 1167.39 | AY15: 0.48 | BB15: LEITURA CORRETA DE 22/07/25: | BH15: 5362 | BI15: M3 | BK15: LEITURA ANTERIOR CORRETA: | BQ15: =BH15 -> 5362 | BR15: M3 | BU15: CONSUMO DE ÁGUA DO CONDOMÍNIO: RAZOÁVEL ENTRE 20 E 40 M3. MENOS DE 20M3 OU MAIS DE 40M3: UMA DAS 2 LEITURAS PODE ESTAR ERRADA
A16: 45258 | B16: ÁGUA | C16: 2455.727 | D16: 0 | E16: 6004.368 | F16: 3909.588 | G16: 1769.361 | H16: 1854.208 | I16: 4010.335 | J16: 2703.906 | K16: 2237.708 | L16: 2043.882 | M16: 1952.156 | N16: 2825.211 | O16: 888.719 | P16: 5262.031 | Q16: 3262.162 | R16: =SUM(C16:Q16) -> 41179.362 | V16: 701 | W16: 0.057 | X16: 0.056 | Y16: 0.061 | Z16: 0.057 | AA16: 0.064 | AB16: 0.07 | AC16: 0.059 | AD16: 0.056 | AE16: 0.059 | AJ16: XXX | AK16: XXX | AL16: XXX | AM16: XXX | AN16: XXX | AP16: 45281 | AQ16: 45337 | AR16: 45337 | AS16: 243 | AT16: =AU16+AV16+AX16+AY16 -> 2699.88 | AU16: 1549.26 | AV16: 3.9 | AW16: =ROUND((AU16+AV16)/AS16,2) -> 6.39 | AX16: 1146.28 | AY16: 0.44 | BB16: LEITURA ANTERIOR: | BH16: 5001 | BI16: M3 | BK16: CONSUMO CORRETO: | BQ16: =BQ14-BQ15 -> 295 | BR16: M3 | BU16: ANOTAR NO FINAL DA TABELA "RESUMO DOS LANÇAMENTOS (RECEITAS/DESPESAS) O SALDO DE CRÉDITO OU DÉBITO DE DIFERENÇA DE LEITURA (DIFERENÇA DE CONSUMO DE ÁGUA DO CONDOMÍNIO FORA DA PREVISÃO)
A17: 45288 | B17: ÁGUA | C17: 2474.42 | D17: 0 | E17: 6053.424 | F17: 3931.077 | G17: 1784.135 | H17: 1871.797 | I17: 4032.631 | J17: 2715.053 | K17: 2250.844 | L17: 2059.568 | M17: 1968.013 | N17: 2836.379 | O17: 891.618 | P17: 5265.855 | Q17: 3281.035 | R17: =SUM(C17:Q17) -> 41415.849 | V17: 702 | W17: 0.023 | X17: 0.026 | Y17: 0.029 | Z17: 0.027 | AA17: 0.028 | AB17: 0.031 | AC17: 0.034 | AD17: 0.026 | AE17: 0.031 | AJ17: XXX | AK17: XXX | AL17: XXX | AM17: XXX | AN17: XXX | AP17: 45313 | AQ17: 45366 | AR17: 45366 | AS17: 293 | AT17: =AU17+AV17+AX17+AY17 -> 3689.84 | AU17: 2117.99 | AV17: 4.15 | AW17: =ROUND((AU17+AV17)/AS17,2) -> 7.24 | AX17: 1567.23 | AY17: 0.47 | BB17: CONSUMO CORRETO: | BH17: =BH15-BH16 -> 361 | BI17: M3
A18: 45319 | B18: ÁGUA | C18: 2491.821 | D18: 0 | E18: 6102.368 | F18: 3953.12 | G18: 1800.569 | H18: 1885.724 | I18: 4058.137 | J18: 2726.861 | K18: 2265.914 | L18: 2075.591 | M18: 1994.272 | N18: 2850.035 | O18: 894.558 | P18: 5267.996 | Q18: 3300.08 | R18: =SUM(C18:Q18) -> 41667.046 | V18: 801 | W18: 0.02 | X18: 0.017 | Y18: 0.015 | Z18: 0.014 | AA18: 0.016 | AB18: 0.024 | AC18: 0.021 | AD18: 0.022 | AE18: 0.02 | AJ18: XXX | AK18: XXX | AL18: XXX | AM18: XXX | AN18: XXX | AP18: 45342 | AQ18: 45397 | AR18: 45397 | AS18: 251 | AT18: =AU18+AV18+AX18+AY18 -> 2951.83 | AU18: 1693.72 | AV18: 4.3 | AW18: =ROUND((AU18+AV18)/AS18,2) -> 6.77 | AX18: 1253.32 | AY18: 0.49
A19: 45350 | B19: ÁGUA | C19: 2505.809 | D19: 0 | E19: 6151.25 | F19: 3971.944 | G19: 1815.415 | H19: 1905.788 | I19: 4084.603 | J19: 2737.65 | K19: 2281.466 | L19: 2090.551 | M19: 2001.276 | N19: 2861.248 | O19: 898.348 | P19: 5268.242 | Q19: 3317.755 | R19: =SUM(C19:Q19) -> 41891.345 | V19: 802 | W19: 0.056 | X19: 0.049 | Y19: 0.037 | Z19: 0.036 | AA19: 0.041 | AB19: 0.066 | AC19: 0.062 | AD19: 0.052 | AE19: 0.062 | AJ19: XXX | AK19: XXX | AL19: XXX | AM19: XXX | AN19: XXX | AP19: 45370 | AQ19: 45427 | AR19: 45427 | AS19: 256 | AT19: =AU19+AV19+AX19+AY19 -> 3039.17 | AU19: 1743.28 | AV19: 5.3 | AW19: =ROUND((AU19+AV19)/AS19,2) -> 6.83 | AX19: 1289.99 | AY19: 0.6 | BB19: TARIFAS DA LEITURA DE 22/07/2025 APÓS SER CORRIGIDA (NÃO FOI CORRIGIDA ATÉ 27/08/25) | BK19: TARIFAS DA LEITURA DE 22/08/25 APÓS A LEITURA DE 22/07/25 SER CORRIGIDA (NÃO FOI CORRIGIDA ATÉ 27/08/25)
A20: 45379 | B20: ÁGUA | C20: 2523.908 | D20: 0 | E20: 6192.33 | F20: 3991.919 | G20: 1830.717 | H20: 1918.385 | I20: 4101.951 | J20: 2748.753 | K20: 2297.261 | L20: 2101.516 | M20: 2023.642 | N20: 2874.74 | O20: 903.365 | P20: 5269.756 | Q20: 3336.855 | R20: =SUM(C20:Q20) -> 42115.098 | V20: TOTAL | W20: =SUM(W4:W19) -> 0.927 | X20: =SUM(X4:X19) -> 0.999 | Y20: =SUM(Y4:Y19) -> 1 | Z20: =SUM(Z4:Z19) -> 1 | AA20: =SUM(AA4:AA19) -> 1 | AB20: =SUM(AB4:AB19) -> 1 | AC20: =SUM(AC4:AC19) -> 1 | AD20: =SUM(AD4:AD19) -> 1 | ... AF20: =SUM(AF4:AF19) -> 0 | AJ20: XXX | AK20: XXX | AL20: XXX | AM20: XXX | AN20: XXX | AP20: 45400 | AQ20: 45460 | AR20: 45460 | AS20: 289 | AT20: =AU20+AV20+AX20+AY20 -> 3649.9 | AU20: 2094.6 | AV20: 4.79 | AW20: =ROUND((AU20+AV20)/AS20,2) -> 7.26 | AX20: 1549.97 | AY20: 0.54 | BB20: FX. CONSUMO M3 | BC20: CONSUMO DA FX. EM M3 | BD20: VOLUME TOTAL | BE20: R$/M3 DE ÁGUA | BF20: VR. DA ÁGUA | BG20: R$/M3 DE ESGOTO | BH20: VR. DO ESGOTO | BI20: SUBTOTAL | BK20: FX. CONSUMO M3 | BL20: CONSUMO DA FX. EM M3 | BM20: VOLUME TOTAL | BN20: R$/M3 DE ÁGUA | BO20: VR. DA ÁGUA | BP20: R$/M3 DE ESGOTO | BQ20: VR. DO ESGOTO | BR20: SUBTOTAL
A21: 45411 | B21: ÁGUA | C21: 2546.976 | D21: 0 | E21: 6237.3 | F21: 4018.728 | G21: 1849.796 | H21: 1928.603 | I21: 4117.224 | J21: 2758.828 | K21: 2320.094 | L21: 2124.267 | M21: 2052.455 | N21: 2893.032 | O21: 909.32 | P21: 5269.944 | Q21: 3353.903 | R21: =SUM(C21:Q21) -> 42380.47 | V21: CONFERÊNCIA | W21: 1 | X21: 1 | Y21: 1 | Z21: 1 | AA21: 1 | AB21: 1 | AC21: 1 | AD21: 1 | AE21: 1 | AF21: 1 | AJ21: XXX | AK21: XXX | AL21: XXX | AM21: XXX | AN21: XXX | AP21: 45433 | AQ21: 45488 | AR21: 45488 | AS21: 302 | AT21: =AU21+AV21+AX21+AY21 -> 3935.17 | AU21: 2258.49 | AV21: 4.88 | AW21: =ROUND((AU21+AV21)/AS21,2) -> 7.49 | AX21: 1671.25 | AY21: 0.55 | BB21: FIXA | BF21: 316.4 | BH21: 233.94 | BI21: =BF21+BH21 -> 550.34 | BK21: FIXA | BO21: 316.4 | BQ21: 233.94 | BR21: =BO21+BQ21 -> 550.34
A22: 45441 | B22: ÁGUA | C22: 2567.926 | D22: 0 | E22: 6280.362 | F22: 4045.151 | G22: 1871.71 | H22: 1943.225 | I22: 4138.443 | J22: 2765.393 | K22: 2329.702 | L22: 2140.097 | M22: 2061.531 | N22: 2916.945 | O22: 914.484 | P22: 5274.594 | Q22: 3368.671 | R22: =SUM(C22:Q22) -> 42618.234 | V22: CONFERÊNCIA | W22: =W20-W21 -> -0.073 | X22: =X20-X21 -> -0.001 | Y22: =Y20-Y21 -> 0 | Z22: =Z20-Z21 -> 0 | AA22: =AA20-AA21 -> 0 | AB22: =AB20-AB21 -> 0 | AC22: =AC20-AC21 -> 0 | AD22: =AD20-AD21 -> 0 | ... AF22: =AF20-AF21 -> -1 | AJ22: XXX | AK22: XXX | AL22: XXX | AM22: XXX | AN22: XXX | AP22: 45463 | AQ22: 45519 | AR22: 45519 | AS22: 287 | AT22: =AU22+AV22+AX22+AY22 -> 3238.72 | AU22: 1852.3 | AV22: 12.45 | AW22: =ROUND((AU22+AV22)/AS22,2) -> 6.5 | AX22: 1370.67 | AY22: 3.3 | BB22: 0 A 5 | BC22: 5 | BD22: 70 | BE22: 2.34 | BF22: =ROUND(BD22*BE22,2) -> 163.8 | BG22: 1.73 | BH22: =BD22*BG22 -> 121.1 | BI22: =BF22+BH22 -> 284.9 | BK22: 0 A 5 | BL22: 5 | BM22: 70 | BN22: 2.34 | BO22: =ROUND(BM22*BN22,2) -> 163.8 | BP22: 1.73 | BQ22: =BM22*BP22 -> 121.1 | BR22: =BO22+BQ22 -> 284.9
A23: 45471 | B23: ÁGUA | C23: 2587.661 | D23: 0 | E23: 6316.765 | F23: 4075.057 | G23: 1898.116 | H23: 1962.961 | I23: 4159.113 | J23: 2774.914 | K23: 2342.361 | L23: 2156.088 | M23: 2065.768 | N23: 2930.577 | O23: 918.504 | P23: 5278.061 | Q23: 3382.209 | R23: =SUM(C23:Q23) -> 42848.155 | AJ23: XXX | AK23: XXX | AL23: XXX | AM23: XXX | AN23: XXX | AP23: 45495 | AQ23: 45551 | AR23: 45551 | AS23: 276 | AT23: =AU23+AV23+AX23+AY23 -> 3395.64 | AU23: 1941.5 | AV23: 13.81 | AW23: =ROUND((AU23+AV23)/AS23,2) -> 7.08 | AX23: 1436.67 | AY23: 3.66 | AZ23: CONTA ORIGINAL DE 22/07/24, C/FATURAMENTO REALIZADO PELA MÉDIA DE CONSUMO (VIDRO EMBAÇADO/SUJO) | BB23: 5 A 10 | BC23: 5 | BD23: 70 | BE23: 4.987 | BF23: =ROUND(BD23*BE23,2) -> 349.09 | BG23: 3.69 | BH23: =BD23*BG23 -> 258.3 | BI23: =BF23+BH23 -> 607.39 | BK23: 5 A 10 | BL23: 5 | BM23: 70 | BN23: 4.987 | BO23: =ROUND(BM23*BN23,2) -> 349.09 | BP23: 3.69 | BQ23: =BM23*BP23 -> 258.3 | BR23: =BO23+BQ23 -> 607.39
A24: 45501 | B24: ÁGUA | C24: 2606.608 | D24: 0 | E24: 6367.535 | F24: 4100.681 | G24: 1917.329 | H24: 1980.374 | I24: 4187.751 | J24: 2789.214 | K24: 2356.703 | L24: 2188.661 | M24: 2069.694 | N24: 2942.168 | O24: 922.149 | P24: 5281.666 | Q24: 3394.571 | R24: =SUM(C24:Q24) -> 43105.104 | AJ24: XXX | AK24: XXX | AL24: XXX | AM24: XXX | AN24: XXX | AP24: 45526 | AQ24: 45580 | AR24: 45580 | AS24: 287 | AT24: =AU24+AV24+AX24+AY24 -> 3616.11 | AU24: 2069.39 | AV24: 12.18 | AW24: =ROUND((AU24+AV24)/AS24,2) -> 7.25 | AX24: 1531.31 | AY24: 3.23 | BB24: 10 A 15 | BC24: 5 | BD24: 70 | BE24: 7.727 | BF24: =ROUND(BD24*BE24,2) -> 540.89 | BG24: 5.718 | BH24: =BD24*BG24 -> 400.26 | BI24: =BF24+BH24 -> 941.15 | BK24: 10 A 15 | BL24: 5 | BM24: 70 | BN24: 7.727 | BO24: =ROUND(BM24*BN24,2) -> 540.89 | BP24: 5.718 | BQ24: =BM24*BP24 -> 400.26 | BR24: =BO24+BQ24 -> 941.15
A25: 45532 | B25: ÁGUA | C25: 2626.524 | D25: 0 | E25: 6414.423 | F25: 4134.323 | G25: 1939.863 | H25: 1998.727 | I25: 4218.262 | J25: 2808.315 | K25: 2372.412 | L25: 2225.998 | M25: 2074.397 | N25: 2956.722 | O25: 925.675 | P25: 5288.84 | Q25: 3407.617 | R25: =SUM(C25:Q25) -> 43392.098 | AJ25: XXX | AK25: XXX | AL25: XXX | AM25: XXX | AN25: XXX | AP25: 45495 | AQ25: 45551 | AR25: 45551 | AS25: 297 | AT25: =AU25+AV25+AX25+AY25 -> 3837.53 | AU25: 2195.46 | AV25: 13.81 | AW25: =ROUND((AU25+AV25)/AS25,2) -> 7.44 | AX25: 1624.6 | AY25: 3.66 | AZ25: DIFERENÇA DE VALOR REF. À CONTA RECALCULADA EM 04/09/24 NA AGÊNCIA DA COPASA (R. TREMEDAL), POIS O FATURAMENTO DA ANTERIOR FOI REALIZADO PELA MÉDIA DE CONSUMO (VIDRO EMBAÇADO/SUJO) | BB25: 15 A 20 | BC25: 5 | BD25: 70 | BE25: 10.549 | BF25: =ROUND(BD25*BE25,2) -> 738.43 | BG25: 7.806 | BH25: =BD25*BG25 -> 546.42 | BI25: =BF25+BH25 -> 1284.85 | BK25: 15 A 20 | BL25: 5 | BM25: 70 | BN25: 10.549 | BO25: =ROUND(BM25*BN25,2) -> 738.43 | BP25: 7.806 | BQ25: =BM25*BP25 -> 546.42 | BR25: =BO25+BQ25 -> 1284.85
A26: 45563 | B26: ÁGUA | C26: 2651.145 | D26: 0 | E26: 6460.245 | F26: 4165.149 | G26: 1967.666 | H26: 2017.377 | I26: 4243.84 | J26: 2831.729 | K26: 2387.454 | L26: 2241.497 | M26: 2079.757 | N26: 2967.437 | O26: 929.334 | P26: 5295.181 | Q26: 3421.916 | R26: =SUM(C26:Q26) -> 43659.727 | AJ26: XXX | AK26: XXX | AL26: XXX | AM26: XXX | AN26: XXX | AP26: 45555 | AQ26: 45614 | AR26: 45614 | AS26: 191 | AT26: =AU26+AV26+AX26+AY26 -> 2015.8 | AU26: 1149.43 | AV26: 12.5 | AW26: =ROUND((AU26+AV26)/AS26,2) -> 6.08 | AX26: 850.56 | AY26: 3.31 | BB26: 20 A 40 | BC26: ??? | BD26: =361-280 -> 81 | BE26: 13.418 | BF26: =ROUND(BD26*BE26,2) -> 1086.86 | BG26: 9.929 | BH26: =BD26*BG26 -> 804.249 | BI26: =BF26+BH26 -> 1891.109 | BK26: 20 A 40 | BL26: ??? | BM26: 15 | BN26: 13.418 | BO26: =ROUND(BM26*BN26,2) -> 201.27 | BP26: 9.929 | BQ26: =BM26*BP26 -> 148.935 | BR26: =BO26+BQ26 -> 350.205
A27: 45593 | B27: ÁGUA | C27: 2674.494 | D27: 0 | E27: 6502.896 | F27: 4197.01 | G27: 1993.943 | H27: 2037.885 | I27: 4268.178 | J27: 2853.405 | K27: 2401.423 | L27: 2245.133 | M27: 2084.641 | N27: 2978.578 | O27: 933.19 | P27: 5300.14 | Q27: 3435.194 | R27: =SUM(C27:Q27) -> 43906.11 | AJ27: XXX | AK27: XXX | AL27: XXX | AM27: XXX | AN27: XXX | AP27: 45587 | AQ27: 45642 | AR27: 45642 | AS27: 294 | AT27: =AU27+AV27+AX27+AY27 -> 3789.21 | AU27: 2157.64 | AV27: 28.18 | AW27: =ROUND((AU27+AV27)/AS27,2) -> 7.43 | AX27: 1596.62 | AY27: 6.77 | BB27: 40 A 60 | BK27: 40 A 60
A28: 45624 | B28: ÁGUA | C28: 2694.831 | D28: 0 | E28: 6540.498 | F28: 4218.168 | G28: 2018.795 | H28: 2058.898 | I28: 4289.126 | J28: 2873.857 | K28: 2416.056 | L28: 2249.807 | M28: 2089.656 | N28: 2989.712 | O28: 936.589 | P28: 5302.492 | Q28: 3464.005 | R28: =SUM(C28:Q28) -> 44142.49 | AJ28: XXX | AK28: XXX | AL28: XXX | AM28: XXX | AN28: XXX | AP28: 45618 | AQ28: 45672 | AR28: 45672 | AS28: 274 | AT28: =AU28+AV28+AX28+AY28 -> 3366.67 | AU28: 1921.67 | AV28: 18.54 | AW28: =ROUND((AU28+AV28)/AS28,2) -> 7.08 | AX28: 1422.01 | AY28: 4.45 | BB28: SOMA | BC28: ??? | BD28: =SUM(BD22:BD27) -> 361 | BF28: =SUM(BF21:BF27) -> 3195.47 | BH28: =SUM(BH21:BH27) -> 2364.269 | BI28: =SUM(BI21:BI27) -> 5559.739 | BK28: SOMA | BL28: ??? | BM28: =SUM(BM22:BM27) -> 295 | BO28: =SUM(BO21:BO27) -> 2309.88 | BQ28: =SUM(BQ21:BQ27) -> 1708.955 | BR28: =SUM(BR21:BR27) -> 4018.835
A29: 45654 | B29: ÁGUA | C29: 2714.766 | D29: 0 | E29: 6586.864 | F29: 4237.037 | G29: 2045.323 | H29: 2081.342 | I29: 4311.653 | J29: 2888.889 | K29: 2430.452 | L29: 2256.901 | M29: 2093.591 | N29: 2999.657 | O29: 940.243 | P29: 5309.751 | Q29: 3475.724 | R29: =SUM(C29:Q29) -> 44372.193 | U29: MENSALMENTE: | AJ29: XXX | AK29: XXX | AL29: XXX | AM29: XXX | AN29: XXX | AP29: 45647 | AQ29: 45705 | AR29: 45705 | AS29: 220 | AT29: =AU29+AV29+AX29+AY29 -> 2446.4 | AU29: 1386.48 | AV29: 27.37 | AW29: =ROUND((AU29+AV29)/AS29,2) -> 6.43 | AX29: 1025.97 | AY29: 6.58 | BB29: USO REC. HÍDR. ÁGUA | BI29: ??? | BK29: USO REC. HÍDR. ÁGUA | BR29: ???
A30: 45686 | B30: ÁGUA | C30: 2733.035 | D30: 0 | E30: 6634.611 | F30: 4252.168 | G30: 2074.272 | H30: 2102.808 | I30: 4339.623 | J30: 2905.589 | K30: 2446.344 | L30: 2261.718 | M30: 2115.941 | N30: 3014.502 | O30: 945.558 | P30: 5314.469 | Q30: 3488.552 | R30: =SUM(C30:Q30) -> 44629.19 | U30: ELIMINAR DA TABELA "MEDIÇÕES E TABELAS" A 1ª COLUNA DATADA | AJ30: XXX | AK30: XXX | AL30: XXX | AM30: XXX | AN30: XXX | AP30: 45679 | AQ30: 45733 | AR30: 45733 | AS30: 292 | AT30: =AU30+AV30+AX30+AY30 -> 3908.29 | AU30: 2226.75 | AV30: 27.42 | AW30: =ROUND((AU30+AV30)/AS30,2) -> 7.72 | AX30: 1647.53 | AY30: 6.59 | BB30: USO REC. HÍDR. ESGOTO | BI30: ??? | BK30: USO REC. HÍDR. ESGOTO | BR30: ???
A31: 45716 | B31: ÁGUA | C31: 2750.222 | D31: 0 | E31: 6676.777 | F31: 4274.198 | G31: 2099.177 | H31: 2124.266 | I31: 4372.04 | J31: 2922.633 | K31: 2460.491 | L31: 2265.593 | M31: 2139.219 | N31: 3027.339 | O31: 951.566 | P31: 5317.16 | Q31: 3500.965 | R31: =SUM(C31:Q31) -> 44881.646 | U31: COPIAR A ÚLTIMA COLUNA DAQUELA TABELA PARA A PRESENTE PLANILHA | AJ31: XXX | AK31: XXX | AL31: XXX | AM31: XXX | AN31: XXX | AP31: 45708 | AQ31: 45762 | AR31: 45762 | AS31: 266 | AT31: =AU31+AV31+AX31+AY31 -> 3438.61 | AU31: 1960.92 | AV31: 21.73 | AW31: =ROUND((AU31+AV31)/AS31,2) -> 7.45 | AX31: 1450.74 | AY31: 5.22 | BB31: TOTAL | BI31: =BI28 -> 5559.739 | BK31: TOTAL | BR31: =BR28 -> 4018.835
A32: 45745 | B32: ÁGUA | C32: 2769.255 | D32: 0 | E32: 6718.496 | F32: 4292.982 | G32: 2126.985 | H32: 2142.016 | I32: 4405.98 | J32: 2937.697 | K32: 2471.101 | L32: 2269.266 | M32: 2161.24 | N32: 3039.59 | O32: 957.542 | P32: 5321.136 | Q32: 3512.612 | R32: =SUM(C32:Q32) -> 45125.898 | AJ32: XXX | AK32: XXX | AL32: XXX | AM32: XXX | AN32: XXX | AP32: 45740 | AQ32: 45792 | AR32: 45792 | AS32: 289 | AT32: =AU32+AV32+AX32+AY32 -> 3916.52 | AU32: 2229.37 | AV32: 30.45 | AW32: =ROUND((AU32+AV32)/AS32,2) -> 7.82 | AX32: 1649.38 | AY32: 7.32 | AZ32: ESTA CONTA FOI REEMITIDA EM 04/04/25 APÓS SOLICITAÇAO DE 31/03/25. A ORIGINAL DE 24/03/25 ESTAVA COM C/FATURAMENTO REALIZADO PELA MÉDIA DE CONSUMO (VIDRO EMBAÇADO/SUJO)
A33: 45775 | B33: ÁGUA | C33: 2792.975 | D33: 0 | E33: 6760.554 | F33: 4313.315 | G33: 2154.435 | H33: 2162.217 | I33: 4438.931 | J33: 2952.925 | K33: 2483.245 | L33: 2276.685 | M33: 2184.038 | N33: 3055.548 | O33: 964.436 | P33: 5327.134 | Q33: 3527.734 | R33: =SUM(C33:Q33) -> 45394.172 | AJ33: XXX | AK33: XXX | AL33: XXX | AM33: XXX | AN33: XXX | AP33: 45771 | AQ33: 45824 | AR33: 45824 | AS33: 244 | AT33: =AU33+AV33+AX33+AY33 -> 3043.18 | AU33: 1728.85 | AV33: 28.49 | AW33: =ROUND((AU33+AV33)/AS33,2) -> 7.2 | AX33: 1279 | AY33: 6.84
A34: 45805 | B34: ÁGUA | C34: 2819.356 | D34: 0 | E34: 6808.096 | F34: 4333.909 | G34: 2181.332 | H34: 2184.799 | I34: 4479.234 | J34: 2966.677 | K34: 2497.318 | L34: 2281.158 | M34: 2201.411 | N34: 3069.081 | O34: 970.584 | P34: 5331.826 | Q34: 3541.107 | R34: =SUM(C34:Q34) -> 45665.888 | AJ34: XXX | AK34: XXX | AL34: XXX | AM34: XXX | AN34: XXX | AP34: 45800 | AQ34: 45853 | AR34: 45853 | AS34: 309 | AT34: =AU34+AV34+AX34+AY34 -> 4380.41 | AU34: 2497.73 | AV34: 28 | AW34: =ROUND((AU34+AV34)/AS34,2) -> 8.17 | AX34: 1847.96 | AY34: 6.72 | AZ34: ESTA CONTA FOI REEMITIDA EM 27/05/25 APÓS SOLICITAÇAO DE MESMA DATA. A ORIGINAL DE 23/05/25 ESTAVA COM C/FATURAMENTO REALIZADO PELA MÉDIA DE CONSUMO (VIDRO EMBAÇADO/SUJO)
A35: 45836 | B35: ÁGUA | C35: 2845.108 | D35: 0 | E35: 6853.487 | F35: 4352.74 | G35: 2209.487 | H35: 2209.08 | I35: 4542.657 | J35: 2982.973 | K35: 2511.29 | L35: 2286.864 | M35: 2220.498 | N35: 3084.382 | O35: 976.98 | P35: 5335.117 | Q35: 3551.921 | R35: =SUM(C35:Q35) -> 45962.584 | AJ35: XXX | AK35: XXX | AL35: XXX | AM35: XXX | AN35: XXX | AP35: 45832 | AQ35: 45887 | AR35: 45887 | AS35: 288 | AT35: =AU35+AV35+AX35+AY35 -> 3870.33 | AU35: 2215.95 | AV35: 12.24 | AW35: =ROUND((AU35+AV35)/AS35,2) -> 7.74 | AX35: 1639.45 | AY35: 2.69 | AZ35: O CONSUMO TOTAL EM M3 E O VALOR DO ESGOTO DESTA CONTA FORAM TAMBÉM USADOS PARA O FIM DO RATEIO REFERENTE A 08/2025. O TOTAL DA LEITURA DE 24/06/25 FOI USADO (E DEPOIS ZERADO) PARA A APURAÇÃO DO CONSUMO DO CONDOMÍNIO DA REFERÊNCIA 08/2025, UMA VEZ QUE A LEITURA NA CONTA DA COPASA (DE 22/07/25) ESTÁ INCORRETA (PARA MENOR!!!), E QUE NÃO FOI ATENDIDA ATÉ O DIA 08/08/25 MINHA SOLICITAÇÃO DE CORREÇÃO DA LEITURA JUNTO À COPASA.
A36: 45866 | B36: ÁGUA | C36: 2859.658 | D36: 0 | E36: 6883.806 | F36: 4371.664 | G36: 2237.09 | H36: 2236.475 | I36: 4599.043 | J36: 2998.207 | K36: 2526.018 | L36: 2290.725 | M36: 2233.459 | N36: 3100.83 | O36: 983.732 | P36: 5340.984 | Q36: 3567.961 | R36: =SUM(C36:Q36) -> 46229.652 | AJ36: XXX | AK36: XXX | AL36: XXX | AM36: XXX | AN36: XXX | AP36: 45860 | AQ36: 45915 | AR36: CTª SUBSTITUÍDA | AS36: 20 | AT36: =AU36+AV36+AX36+AY36 -> 650.78 | AU36: 363.2 | AV36: 15.61 | AW36: =ROUND((AU36+AV36)/AS36,2) -> 18.94 | AX36: 268.54 | AY36: 3.43 | AZ36: ESTA CONTA FOI REEMITIDA EM XX/XX/25 APÓS SOLICITAÇAO DE MESMA DATA. A ORIGINAL DE 22/07/25 ESTAVA COM C/ERRO DE LEITURA, TALVEZ PELO VIDRO ESTAR EMBAÇADO (PEDI NA AGÊNCIA DA COPASA NA R. CURITIBA, +-1135, CORREÇÃO DA LEITURA E SUBSTITUIÇÃO DO VIDRO DO HIDRÔMETRO, QUE ESTÁ DIFICULTANDO A LEITURA)
A37: 45897 | B37: ÁGUA | C37: 2881.573 | D37: 0 | E37: 6907.842 | F37: 4394.079 | G37: 2266.687 | H37: 2266.206 | I37: 4658.325 | J37: 3014.01 | K37: 2539.95 | L37: 2295.441 | M37: 2255.938 | N37: 3117.38 | O37: 991.377 | P37: 5346.02 | Q37: 3582.467 | R37: =SUM(C37:Q37) -> 46517.295 | AJ37: =[1]LANÇTºS!R27 -> 45901 | AK37: 102.13 | AM37: 570.56 | AP37: 45891 | AQ37: 45945 | AR37: CTª SUBSTITUÍDA | AS37: =BM28 -> 295 | AT37: =AU37+AV37+AX37+AY37 -> 4018.835 | AU37: =BO28 -> 2309.88 | AV37: 0 | AW37: =ROUND((AU37+AV37)/AS37,2) -> 7.83 | AX37: =BQ28 -> 1708.955 | AY37: 0 | AZ37: OS DADOS AQUI LANÇADOS SÃO HIPOTÉTICOS, POIS ESTA CONTA ESTÁ SENDO POR MIM QUESTIONADA, CONFORME TABELAS À DIREITA, EM VISTA DE NÃO TER SIDO AINDA CORRIGIDA A CONTA ANTERIOR
A38: 45928 | B38: ÁGUA | C38: 2901.993 | D38: 0 | E38: 6935.39 | F38: 4415.237 | G38: 2299.257 | H38: 2299.648 | I38: 4680.888 | J38: 3029.976 | K38: 2555.083 | L38: 2299.55 | M38: 2277.98 | N38: 3135.365 | O38: 999.908 | P38: 5350.331 | Q38: 3593.277 | R38: =SUM(C38:Q38) -> 46773.883 | AJ38: XXX | AK38: XXX | AL38: XXX | AM38: XXX | AN38: XXX | AP38: 45860 | AQ38: 45915 | AR38: 45912 | AS38: 311 | AT38: =AU38+AV38+AX38+AY38 -> 4411.43 | AU38: 2524.57 | AV38: 15.61 | AW38: =ROUND((AU38+AV38)/AS38,2) -> 8.17 | AX38: 1867.82 | AY38: 3.43 | AZ38: NOVA CONTA OBTIDA EM 02/09/25, SUBSTITUINDO A ANTERIOR, QUE TINHA ERRO DE LEITURA (NÃO FOI USADA P/CALCULAR RATEIOS)
A39: 45958 | B39: ÁGUA | C39: 2922.166 | D39: 0 | E39: 6945.799 | F39: 4433.945 | G39: 2332.998 | H39: 2334.054 | I39: 4702.757 | J39: 3044.133 | K39: 2568.217 | L39: 2302.894 | M39: 2303.538 | N39: 3152.257 | O39: 1007.78 | P39: 5354.332 | Q39: 3603.907 | R39: =SUM(C39:Q39) -> 47008.777 | U39: MENSALMENTE: | AJ39: XXX | AK39: XXX | AL39: XXX | AM39: XXX | AN39: XXX | AP39: 45891 | AQ39: 45945 | AR39: 45945 | AS39: 345 | AT39: =AU39+AV39+AX39+AY39 -> 5204.82 | AU39: 2980.78 | AV39: 15.28 | AW39: =ROUND((AU39+AV39)/AS39,2) -> 8.68 | AX39: 2205.4 | AY39: 3.36 | AZ39: NOVA CONTA OBTIDA EM 02/09/25, SUBSTITUINDO A ANTERIOR, QUE TINHA ERRO DE LEITURA (NÃO FOI USADA P/CALCULAR RATEIOS)
A40: 45988 | B40: ÁGUA | C40: 2943.512 | D40: 0 | E40: 6968.752 | F40: 4454.109 | G40: 2367.015 | H40: 2371.531 | I40: 4725.655 | J40: 3058.525 | K40: 2582.062 | L40: 2306.115 | M40: 2320.802 | N40: 3171.152 | O40: 1015.935 | P40: 5359.148 | Q40: 3615.872 | R40: =SUM(C40:Q40) -> 47260.185 | U40: ELIMINAR DA TABELA "MEDIÇÕES E TABELAS" A 1ª LINHA DE ÁGUA E A 1ª DE GÁS | AJ40: 45931 | AK40: 348.46 | AM40: 478.07 | AP40: 45923 | AQ40: 45978 | AR40: 45978 | AS40: 274 | AT40: =AU40+AV40+AX40+AY40 -> 3715.89 | AU40: 2045.31 | AV40: 1.1 | AW40: =ROUND((AU40+AV40)/AS40,2) -> 7.47 | AX40: 1669.24 | AY40: 0.24 | AZ40: NOVA CONTA OBTIDA EM 02/09/25, SUBSTITUINDO A ANTERIOR, QUE TINHA ERRO DE LEITURA (NÃO FOI USADA P/CALCULAR RATEIOS)
A41: 46019 | B41: ÁGUA | C41: 2965.83 | D41: 0 | E41: 6996.308 | F41: 4477.698 | G41: 2396.634 | H41: 2406.015 | I41: 4745.622 | J41: 3074.752 | K41: 2597.378 | L41: 2312.217 | M41: 2346.024 | N41: 3190.299 | O41: 1024.254 | P41: 5365.727 | Q41: 3633.833 | R41: =SUM(C41:Q41) -> 47532.591 | U41: COPIAR A ÚLTIMA LINHA DE CADA ITEM DAQUELA TABELA PARA A PRESENTE PLANILHA | AJ41: 45962 | AK41: 351.47 | AM41: 435.18 | AP41: 45954 | AQ41: 46006 | AR41: 46006 | AS41: 247 | AT41: =AU41+AV41+AX41+AY41 -> 3062.91 | AU41: 1760.49 | AV41: 0 | AW41: =ROUND((AU41+AV41)/AS41,2) -> 7.13 | AX41: 1302.42 | AY41: 0 | AZ41: NOVA CONTA OBTIDA EM 02/10/25, SUBSTITUINDO A ANTERIOR, QUE TINHA ERRO DE LEITURA
A42: 46050 | B42: ÁGUA | C42: 2983.276 | D42: 0 | E42: 7021.616 | F42: 4499.176 | G42: 2417.275 | H42: 2438.385 | I42: 4765.244 | J42: 3103.937 | K42: 2613.08 | L42: 2317.832 | M42: 2347.365 | N42: 3203.754 | O42: 1031.989 | P42: 5370.498 | Q42: 3647.977 | R42: =SUM(C42:Q42) -> 47761.404
A43: 46081 | B43: ÁGUA | C43: 3004.288 | D43: 0 | E43: 7046.072 | F43: 4520.851 | G43: 2434.714 | H43: 2472.444 | I43: 4788.671 | J43: 3150.294 | K43: 2627.243 | L43: 2321.426 | M43: 2352.726 | N43: 3217.678 | O43: 1038.48 | P43: 5375.905 | Q43: 3660.88 | R43: =SUM(C43:Q43) -> 48011.672
A44: 46109 | B44: ÁGUA | C44: 3026.174 | D44: 0 | E44: 7062.835 | F44: 4540.61 | G44: 2454.702 | H44: 2498.003 | I44: 4812.448 | J44: 3175.715 | K44: 2640.684 | L44: 2325.405 | M44: 2353.408 | N44: 3231.136 | O44: 1045.67 | P44: 5380.436 | Q44: 3674.989 | R44: =SUM(C44:Q44) -> 48222.215 | AJ44: 45992 | AK44: 346.4 | AM44: 490.06 | AP44: 45987 | AQ44: 46037 | AR44: 46036 | AS44: 269 | AT44: =AU44+AV44+AX44+AY44 -> 3466.72 | AU44: 1992.57 | AV44: 0 | AW44: =ROUND((AU44+AV44)/AS44,2) -> 7.41 | AX44: 1474.15 | AY44: 0
AJ45: 46023 | AK45: 0 | AM45: 526.58 | AP45: 46020 | AQ45: 46069 | AR45: 46071 | AS45: 189 | AT45: =AU45+AV45+AX45+AY45 -> 2101.43 | AU45: 1207.91 | AV45: 0 | AW45: =ROUND((AU45+AV45)/AS45,2) -> 6.39 | AX45: 893.52 | AY45: 0
A46: 44893 | B46: GÁS | C46: 247.339 | D46: 23.805 | E46: 824.588 | F46: 531.463 | G46: 318.205 | H46: 285.273 | I46: 661.158 | J46: 346.037 | K46: 251.363 | L46: 379.531 | M46: 311.731 | N46: 577.235 | O46: 340.323 | P46: 303.424 | Q46: 317.991 | R46: =SUM(C46:Q46) -> 5719.466 | AJ46: 46054 | AK46: 0 | AM46: 463.48 | AP46: 46050 | AQ46: 46096 | AR46: 46099 | AS46: 83 | AT46: =AU46+AV46+AX46+AY46 -> 997.74 | AU46: 582.15 | AV46: 0 | AW46: =ROUND((AU46+AV46)/AS46,2) -> 7.01 | AX46: 415.59 | AY46: 0
A47: 44923 | B47: GÁS | C47: 247.339 | D47: 23.805 | E47: 828.853 | F47: 535.009 | G47: 319.314 | H47: 287.213 | I47: 664.817 | J47: 346.647 | K47: 252.518 | L47: 379.697 | M47: 313.772 | N47: 577.852 | O47: 341.881 | P47: 305.184 | Q47: 319.557 | R47: =SUM(C47:Q47) -> 5743.458 | AJ47: 46082 | AK47: 0 | AM47: 454.67 | AP47: 46078 | AQ47: 46127 | AS47: 76 | AT47: =AU47+AV47+AX47+AY47 -> 1010.35 | AU47: 581.08 | AV47: 0 | AW47: =ROUND((AU47+AV47)/AS47,2) -> 7.65 | AX47: 429.27 | AY47: 0
A48: 44954 | B48: GÁS | C48: 247.339 | D48: 24.419 | E48: 832.811 | F48: 539.418 | G48: 320.837 | H48: 289.177 | I48: 669.715 | J48: 347.393 | K48: 253.962 | L48: 379.833 | M48: 315.998 | N48: 578.602 | O48: 343.826 | P48: 306.23 | Q48: 322.381 | R48: =SUM(C48:Q48) -> 5771.941 | AJ48: 46113 | AK48: 236.41 | AM48: 564.68 | AP48: 46097 | AQ48: 46157 | AS48: 229 | AT48: =AU48+AV48+AX48+AY48 -> 2943.7 | AU48: 1692.15 | AV48: 0 | AW48: =ROUND((AU48+AV48)/AS48,2) -> 7.39 | AX48: 1251.55 | AY48: 0
A49: 44985 | B49: GÁS | C49: 247.339 | D49: 24.419 | E49: 836.993 | F49: 543.049 | G49: 321.694 | H49: 291.036 | I49: 674.319 | J49: 348.979 | K49: 255.719 | L49: 380.011 | M49: 318.908 | N49: 579.47 | O49: 345.926 | P49: 308.318 | Q49: 325.341 | R49: =SUM(C49:Q49) -> 5801.521
A50: 45013 | B50: GÁS | C50: 247.339 | D50: 24.419 | E50: 840.618 | F50: 546.171 | G50: 322.906 | H50: 292.561 | I50: 678.781 | J50: 349.906 | K50: 256.668 | L50: 380.252 | M50: 320.888 | N50: 580.091 | O50: 347.857 | P50: 310.807 | Q50: 327.758 | R50: =SUM(C50:Q50) -> 5827.022
A51: 45044 | B51: GÁS | C51: 247.339 | D51: 24.435 | E51: 844.359 | F51: 549.4 | G51: 324.815 | H51: 294.219 | I51: 683.401 | J51: 351.016 | K51: 257.655 | L51: 380.78 | M51: 323.324 | N51: 581.129 | O51: 349.495 | P51: 312.571 | Q51: 330.217 | R51: =SUM(C51:Q51) -> 5854.155
A52: 45074 | B52: GÁS | C52: 247.339 | D52: 24.435 | E52: 848.575 | F52: 552.61 | G52: 326.086 | H52: 296.155 | I52: 687.646 | J52: 351.942 | K52: 259.133 | L52: 381.056 | M52: 326.117 | N52: 581.8 | O52: 351.036 | P52: 314.401 | Q52: 331.701 | R52: =SUM(C52:Q52) -> 5880.032
A53: 45105 | B53: GÁS | C53: 247.339 | D53: 24.484 | E53: 852.755 | F53: 556.733 | G53: 328.812 | H53: 299.19 | I53: 692.105 | J53: 352.987 | K53: 260.97 | L53: 381.232 | M53: 328.744 | N53: 582.736 | O53: 353.015 | P53: 316.605 | Q53: 333.73 | R53: =SUM(C53:Q53) -> 5911.437
A54: 45138 | B54: GÁS | C54: 247.339 | D54: 24.503 | E54: 857.902 | F54: 559.94 | G54: 331.541 | H54: 301.637 | I54: 698.416 | J54: 354.382 | K54: 262.633 | L54: 381.39 | M54: 331.435 | N54: 583.631 | O54: 353.935 | P54: 319.376 | Q54: 335.808 | R54: =SUM(C54:Q54) -> 5943.868
A55: 45166 | B55: GÁS | C55: 247.339 | D55: 24.868 | E55: 862.402 | F55: 563.537 | G55: 334.194 | H55: 303.754 | I55: 702.73 | J55: 355.473 | K55: 263.891 | L55: 381.505 | M55: 333.376 | N55: 584.359 | O55: 354.554 | P55: 321.591 | Q55: 338.289 | R55: =SUM(C55:Q55) -> 5971.862
A56: 45197 | B56: GÁS | C56: 247.339 | D56: 25.025 | E56: 865.573 | F56: 566.635 | G56: 336.349 | H56: 305.934 | I56: 707.568 | J56: 356.646 | K56: 264.995 | L56: 381.593 | M56: 335.561 | N56: 585.022 | O56: 355.426 | P56: 323.705 | Q56: 340.05 | R56: =SUM(C56:Q56) -> 5997.421 | AJ56: MENSALMENTE: | AQ56: MENSALMENTE:
A57: 45227 | B57: GÁS | C57: 247.339 | D57: 25.538 | E57: 868.009 | F57: 569.681 | G57: 338.197 | H57: 307.801 | I57: 711.59 | J57: 357.572 | K57: 266.108 | L57: 381.687 | M57: 338.057 | N57: 585.748 | O57: 356.362 | P57: 325.837 | Q57: 341.51 | R57: =SUM(C57:Q57) -> 6021.036 | AJ57: ELIMINAR DA TABELA "MEDIÇÕES E TABELAS" A 1ª LINHA | AQ57: ELIMINAR DA TABELA "MEDIÇÕES E TABELAS" A 1ª LINHA | AX57: (31/10/25)
A58: 45258 | B58: GÁS | C58: 247.339 | D58: 25.831 | E58: 871.482 | F58: 572.163 | G58: 340.27 | H58: 309.423 | I58: 715.652 | J58: 358.455 | K58: 267.589 | L58: 381.884 | M58: 340.949 | N58: 586.518 | O58: 357.429 | P58: 325.969 | Q58: 343.476 | R58: =SUM(C58:Q58) -> 6044.429 | AJ58: COPIAR A ÚLTIMA LINHA DAQUELA TABELA PARA A PRESENTE PLANILHA | AQ58: COPIAR A ÚLTIMA LINHA DAQUELA TABELA PARA A PRESENTE PLANILHA | AX58: (31/10/25)
A59: 45288 | B59: GÁS | C59: 247.339 | D59: 26.256 | E59: 876.627 | F59: 575.789 | G59: 341.936 | H59: 311.234 | I59: 719.762 | J59: 359.347 | K59: 269.173 | L59: 381.967 | M59: 343.148 | N59: 587.145 | O59: 358.256 | P59: 325.969 | Q59: 345.967 | R59: =SUM(C59:Q59) -> 6069.915
A60: 45319 | B60: GÁS | C60: 247.339 | D60: 26.286 | E60: 881.686 | F60: 579.125 | G60: 345.594 | H60: 313.236 | I60: 724.611 | J60: 360.297 | K60: 270.849 | L60: 382.106 | M60: 345.145 | N60: 588.263 | O60: 359.26 | P60: 325.969 | Q60: 348.168 | R60: =SUM(C60:Q60) -> 6097.934
A61: 45350 | B61: GÁS | C61: 247.339 | D61: 26.342 | E61: 886.31 | F61: 581.931 | G61: 348.229 | H61: 315.833 | I61: 728.95 | J61: 361.081 | K61: 272.558 | L61: 382.319 | M61: 347.763 | N61: 588.964 | O61: 360.611 | P61: 325.969 | Q61: 351.141 | R61: =SUM(C61:Q61) -> 6125.34
A62: 45379 | B62: GÁS | C62: 247.339 | D62: 26.437 | E62: 890.559 | F62: 584.344 | G62: 351.047 | H62: 317.621 | I62: 731.687 | J62: 361.713 | K62: 273.87 | L62: 382.825 | M62: 349.775 | N62: 589.711 | O62: 362.921 | P62: 325.969 | Q62: 353.715 | R62: =SUM(C62:Q62) -> 6149.533
A63: 45411 | B63: GÁS | C63: 247.339 | D63: 26.489 | E63: 895.181 | F63: 587.563 | G63: 352.877 | H63: 319.707 | I63: 734.815 | J63: 362.421 | K63: 275.615 | L63: 383.313 | M63: 352.122 | N63: 590.42 | O63: 364.954 | P63: 325.969 | Q63: 356.147 | R63: =SUM(C63:Q63) -> 6174.932
A64: 45441 | B64: GÁS | C64: 247.339 | D64: 26.581 | E64: 899.352 | F64: 590.111 | G64: 354.884 | H64: 321.046 | I64: 739.02 | J64: 362.609 | K64: 276.428 | L64: 383.686 | M64: 354.074 | N64: 590.99 | O64: 367.18 | P64: 325.969 | Q64: 357.912 | R64: =SUM(C64:Q64) -> 6197.181
A65: 45471 | B65: GÁS | C65: 247.339 | D65: 26.617 | E65: 902.724 | F65: 593.347 | G65: 356.44 | H65: 323.034 | I65: 742.841 | J65: 363.137 | K65: 277.934 | L65: 384.475 | M65: 355.991 | N65: 591.572 | O65: 368.626 | P65: 325.969 | Q65: 359.887 | R65: =SUM(C65:Q65) -> 6219.933
A66: 45501 | B66: GÁS | C66: 247.339 | D66: 26.648 | E66: 908.485 | F66: 596.267 | G66: 358.669 | H66: 325.189 | I66: 747.182 | J66: 364.036 | K66: 279.952 | L66: 385.193 | M66: 358.344 | N66: 592.173 | O66: 370.003 | P66: 325.969 | Q66: 361.526 | R66: =SUM(C66:Q66) -> 6246.975
A67: 45532 | B67: GÁS | C67: 247.339 | D67: 26.673 | E67: 914.935 | F67: 599.395 | G67: 361.064 | H67: 327.479 | I67: 752.224 | J67: 365.203 | K67: 281.808 | L67: 385.551 | M67: 361.465 | N67: 592.835 | O67: 371.71 | P67: 326.166 | Q67: 362.695 | R67: =SUM(C67:Q67) -> 6276.542
A68: 45563 | B68: GÁS | C68: 247.339 | D68: 26.749 | E68: 919.097 | F68: 602.202 | G68: 363.211 | H68: 329.188 | I68: 756.279 | J68: 366.286 | K68: 283.307 | L68: 385.996 | M68: 364.213 | N68: 593.433 | O68: 373.719 | P68: 326.567 | Q68: 364.136 | R68: =SUM(C68:Q68) -> 6301.722
A69: 45593 | B69: GÁS | C69: 247.339 | D69: 26.838 | E69: 922.079 | F69: 604.774 | G69: 365.826 | H69: 331.45 | I69: 760.143 | J69: 367.489 | K69: 284.486 | L69: 386.3 | M69: 366.923 | N69: 594.333 | O69: 374.996 | P69: 326.577 | Q69: 365.382 | R69: =SUM(C69:Q69) -> 6324.935
A70: 45624 | B70: GÁS | C70: 247.339 | D70: 26.88 | E70: 924.482 | F70: 608.003 | G70: 368.221 | H70: 333.415 | I70: 764.384 | J70: 368.486 | K70: 285.899 | L70: 387.104 | M70: 369.181 | N70: 595.227 | O70: 376.696 | P70: 326.577 | Q70: 367.225 | R70: =SUM(C70:Q70) -> 6349.119
... A86: 46109 | B86: GÁS | C86: 247.339 | D86: 27.376 | E86: 989.347 | F86: 658.665 | G86: 402.255 | H86: 359.326 | I86: 837.636 | J86: 385.871 | K86: 307.803 | L86: 395.883 | M86: 394.264 | N86: 607.169 | O86: 434.643 | P86: 328.112 | Q86: 395.253 | R86: =SUM(C86:Q86) -> 6770.942

Sheet MEDIÇÕES E TABELAS
A1: TABELA 1 | D1: (FORAM BLOQUEADAS DIVERSAS CÉLULAS DESTA PLANILHA A PARTIR DE 30/01/26) | M1: (TABELAS 1 E 2 E AS DEMAIS À DIREITA DELAS) | T1: LANÇAMENTOS - ABRIL/2026 | X1: MANTER E ATUALIZAR ESTE TÍTULO, POIS É OBJETO DE FÓRMULA NA PLANILHA "PLAN P COND" | AP1: RATEIOS DE COPASA E SÍNDICO | AV1: COPASA NFFS | BG1: XXXXX | BH1: TARIFAS DA LEITURA DE 22/07/2025 (A QUE ESTAVA INCORRETA ATÉ 27/08/25) | BQ1: TARIFAS DA LEITURA DE 22/08/2025 | BY1: XXXXX | CA1: GÁS (1KG COMPRADO É IGUAL A 2,5M3 CONSUMIDOS)
A2: LEITURA DOS MEDIDORES DE ÁGUA E GÁS (DIA 28 DE CADA MÊS) | T2: TABELA 2 | U2: ÁGUA/ESGOTO, CÁLCULO | Y2: GÁS, CÁLCULO | AP2: MÊS DO LANÇTº | AQ2: COPASA DO COND. A RATEAR (R$) | AR2: COPASA DO COND. A RATEAR - SÓ FÓRMULA | AS2: PARTE DO SÍNDICO A RATEAR (COPASA, GÁS E DESPESAS, EM R$) | AT2: PARTE DO SÍNDICO A RATEAR - SÓ FÓRMULA | AV2: DATAS E CONSUMO | BA2: PARTE REF. À ÁGUA (R$) | BD2: PARTE REF. AO ESGOTO (R$) | BG2: COLUNAS OCULTAS (TABELAS COM SIMULAÇÃO DAS TARIFAS DAS LEITURAS DE 22/07 E 22/08/2025 ANTES DAS CORREÇÕES QUE A COPASA FEZ) | BH2: FX. CONSUMO M3 | BI2: CONSUMO DA FX. EM M3 | BJ2: VOLUME TOTAL | BK2: R$/M3 DE ÁGUA | BL2: VR. DA ÁGUA | BM2: R$/M3 DE ESGOTO | BN2: VR. DO ESGOTO | BO2: SUBTOTAL | BQ2: FX. CONSUMO M3 | BR2: CONSUMO DA FX. EM M3 | BS2: VOLUME TOTAL | BT2: R$/M3 DE ÁGUA | BU2: VR. DA ÁGUA | BV2: R$/M3 DE ESGOTO | BW2: VR. DO ESGOTO | BX2: SUBTOTAL | BY2: COLUNAS OCULTAS (TABELAS COM SIMULAÇÃO DAS TARIFAS DAS LEITURAS DE 22/07 E 22/08/2025 ANTES DAS CORREÇÕES QUE A COPASA FEZ) | CA2: DATA ABASTECTº | CB2: QUANT. (KG) | CC2: PREÇO/KG (= NF) | CD2: TOTAL (R$) | CE2: PREÇO/KG ARREDOND. | CF2: EQUIV. KG PARA M3 | CG2: CUSTO POR M3 (R$)
A3: DATA | B3: ITEM | C3: 201 | D3: 201 GÁS PISC. | E3: 202 | F3: 301 | G3: 302 | H3: 401 | I3: 402 | J3: 501 | K3: 502 | L3: 601 | M3: 602 | N3: 701 | O3: 702 | P3: 801 | Q3: 802 | R3: TOTAL | T3: UNIDADE / ITEM | U3: CONSUMO (NÃO USAR) | V3: % DO CONSUMO TOTAL, PARA CÁLCULO DO VALOR DO ESGOTO A SER COBRADO POR AP | W3: CONSUMO (USAR) | X3: VALOR ÁGUA/ESGOTO (USAR) | Y3: CONSUMO (NÃO USAR) | Z3: CONSUMO (USAR) | AA3: VALOR (USAR) | AC3: % DO CONSUMO TOTAL, PARA CÁLCULO DO VALOR DO ESGOTO A SER | AD3: UNIDADE / DATA DA LEITURA | AE3: 46019 | AF3: 46050 | AG3: 46081 | AH3: 46109 | AV3: LEITURA | AW3: VENCTº | AX3: QUITAÇÃO | AY3: CONSUMO TOTAL (M3) | AZ3: TOTAL DA CONTA (R$) | BA3: ABASTECTº | BB3: USO DE REC. HÍDR. | BC3: PREÇO/M3 ARREDOND. | BD3: ESG. DINÂM. COLETA E TRATº | BE3: USO DE REC. HÍDR. | BF3: OBS. | BH3: FIXA | BL3: 316.4 | BN3: 233.94 | BO3: =BL3+BN3 -> 550.34 | BQ3: FIXA | BU3: 316.4 | BW3: 233.94 | BX3: =BU3+BW3 -> 550.34 | CA3: 2022 | CC3: 14.276 | CE3: 14.27 | CF3: 2.5 | CG3: =CE3*CF3 -> 35.675
A4: 45044 | B4: ÁGUA | C4: 2323.159 | D4: 0 | E4: 5724.987 | F4: 3788.481 | G4: 1673.075 | H4: 1726.402 | I4: 3879.6 | J4: 2619.173 | K4: 2149.099 | L4: 1967.14 | M4: 1873.535 | N4: 2756.556 | O4: 864.363 | P4: 5215.245 | Q4: 3149.161 | R4: =SUM(C4:Q4) -> 39709.976 | T4: CONDOM. | U4: =AY43-SUM(U5:U19) -> 18.457 | V4: =1-SUM(V5:V19) -> 0.08 | W4: =ROUND(U4,3) -> 18.457 | X4: =IF(W4>0,ROUND(AZ43-SUM(X5:X19),2),0) -> 236.41 | Y4: 0 | Z4: =ROUND(Y4,3) -> 0 | AA4: 0 | AC4: COBRADO POR | AD4: CONDOM. | AE4: 0 | AF4: 0 | AG4: 0 | AH4: 0.08 | AP4: XXX | AQ4: XXX | AR4: XXX | AS4: XXX | AT4: XXX | AV4: 45005 | AW4: 45061 | AX4: 45061 | AY4: 271 | AZ4: 3164.51 | BA4: 1815.59 | BB4: 5.04 | BC4: =ROUND((BA4+BB4)/AY4,2) -> 6.72 | BD4: 1343.37 | BE4: 0.51 | BH4: 0 A 5 | BI4: 1.42857 | BJ4: 20 | BK4: 2.34 | BL4: =ROUND(BJ4*BK4,2) -> 46.8 | BM4: 1.73 | BN4: =BJ4*BM4 -> 34.6 | BO4: =BL4+BN4 -> 81.4 | BQ4: 0 A 5 | BR4: 5 | BS4: 70 | BT4: 2.34 | BU4: =ROUND(BS4*BT4,2) -> 163.8 | BV4: 1.73 | BW4: =BS4*BV4 -> 121.1 | BX4: =BU4+BW4 -> 284.9 | CA4: 44930 | CB4: =90.43+80.67 -> 171.1 | CC4: 13.315824 | CD4: =ROUND(CB4*CC4,2) -> 2278.34 | CE4: =ROUND(CC4,2) -> 13.32 | CF4: 2.5 | CG4: =CE4*CF4 -> 33.3
A5: 45074 | B5: ÁGUA | C5: 2343.659 | D5: 0 | E5: 5772.038 | F5: 3804.161 | G5: 1681.868 | H5: 1744.873 | I5: 3895.201 | J5: 2632.161 | K5: 2161.866 | L5: 1973.59 | M5: 1881.343 | N5: 2765.982 | O5: 868.777 | P5: 5221.618 | Q5: 3160.195 | R5: =SUM(C5:Q5) -> 39907.332 | T5: 201 | U5: =C40 -> 21.886 | V5: =C41 -> 0.096 | W5: =ROUND(U5,3) -> 21.886 | X5: =ROUNDDOWN(W5*$BC$43+($BD$43+$BE$43)*V5,2) -> 281.88 | Y5: =C82 -> 0 | Z5: =ROUND(Y5,3) -> 0 | AA5: =ROUND((Z5+Z6)*$CG$9,2) -> 0 | AC5: AP (COLAR AQUI | AD5: 201 | AE5: 0.082 | AF5: 0.076 | AG5: 0.084 | AH5: 0.096 | AP5: XXX | AQ5: XXX | AR5: XXX | AS5: XXX | AT5: XXX | AV5: 45034 | AW5: 45092 | AX5: 45092 | AY5: 219 | AZ5: 2304.01 | BA5: 1320.97 | BB5: 5.17 | BC5: =ROUND((BA5+BB5)/AY5,2) -> 6.06 | BD5: 977.34 | BE5: 0.53 | BH5: 5 A 10 | BQ5: 5 A 10 | BR5: 5 | BS5: 70 | BT5: 4.987 | BU5: =ROUND(BS5*BT5,2) -> 349.09 | BV5: 3.69 | BW5: =BS5*BV5 -> 258.3 | BX5: =BU5+BW5 -> 607.39 | CA5: 45098 | CB5: 300.73 | CC5: 12.741595 | CD5: =ROUND(CB5*CC5,2) -> 3831.78 | CE5: =ROUND(CC5,2) -> 12.74 | CF5: 2.5 | CG5: =CE5*CF5 -> 31.85
A6: 45105 | B6: ÁGUA | C6: 2361.768 | D6: 0 | E6: 5827.643 | F6: 3822.973 | G6: 1695.446 | H6: 1763.177 | I6: 3911.762 | J6: 2644.027 | K6: 2174.502 | L6: 1981.599 | M6: 1899.927 | N6: 2775.917 | O6: 873.956 | P6: 5229.375 | Q6: 3177.429 | R6: =SUM(C6:Q6) -> 40139.501 | T6: 201 (ESPAÇO "201 GÁS PISC." DA TABELA DE LEITURAS, ZERADO) | U6: =D40 -> 0 | V6: =D41 -> 0 | W6: =ROUND(U6,3) -> 0 | X6: =ROUNDDOWN(W6*$BC$43+($BD$43+$BE$43)*V6,2) -> 0 | Y6: =D82 -> 0 | Z6: =ROUND(Y6,3) -> 0 | AA6: 0 | AC6: O TEXTO DA COLUNA DA TABELA 2) | AD6: 201 (ESPAÇO "201 GÁS PISC." DA TABELA DE LEITURAS, ZERADO) | AE6: 0 | AF6: 0 | AG6: 0 | AH6: 0 | AP6: XXX | AQ6: XXX | AR6: XXX | AS6: XXX | AT6: XXX | AV6: 45064 | AW6: 45124 | AX6: 45124 | AY6: 238 | AZ6: 2618.81 | BA6: 1501.7 | BB6: 5.47 | BC6: =ROUND((BA6+BB6)/AY6,2) -> 6.33 | BD6: 1111.08 | BE6: 0.56 | BH6: 10 A 15 | BQ6: 10 A 15 | BR6: 5 | BS6: 70 | BT6: 7.727 | BU6: =ROUND(BS6*BT6,2) -> 540.89 | BV6: 5.718 | BW6: =BS6*BV6 -> 400.26 | BX6: =BU6+BW6 -> 941.15 | CA6: 45296 | CB6: 280.22 | CC6: 12,809293 | CD6: =ROUND(CB6*CC6,2) -> 3589.42 | CE6: =ROUND(CC6,2) -> 12.81 | CF6: 2.5 | CG6: =CE6*CF6 -> 32.025
A7: 45138 | B7: ÁGUA | C7: 2376.043 | D7: 0 | E7: 5881.028 | F7: 3839.238 | G7: 1709.97 | H7: 1780.795 | I7: 3933.364 | J7: 2655.586 | K7: 2189.083 | L7: 1992.42 | M7: 1929.111 | N7: 2786.031 | O7: 877.042 | P7: 5236.806 | Q7: 3193.116 | R7: =SUM(C7:Q7) -> 40379.633 | T7: 202 | U7: =E40 -> 16.763 | V7: =E41 -> 0.073 | W7: =ROUND(U7,3) -> 16.763 | X7: =ROUNDDOWN(W7*$BC$43+($BD$43+$BE$43)*V7,2) -> 215.24 | Y7: =E82 -> 2.741 | Z7: =ROUND(Y7,3) -> 2.741 | AA7: =ROUND(Z7*$CG$10,2) -> 103.82 | AD7: 202 | AE7: 0.101 | AF7: 0.11 | AG7: 0.097 | AH7: 0.073 | AP7: XXX | AQ7: XXX | AR7: XXX | AS7: XXX | AT7: XXX | AV7: 45096 | AW7: 45153 | AX7: 45153 | AY7: 263 | AZ7: 3031.13 | BA7: 1739.5 | BB7: 4.11 | BC7: =ROUND((BA7+BB7)/AY7,2) -> 6.63 | BD7: 1287.06 | BE7: 0.46 | BH7: 15 A 20 | BQ7: 15 A 20 | BR7: 5 | BS7: 70 | BT7: 10.549 | BU7: =ROUND(BS7*BT7,2) -> 738.43 | BV7: 7.806 | BW7: =BS7*BV7 -> 546.42 | BX7: =BU7+BW7 -> 1284.85 | CA7: 45477 | CB7: 271.38 | CC7: 13.550888 | CD7: =ROUND(CB7*CC7,2) -> 3677.44 | CE7: =ROUND(CC7,2) -> 13.55 | CF7: 2.5 | CG7: =CE7*CF7 -> 33.875
A8: 45166 | B8: ÁGUA | C8: 2396.08 | D8: 0 | E8: 5923.725 | F8: 3855.312 | G8: 1721.456 | H8: 1799.713 | I8: 3950.691 | J8: 2666.401 | K8: 2201.556 | L8: 2001.809 | M8: 1933.433 | N8: 2795.101 | O8: 879.561 | P8: 5244.122 | Q8: 3209.97 | R8: =SUM(C8:Q8) -> 40578.93 | T8: 301 | U8: =F40 -> 19.759 | V8: =F41 -> 0.086 | W8: =ROUND(U8,3) -> 19.759 | X8: =ROUNDDOWN(W8*$BC$43+($BD$43+$BE$43)*V8,2) -> 253.65 | Y8: =F82 -> 4.059 | Z8: =ROUND(Y8,3) -> 4.059 | AA8: =ROUND(Z8*$CG$10,2) -> 153.73 | AD8: 301 | AE8: 0.086 | AF8: 0.093 | AG8: 0.086 | AH8: 0.086 | AP8: XXX | AQ8: XXX | AR8: XXX | AS8: XXX | AT8: XXX | AV8: 45126 | AW8: 45185 | AX8: 45185 | AY8: 274 | AZ8: 3213.33 | BA8: 1844.13 | BB8: 4.23 | BC8: =ROUND((BA8+BB8)/AY8,2) -> 6.75 | BD8: 1364.49 | BE8: 0.48 | BH8: 20 A 40 | BQ8: 20 A 40 | BR8: 20 | BS8: 280 | BT8: 13.418 | BU8: =ROUND(BS8*BT8,2) -> 3757.04 | BV8: 9.929 | BW8: =BS8*BV8 -> 2780.12 | BX8: =BU8+BW8 -> 6537.16 | CA8: 45645 | CB8: 300.56 | CC8: 13.889373 | CD8: =ROUND(CB8*CC8,2) -> 4174.59 | CE8: =ROUND(CC8,2) -> 13.89 | CF8: 2.5 | CG8: =CE8*CF8 -> 34.725
A9: 45197 | B9: ÁGUA | C9: 2416.782 | D9: 0 | E9: 5955.074 | F9: 3872.337 | G9: 1736.355 | H9: 1818.171 | I9: 3967.667 | J9: 2678.981 | K9: 2211.822 | L9: 2017.308 | M9: 1938.571 | N9: 2804.456 | O9: 882.839 | P9: 5251.34 | Q9: 3227.372 | R9: =SUM(C9:Q9) -> 40779.075 | T9: 302 | U9: =G40 -> 19.988 | V9: =G41 -> 0.087 | W9: =ROUND(U9,3) -> 19.988 | X9: =ROUNDDOWN(W9*$BC$43+($BD$43+$BE$43)*V9,2) -> 256.59 | Y9: =G82 -> 2.429 | Z9: =ROUND(Y9,3) -> 2.429 | AA9: =ROUND(Z9*$CG$10,2) -> 92 | AD9: 302 | AE9: 0.109 | AF9: 0.09 | AG9: 0.07 | AH9: 0.087 | AP9: XXX | AQ9: XXX | AR9: XXX | AS9: XXX | AT9: XXX | AV9: 45159 | AW9: 45215 | AX9: 45215 | AY9: 261 | AZ9: 2998.76 | BA9: 1720.47 | BB9: 4.77 | BC9: =ROUND((BA9+BB9)/AY9,2) -> 6.61 | BD9: 1272.98 | BE9: 0.54 | BH9: 40 A 60 | BQ9: 40 A 60 | BR9: 5.42857 | BS9: 76 | BT9: 16.371 | BU9: =ROUND(BS9*BT9,2) -> 1244.2 | BV9: 12.112 | BW9: =BS9*BV9 -> 920.512 | BX9: =BU9+BW9 -> 2164.712 | CA9: 45815 | CB9: 283.91 | CC9: 15.065302 | CD9: =ROUND(CB9*CC9,2) -> 4277.19 | CE9: =ROUND(CC9,2) -> 15.07 | CF9: 2.5 | CG9: =CE9*CF9 -> 37.675
A10: 45227 | B10: ÁGUA | C10: 2436.831 | D10: 0 | E10: 5972.821 | F10: 3892.028 | G10: 1750.664 | H10: 1835.107 | I10: 3987.57 | J10: 2690.956 | K10: 2223.174 | L10: 2028.352 | M10: 1943.757 | N10: 2814.368 | O10: 885.629 | P10: 5260.244 | Q10: 3243.387 | R10: =SUM(C10:Q10) -> 40964.888 | T10: 401 | U10: =H40 -> 25.559 | V10: =H41 -> 0.112 | W10: =ROUND(U10,3) -> 25.559 | X10: =ROUNDDOWN(W10*$BC$43+($BD$43+$BE$43)*V10,2) -> 329.05 | Y10: =H82 -> 1.414 | Z10: =ROUND(Y10,3) -> 1.414 | AA10: =ROUND(Z10*$CG$10,2) -> 53.56 | AD10: 401 | AE10: 0.127 | AF10: 0.141 | AG10: 0.136 | AH10: 0.112 | AP10: XXX | AQ10: XXX | AR10: XXX | AS10: XXX | AT10: XXX | AV10: 45189 | AW10: 45245 | AX10: 45245 | AY10: 242 | AZ10: =BA10+BB10+BD10+BE10 -> 2684.4 | BA10: 1539.74 | BB10: 4.87 | BC10: =ROUND((BA10+BB10)/AY10,2) -> 6.38 | BD10: 1139.24 | BE10: 0.55 | BH10: SOMA | BI10: =SUM(BI4:BI8) -> 1.42857 | BJ10: =SUM(BJ4:BJ8) -> 20 | BL10: =SUM(BL3:BL8) -> 363.2 | BN10: =SUM(BN3:BN8) -> 268.54 | BO10: =SUM(BO3:BO8) -> 631.74 | BQ10: SOMA | BR10: =SUM(BR4:BR9) -> 45.42857 | BS10: =SUM(BS4:BS9) -> 636 | BU10: =SUM(BU3:BU9) -> 7109.85 | BW10: =SUM(BW3:BW9) -> 5260.652 | BX10: =SUM(BX3:BX9) -> 12370.502 | CA10: 46025 | CB10: 320 | CC10: 15.145313 | CD10: =ROUND(CB10*CC10,2) -> 4846.5 | CE10: =ROUND(CC10,2) -> 15.15 | CF10: 2.5 | CG10: =CE10*CF10 -> 37.875
A11: 45258 | B11: ÁGUA | C11: 2455.727 | D11: 0 | E11: 6004.368 | F11: 3909.588 | G11: 1769.361 | H11: 1854.208 | I11: 4010.335 | J11: 2703.906 | K11: 2237.708 | L11: 2043.882 | M11: 1952.156 | N11: 2825.211 | O11: 888.719 | P11: 5262.031 | Q11: 3262.162 | R11: =SUM(C11:Q11) -> 41179.362 | T11: 402 | U11: =I40 -> 23.777 | V11: =I41 -> 0.104 | W11: =ROUND(U11,3) -> 23.777 | X11: =ROUNDDOWN(W11*$BC$43+($BD$43+$BE$43)*V11,2) -> 305.87 | Y11: =I82 -> 4.82 | Z11: =ROUND(Y11,3) -> 4.82 | AA11: =ROUND(Z11*$CG$10,2) -> 182.56 | AD11: 402 | AE11: 0.073 | AF11: 0.086 | AG11: 0.094 | AH11: 0.104 | AP11: XXX | AQ11: XXX | AR11: XXX | AS11: XXX | AT11: XXX | AV11: 45222 | AW11: 45275 | AX11: 45275 | AY11: 239 | AZ11: =BA11+BB11+BD11+BE11 -> 2634.49 | BA11: 1511.21 | BB11: 4.64 | BC11: =ROUND((BA11+BB11)/AY11,2) -> 6.34 | BD11: 1118.12 | BE11: 0.52 | BH11: USO REC. HÍDR. ÁGUA | BO11: 15.61 | BQ11: USO REC. HÍDR. ÁGUA | BX11: 15.28
A12: 45288 | B12: ÁGUA | C12: 2474.42 | D12: 0 | E12: 6053.424 | F12: 3931.077 | G12: 1784.135 | H12: 1871.797 | I12: 4032.631 | J12: 2715.053 | K12: 2250.844 | L12: 2059.568 | M12: 1968.013 | N12: 2836.379 | O12: 891.618 | P12: 5265.855 | Q12: 3281.035 | R12: =SUM(C12:Q12) -> 41415.849 | T12: 501 | U12: =J40 -> 25.421 | V12: =J41 -> 0.111 | W12: =ROUND(U12,3) -> 25.421 | X12: =ROUNDDOWN(W12*$BC$43+($BD$43+$BE$43)*V12,2) -> 326.78 | Y12: =J82 -> 1.213 | Z12: =ROUND(Y12,3) -> 1.213 | AA12: =ROUND(Z12*$CG$10,2) -> 45.94 | AD12: 501 | AE12: 0.06 | AF12: 0.128 | AG12: 0.185 | AH12: 0.111 | AP12: XXX | AQ12: XXX | AR12: XXX | AS12: XXX | AT12: XXX | AV12: 45253 | AW12: 45306 | AX12: 45306 | AY12: 246 | AZ12: =BA12+BB12+BD12+BE12 -> 2749.91 | BA12: 1577.79 | BB12: 4.25 | BC12: =ROUND((BA12+BB12)/AY12,2) -> 6.43 | BD12: 1167.39 | BE12: 0.48 | BH12: USO REC. HÍDR. ESGOTO | BO12: 3.43 | BQ12: USO REC. HÍDR. ESGOTO | BX12: 3.36
A13: 45319 | B13: ÁGUA | C13: 2491.821 | D13: 0 | E13: 6102.368 | F13: 3953.12 | G13: 1800.569 | H13: 1885.724 | I13: 4058.137 | J13: 2726.861 | K13: 2265.914 | L13: 2075.591 | M13: 1994.272 | N13: 2850.035 | O13: 894.558 | P13: 5267.996 | Q13: 3300.08 | R13: =SUM(C13:Q13) -> 41667.046 | T13: 502 | U13: =K40 -> 13.441 | V13: =K41 -> 0.059 | W13: =ROUND(U13,3) -> 13.441 | X13: =ROUNDDOWN(W13*$BC$43+($BD$43+$BE$43)*V13,2) -> 173.17 | Y13: =K82 -> 1.029 | Z13: =ROUND(Y13,3) -> 1.029 | AA13: =ROUND(Z13*$CG$10,2) -> 38.97 | AD13: 502 | AE13: 0.056 | AF13: 0.069 | AG13: 0.057 | AH13: 0.059 | AP13: XXX | AQ13: XXX | AR13: XXX | AS13: XXX | AT13: XXX | AV13: 45281 | AW13: 45337 | AX13: 45337 | AY13: 243 | AZ13: =BA13+BB13+BD13+BE13 -> 2699.88 | BA13: 1549.26 | BB13: 3.9 | BC13: =ROUND((BA13+BB13)/AY13,2) -> 6.39 | BD13: 1146.28 | BE13: 0.44 | BH13: TOTAL | BO13: =BO10+BO11+BO12 -> 650.78 | BQ13: TOTAL | BX13: =BX10+BX11+BX12 -> 12389.142 | CA13: GÁS: HÁ 2 TANQUES DE 200 KG CADA. 1KG COMPRADO É IGUAL A 2,5M3 CONSUMIDOS. ESSE VALOR É CORRIGIDO A CADA ABASTECIMENTO. 2ª VARIÁVEL DA FÓRMULA (COLUNA "CONSUMO M3"): VALOR É IGUAL A 2,5 X O PREÇO UNITÁRIO DO QUILO, QUE SERÁ VERIFICADO NO ÚLTIMO ABASTECIMENTO FEITO
A14: 45350 | B14: ÁGUA | C14: 2505.809 | D14: 0 | E14: 6151.25 | F14: 3971.944 | G14: 1815.415 | H14: 1905.788 | I14: 4084.603 | J14: 2737.65 | K14: 2281.466 | L14: 2090.551 | M14: 2001.276 | N14: 2861.248 | O14: 898.348 | P14: 5268.242 | Q14: 3317.755 | R14: =SUM(C14:Q14) -> 41891.345 | T14: 601 | U14: =L40 -> 3.979 | V14: =L41 -> 0.017 | W14: =ROUND(U14,3) -> 3.979 | X14: =ROUNDDOWN(W14*$BC$43+($BD$43+$BE$43)*V14,2) -> 50.68 | Y14: =L82 -> 0.582 | Z14: =ROUND(Y14,3) -> 0.582 | AA14: =ROUND(Z14*$CG$10,2) -> 22.04 | AD14: 601 | AE14: 0.022 | AF14: 0.025 | AG14: 0.014 | AH14: 0.017 | AP14: XXX | AQ14: XXX | AR14: XXX | AS14: XXX | AT14: XXX | AV14: 45313 | AW14: 45366 | AX14: 45366 | AY14: 293 | AZ14: =BA14+BB14+BD14+BE14 -> 3689.84 | BA14: 2117.99 | BB14: 4.15 | BC14: =ROUND((BA14+BB14)/AY14,2) -> 7.24 | BD14: 1567.23 | BE14: 0.47 | BH14: LEITURA ERRADA QUE FOI FEITA EM 22/07/25: | BN14: 5021 | BO14: M3 | BQ14: LEITURA ATUAL, VERIFIQUEI QUE ESTÁ CORRETA: | BW14: 5657 | BX14: M3 | CA14: GÁS DO 201: TEM UM MEDIDOR A PARTE. NO APTº A MEDIÇÃO GERALMENTE É ZERO, PORQUE TEM FOGÃO ELÉTRICO
A15: 45379 | B15: ÁGUA | C15: 2523.908 | D15: 0 | E15: 6192.33 | F15: 3991.919 | G15: 1830.717 | H15: 1918.385 | I15: 4101.951 | J15: 2748.753 | K15: 2297.261 | L15: 2101.516 | M15: 2023.642 | N15: 2874.74 | O15: 903.365 | P15: 5269.756 | Q15: 3336.855 | R15: =SUM(C15:Q15) -> 42115.098 | T15: 602 | U15: =M40 -> 0.682 | V15: =M41 -> 0.003 | W15: =ROUND(U15,3) -> 0.682 | X15: =ROUNDDOWN(W15*$BC$43+($BD$43+$BE$43)*V15,2) -> 8.79 | Y15: =M82 -> 0.13 | Z15: =ROUND(Y15,3) -> 0.13 | AA15: =ROUND(Z15*$CG$10,2) -> 4.92 | AD15: 602 | AE15: 0.093 | AF15: 0.006 | AG15: 0.021 | AH15: 0.003 | AP15: XXX | AQ15: XXX | AR15: XXX | AS15: XXX | AT15: XXX | AV15: 45342 | AW15: 45397 | AX15: 45397 | AY15: 251 | AZ15: =BA15+BB15+BD15+BE15 -> 2951.83 | BA15: 1693.72 | BB15: 4.3 | BC15: =ROUND((BA15+BB15)/AY15,2) -> 6.77 | BD15: 1253.32 | BE15: 0.49 | BH15: LEITURA CORRETA DE 22/07/25: | BN15: 5362 | BO15: M3 | BQ15: LEITURA ANTERIOR CORRETA: | BW15: =BN15 -> 5362 | BX15: M3 | CA15: ÁGUA/ESGOTO DA LEITURA DE 20/12/22, MODELO, 3ª VARIÁVEL DA FÓRMULA (COLUNA "CONSUMO M3"): IGUAL AO ESGOTO DINÂMICO ($881,49) MAIS RECURSOS HÍDRICOS ESGOTO ($0,49), ISSO DIVIDIDO POR 15 (CONDÔMINOS + CONDOMÍNIO), TUDO NA CONTA, IGUAL A $58,798, ARREDOND. P/$58,80
A16: 45411 | B16: ÁGUA | C16: 2546.976 | D16: 0 | E16: 6237.3 | F16: 4018.728 | G16: 1849.796 | H16: 1928.603 | I16: 4117.224 | J16: 2758.828 | K16: 2320.094 | L16: 2124.267 | M16: 2052.455 | N16: 2893.032 | O16: 909.32 | P16: 5269.944 | Q16: 3353.903 | R16: =SUM(C16:Q16) -> 42380.47 | T16: 701 | U16: =N40 -> 13.458 | V16: =N41 -> 0.059 | W16: =ROUND(U16,3) -> 13.458 | X16: =ROUNDDOWN(W16*$BC$43+($BD$43+$BE$43)*V16,2) -> 173.29 | Y16: =N82 -> 0.785 | Z16: =ROUND(Y16,3) -> 0.785 | AA16: =ROUND(Z16*$CG$10,2) -> 29.73 | AD16: 701 | AE16: 0.07 | AF16: 0.059 | AG16: 0.056 | AH16: 0.059 | AP16: XXX | AQ16: XXX | AR16: XXX | AS16: XXX | AT16: XXX | AV16: 45370 | AW16: 45427 | AX16: 45427 | AY16: 256 | AZ16: =BA16+BB16+BD16+BE16 -> 3039.17 | BA16: 1743.28 | BB16: 5.3 | BC16: =ROUND((BA16+BB16)/AY16,2) -> 6.83 | BD16: 1289.99 | BE16: 0.6 | BH16: LEITURA ANTERIOR: | BN16: 5001 | BO16: M3 | BQ16: CONSUMO CORRETO: | BW16: =BW14-BW15 -> 295 | BX16: M3 | CA16: CONSUMO DE ÁGUA DO CONDOMÍNIO: RAZOÁVEL ENTRE 20 E 40 M3. MENOS DE 20M3 OU MAIS DE 40M3: UMA DAS 2 LEITURAS PODE ESTAR ERRADA
A17: 45441 | B17: ÁGUA | C17: 2567.926 | D17: 0 | E17: 6280.362 | F17: 4045.151 | G17: 1871.71 | H17: 1943.225 | I17: 4138.443 | J17: 2765.393 | K17: 2329.702 | L17: 2140.097 | M17: 2061.531 | N17: 2916.945 | O17: 914.484 | P17: 5274.594 | Q17: 3368.671 | R17: =SUM(C17:Q17) -> 42618.234 | T17: 702 | U17: =O40 -> 7.19 | V17: =O41 -> 0.031 | W17: =ROUND(U17,3) -> 7.19 | X17: =ROUNDDOWN(W17*$BC$43+($BD$43+$BE$43)*V17,2) -> 91.93 | Y17: =O82 -> 3.761 | Z17: =ROUND(Y17,3) -> 3.761 | AA17: =ROUND(Z17*$CG$10,2) -> 142.45 | AD17: 702 | AE17: 0.031 | AF17: 0.034 | AG17: 0.026 | AH17: 0.031 | AP17: XXX | AQ17: XXX | AR17: XXX | AS17: XXX | AT17: XXX | AV17: 45400 | AW17: 45460 | AX17: 45460 | AY17: 289 | AZ17: =BA17+BB17+BD17+BE17 -> 3649.9 | BA17: 2094.6 | BB17: 4.79 | BC17: =ROUND((BA17+BB17)/AY17,2) -> 7.26 | BD17: 1549.97 | BE17: 0.54 | BH17: CONSUMO CORRETO: | BN17: =BN15-BN16 -> 361 | BO17: M3 | CA17: ANOTAR NO FINAL DA TABELA "RESUMO DOS LANÇAMENTOS (RECEITAS/DESPESAS) O SALDO DE CRÉDITO OU DÉBITO DE DIFERENÇA DE LEITURA (DIFERENÇA DE CONSUMO DE ÁGUA DO CONDOMÍNIO FORA DA PREVISÃO)
A18: 45471 | B18: ÁGUA | C18: 2587.661 | D18: 0 | E18: 6316.765 | F18: 4075.057 | G18: 1898.116 | H18: 1962.961 | I18: 4159.113 | J18: 2774.914 | K18: 2342.361 | L18: 2156.088 | M18: 2065.768 | N18: 2930.577 | O18: 918.504 | P18: 5278.061 | Q18: 3382.209 | R18: =SUM(C18:Q18) -> 42848.155 | T18: 801 | U18: =P40 -> 4.531 | V18: =P41 -> 0.02 | W18: =ROUND(U18,3) -> 4.531 | X18: =ROUNDDOWN(W18*$BC$43+($BD$43+$BE$43)*V18,2) -> 58.51 | Y18: =P82 -> 0.423 | Z18: =ROUND(Y18,3) -> 0.423 | AA18: =ROUND(Z18*$CG$10,2) -> 16.02 | AD18: 801 | AE18: 0.024 | AF18: 0.021 | AG18: 0.022 | AH18: 0.02 | AP18: XXX | AQ18: XXX | AR18: XXX | AS18: XXX | AT18: XXX | AV18: 45433 | AW18: 45488 | AX18: 45488 | AY18: 302 | AZ18: =BA18+BB18+BD18+BE18 -> 3935.17 | BA18: 2258.49 | BB18: 4.88 | BC18: =ROUND((BA18+BB18)/AY18,2) -> 7.49 | BD18: 1671.25 | BE18: 0.55
A19: 45501 | B19: ÁGUA | C19: 2606.608 | D19: 0 | E19: 6367.535 | F19: 4100.681 | G19: 1917.329 | H19: 1980.374 | I19: 4187.751 | J19: 2789.214 | K19: 2356.703 | L19: 2188.661 | M19: 2069.694 | N19: 2942.168 | O19: 922.149 | P19: 5281.666 | Q19: 3394.571 | R19: =SUM(C19:Q19) -> 43105.104 | T19: 802 | U19: =Q40 -> 14.109 | V19: =Q41 -> 0.062 | W19: =ROUND(U19,3) -> 14.109 | X19: =ROUNDDOWN(W19*$BC$43+($BD$43+$BE$43)*V19,2) -> 181.86 | Y19: =Q82 -> 2.44 | Z19: =ROUND(Y19,3) -> 2.44 | AA19: =ROUND(Z19*$CG$10,2) -> 92.42 | AD19: 802 | AE19: 0.066 | AF19: 0.062 | AG19: 0.052 | AH19: 0.062 | AP19: XXX | AQ19: XXX | AR19: XXX | AS19: XXX | AT19: XXX | AV19: 45463 | AW19: 45519 | AX19: 45519 | AY19: 287 | AZ19: =BA19+BB19+BD19+BE19 -> 3238.72 | BA19: 1852.3 | BB19: 12.45 | BC19: =ROUND((BA19+BB19)/AY19,2) -> 6.5 | BD19: 1370.67 | BE19: 3.3 | BH19: TARIFAS DA LEITURA DE 22/07/2025 APÓS SER CORRIGIDA (NÃO FOI CORRIGIDA ATÉ 27/08/25) | BQ19: TARIFAS DA LEITURA DE 22/08/25 APÓS A LEITURA DE 22/07/25 SER CORRIGIDA (NÃO FOI CORRIGIDA ATÉ 27/08/25)
A20: 45532 | B20: ÁGUA | C20: 2626.524 | D20: 0 | E20: 6414.423 | F20: 4134.323 | G20: 1939.863 | H20: 1998.727 | I20: 4218.262 | J20: 2808.315 | K20: 2372.412 | L20: 2225.998 | M20: 2074.397 | N20: 2956.722 | O20: 925.675 | P20: 5288.84 | Q20: 3407.617 | R20: =SUM(C20:Q20) -> 43392.098 | T20: TOTAL | U20: =SUM(U4:U19) -> 229 | V20: =SUM(V4:V19) -> 1 | W20: =SUM(W4:W19) -> 229 | X20: =SUM(X4:X19) -> 2943.7 | Y20: =SUM(Y4:Y19) -> 25.826 | Z20: =SUM(Z4:Z19) -> 25.826 | AA20: =SUM(AA4:AA19) -> 978.16 | AD20: TOTAL | AE20: =SUM(AE4:AE19) -> 1 | AF20: =SUM(AF4:AF19) -> 1 | AG20: =SUM(AG4:AG19) -> 1 | AH20: =SUM(AH4:AH19) -> 1 | AI20: =SUM(AI4:AI19) -> 0 | AP20: XXX | AQ20: XXX | AR20: XXX | AS20: XXX | AT20: XXX | AV20: 45495 | AW20: 45551 | AX20: 45551 | AY20: 276 | AZ20: =BA20+BB20+BD20+BE20 -> 3395.64 | BA20: 1941.5 | BB20: 13.81 | BC20: =ROUND((BA20+BB20)/AY20,2) -> 7.08 | BD20: 1436.67 | BE20: 3.66 | BH20: FX. CONSUMO M3 | BI20: CONSUMO DA FX. EM M3 | BJ20: VOLUME TOTAL | BK20: R$/M3 DE ÁGUA | BL20: VR. DA ÁGUA | BM20: R$/M3 DE ESGOTO | BN20: VR. DO ESGOTO | BO20: SUBTOTAL | BQ20: FX. CONSUMO M3 | BR20: CONSUMO DA FX. EM M3 | BS20: VOLUME TOTAL | BT20: R$/M3 DE ÁGUA | BU20: VR. DA ÁGUA | BV20: R$/M3 DE ESGOTO | BW20: VR. DO ESGOTO | BX20: SUBTOTAL
A21: 45563 | B21: ÁGUA | C21: 2651.145 | D21: 0 | E21: 6460.245 | F21: 4165.149 | G21: 1967.666 | H21: 2017.377 | I21: 4243.84 | J21: 2831.729 | K21: 2387.454 | L21: 2241.497 | M21: 2079.757 | N21: 2967.437 | O21: 929.334 | P21: 5295.181 | Q21: 3421.916 | R21: =SUM(C21:Q21) -> 43659.727 | T21: CONFERÊNCIA | U21: =AY43 -> 229 | V21: 1 | W21: =U21 -> 229 | X21: =AZ43 -> 2943.7 | Y21: =R82 -> 25.826 | Z21: =Y21 -> 25.826 | AD21: CONFERÊNCIA | AE21: 1 | AF21: 1 | AG21: 1 | AH21: 1 | AI21: 1 | AP21: XXX | AQ21: XXX | AR21: XXX | AS21: XXX | AT21: XXX | AV21: 45526 | AW21: 45580 | AX21: 45580 | AY21: 287 | AZ21: =BA21+BB21+BD21+BE21 -> 3616.11 | BA21: 2069.39 | BB21: 12.18 | BC21: =ROUND((BA21+BB21)/AY21,2) -> 7.25 | BD21: 1531.31 | BE21: 3.23 | BH21: FIXA | BL21: 316.4 | BN21: 233.94 | BO21: =BL21+BN21 -> 550.34 | BQ21: FIXA | BU21: 316.4 | BW21: 233.94 | BX21: =BU21+BW21 -> 550.34
A22: 45593 | B22: ÁGUA | C22: 2674.494 | D22: 0 | E22: 6502.896 | F22: 4197.01 | G22: 1993.943 | H22: 2037.885 | I22: 4268.178 | J22: 2853.405 | K22: 2401.423 | L22: 2245.133 | M22: 2084.641 | N22: 2978.578 | O22: 933.19 | P22: 5300.14 | Q22: 3435.194 | R22: =SUM(C22:Q22) -> 43906.11 | T22: CONFERÊNCIA | U22: =U20-U21 -> 0 | V22: =V20-V21 -> 0 | W22: =W20-W21 -> 0 | X22: =X20-X21 -> 0 | Y22: =Y20-Y21 -> 0 | Z22: =Z20-Z21 -> 2.0605739e-13 | AD22: CONFERÊNCIA | AE22: =AE20-AE21 -> 0 | AF22: =AF20-AF21 -> 0 | AG22: =AG20-AG21 -> 0 | AH22: =AH20-AH21 -> 0 | AI22: =AI20-AI21 -> -1 | AP22: XXX | AQ22: XXX | AR22: XXX | AS22: XXX | AT22: XXX | AV22: 45495 | AW22: 45551 | AX22: 45551 | AY22: 297 | AZ22: =BA22+BB22+BD22+BE22 -> 3837.53 | BA22: 2195.46 | BB22: 13.81 | BC22: =ROUND((BA22+BB22)/AY22,2) -> 7.44 | BD22: 1624.6 | BE22: 3.66 | BF22: CONTA ORIGINAL DE 22/07/24, C/FATURAMENTO REALIZADO PELA MÉDIA DE CONSUMO (VIDRO EMBAÇADO/SUJO) | BH22: 0 A 5 | BI22: 5 | BJ22: 70 | BK22: 2.34 | BL22: =ROUND(BJ22*BK22,2) -> 163.8 | BM22: 1.73 | BN22: =BJ22*BM22 -> 121.1 | BO22: =BL22+BN22 -> 284.9 | BQ22: 0 A 5 | BR22: 5 | BS22: 70 | BT22: 2.34 | BU22: =ROUND(BS22*BT22,2) -> 163.8 | BV22: 1.73 | BW22: =BS22*BV22 -> 121.1 | BX22: =BU22+BW22 -> 284.9
A23: 45624 | B23: ÁGUA | C23: 2694.831 | D23: 0 | E23: 6540.498 | F23: 4218.168 | G23: 2018.795 | H23: 2058.898 | I23: 4289.126 | J23: 2873.857 | K23: 2416.056 | L23: 2249.807 | M23: 2089.656 | N23: 2989.712 | O23: 936.589 | P23: 5302.492 | Q23: 3464.005 | R23: =SUM(C23:Q23) -> 44142.49 | AP23: XXX | AQ23: XXX | AR23: XXX | AS23: XXX | AT23: XXX | AV23: 45555 | AW23: 45614 | AX23: 45614 | AY23: 191 | AZ23: =BA23+BB23+BD23+BE23 -> 2015.8 | BA23: 1149.43 | BB23: 12.5 | BC23: =ROUND((BA23+BB23)/AY23,2) -> 6.08 | BD23: 850.56 | BE23: 3.31 | BH23: 5 A 10 | BI23: 5 | BJ23: 70 | BK23: 4.987 | BL23: =ROUND(BJ23*BK23,2) -> 349.09 | BM23: 3.69 | BN23: =BJ23*BM23 -> 258.3 | BO23: =BL23+BN23 -> 607.39 | BQ23: 5 A 10 | BR23: 5 | BS23: 70 | BT23: 4.987 | BU23: =ROUND(BS23*BT23,2) -> 349.09 | BV23: 3.69 | BW23: =BS23*BV23 -> 258.3 | BX23: =BU23+BW23 -> 607.39
A24: 45654 | B24: ÁGUA | C24: 2714.766 | D24: 0 | E24: 6586.864 | F24: 4237.037 | G24: 2045.323 | H24: 2081.342 | I24: 4311.653 | J24: 2888.889 | K24: 2430.452 | L24: 2256.901 | M24: 2093.591 | N24: 2999.657 | O24: 940.243 | P24: 5309.751 | Q24: 3475.724 | R24: =SUM(C24:Q24) -> 44372.193 | T24: ÁGUA | U24: 20.173 | V24: 0 | W24: 10.409 | X24: 18.708 | Y24: 33.741 | Z24: 34.406 | AA24: 21.869 | AB24: 14.157 | AC24: 13.134 | AD24: 3.344 | AE24: 25.558 | AF24: 16.892 | AG24: 7.872 | AH24: 4.001 | AI24: 10.63 | AJ24: =SUM(U24:AI24) -> 234.894 | AP24: XXX | AQ24: XXX | AR24: XXX | AS24: XXX | AT24: XXX | AV24: 45587 | AW24: 45642 | AX24: 45642 | AY24: 294 | AZ24: =BA24+BB24+BD24+BE24 -> 3789.21 | BA24: 2157.64 | BB24: 28.18 | BC24: =ROUND((BA24+BB24)/AY24,2) -> 7.43 | BD24: 1596.62 | BE24: 6.77 | BF24: DIFERENÇA DE VALOR REF. À CONTA RECALCULADA EM 04/09/24 NA AGÊNCIA DA COPASA (R. TREMEDAL), POIS O FATURAMENTO DA ANTERIOR FOI REALIZADO PELA MÉDIA DE CONSUMO (VIDRO EMBAÇADO/SUJO) | BH24: 10 A 15 | BI24: 5 | BJ24: 70 | BK24: 7.727 | BL24: =ROUND(BJ24*BK24,2) -> 540.89 | BM24: 5.718 | BN24: =BJ24*BM24 -> 400.26 | BO24: =BL24+BN24 -> 941.15 | BQ24: 10 A 15 | BR24: 5 | BS24: 70 | BT24: 7.727 | BU24: =ROUND(BS24*BT24,2) -> 540.89 | BV24: 5.718 | BW24: =BS24*BV24 -> 400.26 | BX24: =BU24+BW24 -> 941.15
A25: 45686 | B25: ÁGUA | C25: 2733.035 | D25: 0 | E25: 6634.611 | F25: 4252.168 | G25: 2074.272 | H25: 2102.808 | I25: 4339.623 | J25: 2905.589 | K25: 2446.344 | L25: 2261.718 | M25: 2115.941 | N25: 3014.502 | O25: 945.558 | P25: 5314.469 | Q25: 3488.552 | R25: =SUM(C25:Q25) -> 44629.19 | T25: % DO CONSUMO TOTAL, PARA CÁLCULO DO VALOR DO ESGOTO A SER COBRADO POR AP (COLAR "TEXTO" AQUI O TEXTO DA COLUNA DA TABELA 2) | U25: 0.068 | V25: 0 | W25: 0.035 | X25: 0.063 | Y25: 0.114 | Z25: 0.117 | AA25: 0.074 | AB25: 0.048 | AC25: 0.045 | AD25: 0.011 | AE25: 0.087 | AF25: 0.057 | AG25: 0.027 | AH25: 0.014 | AI25: 0.036 | AJ25: =SUM(U25:AI25) -> 0.796 | AP25: XXX | AQ25: XXX | AR25: XXX | AS25: XXX | AT25: XXX | AV25: 45618 | AW25: 45672 | AX25: 45672 | AY25: 274 | AZ25: =BA25+BB25+BD25+BE25 -> 3366.67 | BA25: 1921.67 | BB25: 18.54 | BC25: =ROUND((BA25+BB25)/AY25,2) -> 7.08 | BD25: 1422.01 | BE25: 4.45 | BH25: 15 A 20 | BI25: 5 | BJ25: 70 | BK25: 10.549 | BL25: =ROUND(BJ25*BK25,2) -> 738.43 | BM25: 7.806 | BN25: =BJ25*BM25 -> 546.42 | BO25: =BL25+BN25 -> 1284.85 | BQ25: 15 A 20 | BR25: 5 | BS25: 70 | BT25: 10.549 | BU25: =ROUND(BS25*BT25,2) -> 738.43 | BV25: 7.806 | BW25: =BS25*BV25 -> 546.42 | BX25: =BU25+BW25 -> 1284.85
A26: 45716 | B26: ÁGUA | C26: 2750.222 | D26: 0 | E26: 6676.777 | F26: 4274.198 | G26: 2099.177 | H26: 2124.266 | I26: 4372.04 | J26: 2922.633 | K26: 2460.491 | L26: 2265.593 | M26: 2139.219 | N26: 3027.339 | O26: 951.566 | P26: 5317.16 | Q26: 3500.965 | R26: =SUM(C26:Q26) -> 44881.646 | T26: GÁS | U26: 0 | V26: 0.015 | W26: 1.03 | X26: 2.895 | Y26: 1.34 | Z26: 1.508 | AA26: 3.856 | AB26: 1.266 | AC26: 1.421 | AD26: 0.32 | AE26: 1.549 | AF26: 0.422 | AG26: 3.771 | AH26: 0 | AI26: 1.007 | AJ26: =SUM(U26:AI26) -> 20.4 | AP26: XXX | AQ26: XXX | AR26: XXX | AS26: XXX | AT26: XXX | AV26: 45647 | AW26: 45705 | AX26: 45705 | AY26: 220 | AZ26: =BA26+BB26+BD26+BE26 -> 2446.4 | BA26: 1386.48 | BB26: 27.37 | BC26: =ROUND((BA26+BB26)/AY26,2) -> 6.43 | BD26: 1025.97 | BE26: 6.58 | BH26: 20 A 40 | BI26: ??? | BJ26: =361-280 -> 81 | BK26: 13.418 | BL26: =ROUND(BJ26*BK26,2) -> 1086.86 | BM26: 9.929 | BN26: =BJ26*BM26 -> 804.249 | BO26: =BL26+BN26 -> 1891.109 | BQ26: 20 A 40 | BR26: ??? | BS26: 15 | BT26: 13.418 | BU26: =ROUND(BS26*BT26,2) -> 201.27 | BV26: 9.929 | BW26: =BS26*BV26 -> 148.935 | BX26: =BU26+BW26 -> 350.205
A27: 45745 | B27: ÁGUA | C27: 2769.255 | D27: 0 | E27: 6718.496 | F27: 4292.982 | G27: 2126.985 | H27: 2142.016 | I27: 4405.98 | J27: 2937.697 | K27: 2471.101 | L27: 2269.266 | M27: 2161.24 | N27: 3039.59 | O27: 957.542 | P27: 5321.136 | Q27: 3512.612 | R27: =SUM(C27:Q27) -> 45125.898 | T27: ALTERAÇÃO FEITA EM 29/10/2025: NÃO USAR ESTA ÚLTIMA TABELA. BASTA SELECIONAR AS CORRESPONDENTES COLUNAS DA TABELA 2 E SUBSTITUIR O Nº DA LINHA ANTERIOR PELA LINHA ATUAL, COM DADOS DA TABELA 1 | AP27: XXX | AQ27: XXX | AR27: XXX | AS27: XXX | AT27: XXX | AV27: 45679 | AW27: 45733 | AX27: 45733 | AY27: 292 | AZ27: =BA27+BB27+BD27+BE27 -> 3908.29 | BA27: 2226.75 | BB27: 27.42 | BC27: =ROUND((BA27+BB27)/AY27,2) -> 7.72 | BD27: 1647.53 | BE27: 6.59 | BH27: 40 A 60 | BQ27: 40 A 60
A28: 45775 | B28: ÁGUA | C28: 2792.975 | D28: 0 | E28: 6760.554 | F28: 4313.315 | G28: 2154.435 | H28: 2162.217 | I28: 4438.931 | J28: 2952.925 | K28: 2483.245 | L28: 2276.685 | M28: 2184.038 | N28: 3055.548 | O28: 964.436 | P28: 5327.134 | Q28: 3527.734 | R28: =SUM(C28:Q28) -> 45394.172 | AP28: XXX | AQ28: XXX | AR28: XXX | AS28: XXX | AT28: XXX | AV28: 45708 | AW28: 45762 | AX28: 45762 | AY28: 266 | AZ28: =BA28+BB28+BD28+BE28 -> 3438.61 | BA28: 1960.92 | BB28: 21.73 | BC28: =ROUND((BA28+BB28)/AY28,2) -> 7.45 | BD28: 1450.74 | BE28: 5.22 | BH28: SOMA | BI28: ??? | BJ28: =SUM(BJ22:BJ27) -> 361 | BL28: =SUM(BL21:BL27) -> 3195.47 | BN28: =SUM(BN21:BN27) -> 2364.269 | BO28: =SUM(BO21:BO27) -> 5559.739 | BQ28: SOMA | BR28: ??? | BS28: =SUM(BS22:BS27) -> 295 | BU28: =SUM(BU21:BU27) -> 2309.88 | BW28: =SUM(BW21:BW27) -> 1708.955 | BX28: =SUM(BX21:BX27) -> 4018.835
A29: 45805 | B29: ÁGUA | C29: 2819.356 | D29: 0 | E29: 6808.096 | F29: 4333.909 | G29: 2181.332 | H29: 2184.799 | I29: 4479.234 | J29: 2966.677 | K29: 2497.318 | L29: 2281.158 | M29: 2201.411 | N29: 3069.081 | O29: 970.584 | P29: 5331.826 | Q29: 3541.107 | R29: =SUM(C29:Q29) -> 45665.888 | AP29: XXX | AQ29: XXX | AR29: XXX | AS29: XXX | AT29: XXX | AV29: 45740 | AW29: 45792 | AX29: 45792 | AY29: 289 | AZ29: =BA29+BB29+BD29+BE29 -> 3916.52 | BA29: 2229.37 | BB29: 30.45 | BC29: =ROUND((BA29+BB29)/AY29,2) -> 7.82 | BD29: 1649.38 | BE29: 7.32 | BH29: USO REC. HÍDR. ÁGUA | BO29: ??? | BQ29: USO REC. HÍDR. ÁGUA | BX29: ???
A30: 45836 | B30: ÁGUA | C30: 2845.108 | D30: 0 | E30: 6853.487 | F30: 4352.74 | G30: 2209.487 | H30: 2209.08 | I30: 4542.657 | J30: 2982.973 | K30: 2511.29 | L30: 2286.864 | M30: 2220.498 | N30: 3084.382 | O30: 976.98 | P30: 5335.117 | Q30: 3551.921 | R30: =SUM(C30:Q30) -> 45962.584 | U30: FÓRMULA QUE FOI USADA DE 12/2025 A 02/2026: TOTAL DO CONSUMO DA TABELA 1 (-) SOMA(U5:U19). FOI PRECISO ALTERAR A FÓRMULA PARA ESTA, DEVIDO A ERRO NO HIDRÔMETRO DA COPASA NA LEITURA DE 28/01/26 (E TAMBÉM DE 29/12/25), CUJO CONSUMO APURADO PELA COPASA VEIO MENOR QUE O CONSUMO TOTAL DOS CONDÔMINOS QUE FOI POR MIM APURADO, SENDO POR ISSO ZERADO O CONSUMO REFERENTE AO CONDOMÍNIO. | AP30: XXX | AQ30: XXX | AR30: XXX | AS30: XXX | AT30: XXX | AV30: 45771 | AW30: 45824 | AX30: 45824 | AY30: 244 | AZ30: =BA30+BB30+BD30+BE30 -> 3043.18 | BA30: 1728.85 | BB30: 28.49 | BC30: =ROUND((BA30+BB30)/AY30,2) -> 7.2 | BD30: 1279 | BE30: 6.84 | BH30: USO REC. HÍDR. ESGOTO | BO30: ??? | BQ30: USO REC. HÍDR. ESGOTO | BX30: ???
A31: 45866 | B31: ÁGUA | C31: 2859.658 | D31: 0 | E31: 6883.806 | F31: 4371.664 | G31: 2237.09 | H31: 2236.475 | I31: 4599.043 | J31: 2998.207 | K31: 2526.018 | L31: 2290.725 | M31: 2233.459 | N31: 3100.83 | O31: 983.732 | P31: 5340.984 | Q31: 3567.961 | R31: =SUM(C31:Q31) -> 46229.652 | U31: VOLTAR À FÓRMULA CORRETA: AY41-SOMA(U5:U19), SENDO O 1º ITEM DESTA FÓRMULA O "CONSUMO TOTAL" DA TABELA "COPASA NFFS'. NA APURAÇÃO PARA FEVEREIRO/2026 (E TAMBÉM PARA JANEIRO/2026) FOI PRECISO ALTERAR ESTA FÓRMULA, DEVIDO A ERRO NO HIDRÔMETRO DA COPASA NA LEITURA DE 28/01/26 (E TAMBÉM DE 29/12/25), CUJO CONSUMO APURADO PELA COPASA VEIO MENOR QUE O CONSUMO TOTAL DOS CONDÔMINOS QUE FOI POR MIM APURADO, SENDO POR ISSO ZERADO O CONSUMO REFERENTE AO CONDOMÍNIO. | AP31: XXX | AQ31: XXX | AR31: XXX | AS31: XXX | AT31: XXX | AV31: 45800 | AW31: 45853 | AX31: 45853 | AY31: 309 | AZ31: =BA31+BB31+BD31+BE31 -> 4380.41 | BA31: 2497.73 | BB31: 28 | BC31: =ROUND((BA31+BB31)/AY31,2) -> 8.17 | BD31: 1847.96 | BE31: 6.72 | BF31: ESTA CONTA FOI REEMITIDA EM 04/04/25 APÓS SOLICITAÇAO DE 31/03/25. A ORIGINAL DE 24/03/25 ESTAVA COM C/FATURAMENTO REALIZADO PELA MÉDIA DE CONSUMO (VIDRO EMBAÇADO/SUJO) | BH31: TOTAL | BO31: =BO28 -> 5559.739 | BQ31: TOTAL | BX31: =BX28 -> 4018.835
A32: 45897 | B32: ÁGUA | C32: 2881.573 | D32: 0 | E32: 6907.842 | F32: 4394.079 | G32: 2266.687 | H32: 2266.206 | I32: 4658.325 | J32: 3014.01 | K32: 2539.95 | L32: 2295.441 | M32: 2255.938 | N32: 3117.38 | O32: 991.377 | P32: 5346.02 | Q32: 3582.467 | R32: =SUM(C32:Q32) -> 46517.295 | AP32: XXX | AQ32: XXX | AR32: XXX | AS32: XXX | AT32: XXX | AV32: 45832 | AW32: 45887 | AX32: 45887 | AY32: 288 | AZ32: =BA32+BB32+BD32+BE32 -> 3870.33 | BA32: 2215.95 | BB32: 12.24 | BC32: =ROUND((BA32+BB32)/AY32,2) -> 7.74 | BD32: 1639.45 | BE32: 2.69
A33: 45928 | B33: ÁGUA | C33: 2901.993 | D33: 0 | E33: 6935.39 | F33: 4415.237 | G33: 2299.257 | H33: 2299.648 | I33: 4680.888 | J33: 3029.976 | K33: 2555.083 | L33: 2299.55 | M33: 2277.98 | N33: 3135.365 | O33: 999.908 | P33: 5350.331 | Q33: 3593.277 | R33: =SUM(C33:Q33) -> 46773.883 | AP33: XXX | AQ33: XXX | AR33: XXX | AS33: XXX | AT33: XXX | AV33: 45860 | AW33: 45915 | AX33: CTª SUBSTITUÍDA | AY33: 20 | AZ33: =BA33+BB33+BD33+BE33 -> 650.78 | BA33: 363.2 | BB33: 15.61 | BC33: =ROUND((BA33+BB33)/AY33,2) -> 18.94 | BD33: 268.54 | BE33: 3.43 | BF33: ESTA CONTA FOI REEMITIDA EM 27/05/25 APÓS SOLICITAÇAO DE MESMA DATA. A ORIGINAL DE 23/05/25 ESTAVA COM C/FATURAMENTO REALIZADO PELA MÉDIA DE CONSUMO (VIDRO EMBAÇADO/SUJO)
A34: 45958 | B34: ÁGUA | C34: 2922.166 | D34: 0 | E34: 6945.799 | F34: 4433.945 | G34: 2332.998 | H34: 2334.054 | I34: 4702.757 | J34: 3044.133 | K34: 2568.217 | L34: 2302.894 | M34: 2303.538 | N34: 3152.257 | O34: 1007.78 | P34: 5354.332 | Q34: 3603.907 | R34: =SUM(C34:Q34) -> 47008.777 | AP34: =LANÇTºS!R33 -> 45901 | AQ34: 102.13 | AR34: =$X$4 -> 236.41 | AS34: 570.56 | AT34: =$X$19+$AA$19+ROUND(LANÇTºS!S37/14,2) -> 581.89 | AV34: 45891 | AW34: 45945 | AX34: CTª SUBSTITUÍDA | AY34: =BS27 -> 0 | AZ34: =BA34+BB34+BD34+BE34 -> 0 | BA34: =BU27 -> 0 | BB34: 0 | BC34: =ROUND((BA34+BB34)/AY34,2) -> #DIV/0! | BD34: =BW27 -> 0 | BE34: 0 | BF34: O CONSUMO TOTAL EM M3 E O VALOR DO ESGOTO DESTA CONTA FORAM TAMBÉM USADOS PARA O FIM DO RATEIO REFERENTE A 08/2025. O TOTAL DA LEITURA DE 24/06/25 FOI USADO (E DEPOIS ZERADO) PARA A APURAÇÃO DO CONSUMO DO CONDOMÍNIO DA REFERÊNCIA 08/2025, UMA VEZ QUE A LEITURA NA CONTA DA COPASA (DE 22/07/25) ESTÁ INCORRETA (PARA MENOR!!!), E QUE NÃO FOI ATENDIDA ATÉ O DIA 08/08/25 MINHA SOLICITAÇÃO DE CORREÇÃO DA LEITURA JUNTO À COPASA.
A35: 45988 | B35: ÁGUA | C35: 2943.512 | D35: 0 | E35: 6968.752 | F35: 4454.109 | G35: 2367.015 | H35: 2371.531 | I35: 4725.655 | J35: 3058.525 | K35: 2582.062 | L35: 2306.115 | M35: 2320.802 | N35: 3171.152 | O35: 1015.935 | P35: 5359.148 | Q35: 3615.872 | R35: =SUM(C35:Q35) -> 47260.185 | AP35: XXX | AQ35: XXX | AR35: XXX | AS35: XXX | AT35: XXX | AV35: 45860 | AW35: 45915 | AX35: 45912 | AY35: 311 | AZ35: =BA35+BB35+BD35+BE35 -> 4411.43 | BA35: 2524.57 | BB35: 15.61 | BC35: =ROUND((BA35+BB35)/AY35,2) -> 8.17 | BD35: 1867.82 | BE35: 3.43 | BF35: ESTA CONTA FOI REEMITIDA EM XX/XX/25 APÓS SOLICITAÇAO DE MESMA DATA. A ORIGINAL DE 22/07/25 ESTAVA COM C/ERRO DE LEITURA, TALVEZ PELO VIDRO ESTAR EMBAÇADO (PEDI NA AGÊNCIA DA COPASA NA R. CURITIBA, +-1135, CORREÇÃO DA LEITURA E SUBSTITUIÇÃO DO VIDRO DO HIDRÔMETRO, QUE ESTÁ DIFICULTANDO A LEITURA)
A36: 46019 | B36: ÁGUA | C36: 2965.83 | D36: 0 | E36: 6996.308 | F36: 4477.698 | G36: 2396.634 | H36: 2406.015 | I36: 4745.622 | J36: 3074.752 | K36: 2597.378 | L36: 2312.217 | M36: 2346.024 | N36: 3190.299 | O36: 1024.254 | P36: 5365.727 | Q36: 3633.833 | R36: =SUM(C36:Q36) -> 47532.591 | AP36: XXX | AQ36: XXX | AR36: XXX | AS36: XXX | AT36: XXX | AV36: 45891 | AW36: 45945 | AX36: 45945 | AY36: 345 | AZ36: =BA36+BB36+BD36+BE36 -> 5204.82 | BA36: 2980.78 | BB36: 15.28 | BC36: =ROUND((BA36+BB36)/AY36,2) -> 8.68 | BD36: 2205.4 | BE36: 3.36 | BF36: OS DADOS AQUI LANÇADOS SÃO HIPOTÉTICOS, POIS ESTA CONTA ESTÁ SENDO POR MIM QUESTIONADA, CONFORME TABELAS À DIREITA, EM VISTA DE NÃO TER SIDO AINDA CORRIGIDA A CONTA ANTERIOR
A37: 46050 | B37: ÁGUA | C37: 2983.276 | D37: 0 | E37: 7021.616 | F37: 4499.176 | G37: 2417.275 | H37: 2438.385 | I37: 4765.244 | J37: 3103.937 | K37: 2613.08 | L37: 2317.832 | M37: 2347.365 | N37: 3203.754 | O37: 1031.989 | P37: 5370.498 | Q37: 3647.977 | R37: =SUM(C37:Q37) -> 47761.404 | AP37: 45931 | AQ37: 348.46 | AR37: =$X$4 -> 236.41 | AS37: 478.07 | AT37: =$X$19+$AA$19+ROUND(LANÇTºS!W37/14,2) -> 558.93 | AV37: 45923 | AW37: 45978 | AX37: 45978 | AY37: 274 | AZ37: =BA37+BB37+BD37+BE37 -> 3715.89 | BA37: 2045.31 | BB37: 1.1 | BC37: =ROUND((BA37+BB37)/AY37,2) -> 7.47 | BD37: 1669.24 | BE37: 0.24 | BF37: NOVA CONTA OBTIDA EM 02/09/25, SUBSTITUINDO A ANTERIOR, QUE TINHA ERRO DE LEITURA (NÃO FOI USADA P/CALCULAR RATEIOS)
A38: 46081 | B38: ÁGUA | C38: 3004.288 | D38: 0 | E38: 7046.072 | F38: 4520.851 | G38: 2434.714 | H38: 2472.444 | I38: 4788.671 | J38: 3150.294 | K38: 2627.243 | L38: 2321.426 | M38: 2352.726 | N38: 3217.678 | O38: 1038.48 | P38: 5375.905 | Q38: 3660.88 | R38: =SUM(C38:Q38) -> 48011.672 | T38: MENSALMENTE: | AP38: 45962 | AQ38: 351.47 | AR38: =$X$4 -> 236.41 | AS38: 435.18 | AT38: =$X$19+$AA$19+ROUND(LANÇTºS!AA37/14,2) -> 548.85 | AV38: 45954 | AW38: 46006 | AX38: 46006 | AY38: 247 | AZ38: =BA38+BB38+BD38+BE38 -> 3062.91 | BA38: 1760.49 | BB38: 0 | BC38: =ROUND((BA38+BB38)/AY38,2) -> 7.13 | BD38: 1302.42 | BE38: 0 | BF38: NOVA CONTA OBTIDA EM 02/09/25, SUBSTITUINDO A ANTERIOR, QUE TINHA ERRO DE LEITURA (NÃO FOI USADA P/CALCULAR RATEIOS)
A39: 46109 | B39: ÁGUA | C39: 3026.174 | D39: 0 | E39: 7062.835 | F39: 4540.61 | G39: 2454.702 | H39: 2498.003 | I39: 4812.448 | J39: 3175.715 | K39: 2640.684 | L39: 2325.405 | M39: 2353.408 | N39: 3231.136 | O39: 1045.67 | P39: 5380.436 | Q39: 3674.989 | R39: =SUM(C39:Q39) -> 48222.215 | T39: ELIMINAR DA "TABELA 1" A 1ª LINHA DE ÁGUA E A 1ª DE GÁS | AA39: (31/10/25) | AG39: MENSALMENTE: | AP39: 45992 | AQ39: 346.4 | AR39: =$X$4 -> 236.41 | AS39: 490.06 | AT39: =$X$19+$AA$19+ROUND(LANÇTºS!AE37/14,2) -> 561.78 | AV39: 45987 | AW39: 46037 | AX39: 46036 | AY39: 269 | AZ39: =BA39+BB39+BD39+BE39 -> 3466.72 | BA39: 1992.57 | BB39: 0 | BC39: =ROUND((BA39+BB39)/AY39,2) -> 7.41 | BD39: 1474.15 | BE39: 0 | BF39: NOVA CONTA OBTIDA EM 02/10/25, SUBSTITUINDO A ANTERIOR, QUE TINHA ERRO DE LEITURA
B40: (A) DIF. C/LEIT. ANT. | C40: =C39-C38 -> 21.886 | D40: =D39-D38 -> 0 | E40: =E39-E38 -> 16.763 | F40: =F39-F38 -> 19.759 | G40: =G39-G38 -> 19.988 | H40: =H39-H38 -> 25.559 | I40: =I39-I38 -> 23.777 | J40: =J39-J38 -> 25.421 | ... Q40: =Q39-Q38 -> 14.109 | R40: =SUM(C40:Q40) -> 210.543 | T40: COPIAR A ÚLTIMA LINHA DE CADA ITEM PARA A PLANILHA "MEDIÇÕES E COPASA HISTÓRICO" | AA40: (31/10/25) | AG40: ELIMINAR DESTA TABELA A 1ª COLUNA DATADA | AP40: 46023 | AQ40: 0 | AR40: =$X$4 -> 236.41 | AS40: 526.58 | AT40: =$X$19+$AA$19+ROUND(LANÇTºS!AI37/14,2) -> 542.16 | AV40: 46020 | AW40: 46071 | AX40: 46071 | AY40: 189 | AZ40: =BA40+BB40+BD40+BE40 -> 2101.43 | BA40: 1207.91 | BB40: 0 | BC40: =ROUND((BA40+BB40)/AY40,2) -> 6.39 | BD40: 893.52 | BE40: 0
B41: % DO CONSUMO TOTAL, PARA CÁLCULO DO VALOR DO ESGOTO A SER COBRADO POR AP | C41: =ROUND(C40/$AY$43,3) -> 0.096 | D41: =ROUND(D40/$AY$43,3) -> 0 | E41: =ROUND(E40/$AY$43,3) -> 0.073 | F41: =ROUND(F40/$AY$43,3) -> 0.086 | G41: =ROUND(G40/$AY$43,3) -> 0.087 | H41: =ROUND(H40/$AY$43,3) -> 0.112 | I41: =ROUND(I40/$AY$43,3) -> 0.104 | J41: =ROUND(J40/$AY$43,3) -> 0.111 | ... Q41: =ROUND(Q40/$AY$43,3) -> 0.062 | R41: =SUM(C41:Q41) -> 0.92 | T41: FÓRMULA QUE FOI USADA DE 12/2025 A 02/2026: ARRED(C40/TOTAL DO CONSUMO DA TABELA 1;3). FOI PRECISO ALTERAR A FÓRMULA PARA ESTA, DEVIDO A ERRO NO HIDRÔMETRO DA COPASA NA LEITURA DE 28/01/26 (E TAMBÉM DE 29/12/25), CUJO CONSUMO APURADO PELA COPASA VEIO MENOR QUE O CONSUMO TOTAL DOS CONDÔMINOS QUE FOI POR MIM APURADO, SENDO POR ISSO ZERADO O CONSUMO REFERENTE AO CONDOMÍNIO. | AG41: COPIAR A ÚLTIMA COLUNA PARA TABELA IDÊNTICA DA PLANILHA "MEDIÇÕES E COPASA HISTÓRICO" | AP41: 46054 | AQ41: 0 | AR41: =$X$4 -> 236.41 | AS41: 463.48 | AT41: =$X$19+$AA$19+ROUND(LANÇTºS!AM37/14,2) -> 550.81 | AV41: 46050 | AW41: 46099 | AX41: 46099 | AY41: 83 | AZ41: =BA41+BB41+BD41+BE41 -> 997.74 | BA41: 582.15 | BB41: 0 | BC41: =ROUND((BA41+BB41)/AY41,2) -> 7.01 | BD41: 415.59 | BE41: 0
B42: (B) DIF. ANT. | C42: =C38-C37 -> 21.012 | D42: =D38-D37 -> 0 | E42: =E38-E37 -> 24.456 | F42: =F38-F37 -> 21.675 | G42: =G38-G37 -> 17.439 | H42: =H38-H37 -> 34.059 | I42: =I38-I37 -> 23.427 | J42: =J38-J37 -> 46.357 | ... Q42: =Q38-Q37 -> 12.903 | R42: =SUM(C42:Q42) -> 250.268 | T42: VOLTAR À FÓRMULA CORRETA: ARRED(C40/$AY$41;3), SENDO O DIVISOR O "CONSUMO TOTAL" DA TABELA "COPASA NFFS'. NA APURAÇÃO PARA FEVEREIRO/2026 (E TAMBÉM PARA JANEIRO/2026) FOI PRECISO ALTERAR ESTA FÓRMULA, DEVIDO A ERRO NO HIDRÔMETRO DA COPASA NA LEITURA DE 28/01/26 (E TAMBÉM DE 29/12/25), CUJO CONSUMO APURADO PELA COPASA VEIO MENOR QUE O CONSUMO TOTAL DOS CONDÔMINOS QUE FOI POR MIM APURADO, SENDO POR ISSO ZERADO O CONSUMO REFERENTE AO CONDOMÍNIO. | AP42: 46082 | AQ42: 0 | AR42: =$X$4 -> 236.41 | AS42: 454.67 | AT42: =$X$19+$AA$19+ROUND(LANÇTºS!AQ37/14,2) -> 545.95 | AV42: 46078 | AW42: 46127 | AY42: 76 | AZ42: =BA42+BB42+BD42+BE42 -> 1010.35 | BA42: 581.08 | BB42: 0 | BC42: =ROUND((BA42+BB42)/AY42,2) -> 7.65 | BD42: 429.27 | BE42: 0
B43: A (-) B | C43: =C40-C42 -> 0.874 | D43: =D40-D42 -> 0 | E43: =E40-E42 -> -7.693 | F43: =F40-F42 -> -1.916 | G43: =G40-G42 -> 2.549 | H43: =H40-H42 -> -8.5 | I43: =I40-I42 -> 0.35 | J43: =J40-J42 -> -20.936 | ... Q43: =Q40-Q42 -> 1.206 | R43: =SUM(C43:Q43) -> -39.725 | AP43: 46113 | AQ43: 236.41 | AR43: =$X$4 -> 236.41 | AS43: 564.68 | AT43: =$X$19+$AA$19+ROUND(LANÇTºS!AU37/14,2) -> 564.68 | AV43: 46097 | AW43: 46157 | AY43: 229 | AZ43: =BA43+BB43+BD43+BE43 -> 2943.7 | BA43: 1692.15 | BB43: 0 | BC43: =ROUND((BA43+BB43)/AY43,2) -> 7.39 | BD43: 1251.55 | BE43: 0
B44: A (-) B ANTERIOR | C44: =(C38-C37)-(C37-C36) -> 3.566 | D44: =(D38-D37)-(D37-D36) -> 0 | E44: =(E38-E37)-(E37-E36) -> -0.852 | F44: =(F38-F37)-(F37-F36) -> 0.197 | G44: =(G38-G37)-(G37-G36) -> -3.202 | H44: =(H38-H37)-(H37-H36) -> 1.689 | I44: =(I38-I37)-(I37-I36) -> 3.805 | J44: =(J38-J37)-(J37-J36) -> 17.172 | ... L44: =(L38-L37)-(L37-L36) -> -2.021 | M44: =(M37-M36)-(M36-M35) -> -23.881 | N44: =(N38-N37)-(N37-N36) -> 0.469 | O44: =(O38-O37)-(O37-O36) -> -1.244 | P44: =(P38-P37)-(P37-P36) -> 0.636 | Q44: =(Q38-Q37)-(Q37-Q36) -> -1.241 | R44: =SUM(C44:Q44) -> -6.446 | AP44: 46143 | AR44: =$X$4 -> 236.41 | AT44: =$X$19+$AA$19+ROUND(LANÇTºS!AQ37/14,2) -> 545.95 | AZ44: =BA44+BB44+BD44+BE44 -> 0 | BC44: =ROUND((BA44+BB44)/AY44,2) -> #DIV/0!
B45: A (-) B ANTEANTERIOR | C45: =(C37-C36)-(C36-C35) -> -4.872 | D45: =(D37-D36)-(D36-D35) -> 0 | E45: =(E37-E36)-(E36-E35) -> -2.248 | F45: =(F37-F36)-(F36-F35) -> -2.111 | G45: =(G37-G36)-(G36-G35) -> -8.978 | H45: =(H37-H36)-(H36-H35) -> -2.114 | I45: =(I37-I36)-(I36-I35) -> -0.345 | J45: =(J37-J36)-(J36-J35) -> 12.958 | ... L45: =(L37-L36)-(L36-L35) -> -0.487 | M45: =M44-M43 -> -19.202 | N45: =(N37-N36)-(N36-N35) -> -5.692 | O45: =(O37-O36)-(O36-O35) -> -0.584 | P45: =(P37-P36)-(P36-P35) -> -1.808 | Q45: =(Q37-Q36)-(Q36-Q35) -> -3.817 | R45: =SUM(C45:Q45) -> -38.914
A46: 45044 | B46: GÁS | C46: 247.339 | D46: 24.435 | E46: 844.359 | F46: 549.4 | G46: 324.815 | H46: 294.219 | I46: 683.401 | J46: 351.016 | K46: 257.655 | L46: 380.78 | M46: 323.324 | N46: 581.129 | O46: 349.495 | P46: 312.571 | Q46: 330.217 | R46: =SUM(C46:Q46) -> 5854.155
A47: 45074 | B47: GÁS | C47: 247.339 | D47: 24.435 | E47: 848.575 | F47: 552.61 | G47: 326.086 | H47: 296.155 | I47: 687.646 | J47: 351.942 | K47: 259.133 | L47: 381.056 | M47: 326.117 | N47: 581.8 | O47: 351.036 | P47: 314.401 | Q47: 331.701 | R47: =SUM(C47:Q47) -> 5880.032
A48: 45105 | B48: GÁS | C48: 247.339 | D48: 24.484 | E48: 852.755 | F48: 556.733 | G48: 328.812 | H48: 299.19 | I48: 692.105 | J48: 352.987 | K48: 260.97 | L48: 381.232 | M48: 328.744 | N48: 582.736 | O48: 353.015 | P48: 316.605 | Q48: 333.73 | R48: =SUM(C48:Q48) -> 5911.437
A49: 45138 | B49: GÁS | C49: 247.339 | D49: 24.503 | E49: 857.902 | F49: 559.94 | G49: 331.541 | H49: 301.637 | I49: 698.416 | J49: 354.382 | K49: 262.633 | L49: 381.39 | M49: 331.435 | N49: 583.631 | O49: 353.935 | P49: 319.376 | Q49: 335.808 | R49: =SUM(C49:Q49) -> 5943.868
A50: 45166 | B50: GÁS | C50: 247.339 | D50: 24.868 | E50: 862.402 | F50: 563.537 | G50: 334.194 | H50: 303.754 | I50: 702.73 | J50: 355.473 | K50: 263.891 | L50: 381.505 | M50: 333.376 | N50: 584.359 | O50: 354.554 | P50: 321.591 | Q50: 338.289 | R50: =SUM(C50:Q50) -> 5971.862
A51: 45197 | B51: GÁS | C51: 247.339 | D51: 25.025 | E51: 865.573 | F51: 566.635 | G51: 336.349 | H51: 305.934 | I51: 707.568 | J51: 356.646 | K51: 264.995 | L51: 381.593 | M51: 335.561 | N51: 585.022 | O51: 355.426 | P51: 323.705 | Q51: 340.05 | R51: =SUM(C51:Q51) -> 5997.421
A52: 45227 | B52: GÁS | C52: 247.339 | D52: 25.538 | E52: 868.009 | F52: 569.681 | G52: 338.197 | H52: 307.801 | I52: 711.59 | J52: 357.572 | K52: 266.108 | L52: 381.687 | M52: 338.057 | N52: 585.748 | O52: 356.362 | P52: 325.837 | Q52: 341.51 | R52: =SUM(C52:Q52) -> 6021.036 | AP52: MENSALMENTE: | AW52: MENSALMENTE:
A53: 45258 | B53: GÁS | C53: 247.339 | D53: 25.831 | E53: 871.482 | F53: 572.163 | G53: 340.27 | H53: 309.423 | I53: 715.652 | J53: 358.455 | K53: 267.589 | L53: 381.884 | M53: 340.949 | N53: 586.518 | O53: 357.429 | P53: 325.969 | Q53: 343.476 | R53: =SUM(C53:Q53) -> 6044.429 | AP53: ELIMINAR DESTA TABELA A 1ª LINHA | AW53: ELIMINAR DESTA TABELA A 1ª LINHA | BD53: (31/10/25)
A54: 45288 | B54: GÁS | C54: 247.339 | D54: 26.256 | E54: 876.627 | F54: 575.789 | G54: 341.936 | H54: 311.234 | I54: 719.762 | J54: 359.347 | K54: 269.173 | L54: 381.967 | M54: 343.148 | N54: 587.145 | O54: 358.256 | P54: 325.969 | Q54: 345.967 | R54: =SUM(C54:Q54) -> 6069.915 | AP54: COPIAR A ÚLTIMA LINHA PARA A PLANILHA "MEDIÇÕES E COPASA HISTÓRICO" | AW54: COPIAR A ÚLTIMA LINHA PARA A PLANILHA "MEDIÇÕES E COPASA HISTÓRICO" | BD54: (31/10/25)
A55: 45319 | B55: GÁS | C55: 247.339 | D55: 26.286 | E55: 881.686 | F55: 579.125 | G55: 345.594 | H55: 313.236 | I55: 724.611 | J55: 360.297 | K55: 270.849 | L55: 382.106 | M55: 345.145 | N55: 588.263 | O55: 359.26 | P55: 325.969 | Q55: 348.168 | R55: =SUM(C55:Q55) -> 6097.934
A56: 45350 | B56: GÁS | C56: 247.339 | D56: 26.342 | E56: 886.31 | F56: 581.931 | G56: 348.229 | H56: 315.833 | I56: 728.95 | J56: 361.081 | K56: 272.558 | L56: 382.319 | M56: 347.763 | N56: 588.964 | O56: 360.611 | P56: 325.969 | Q56: 351.141 | R56: =SUM(C56:Q56) -> 6125.34
A57: 45379 | B57: GÁS | C57: 247.339 | D57: 26.437 | E57: 890.559 | F57: 584.344 | G57: 351.047 | H57: 317.621 | I57: 731.687 | J57: 361.713 | K57: 273.87 | L57: 382.825 | M57: 349.775 | N57: 589.711 | O57: 362.921 | P57: 325.969 | Q57: 353.715 | R57: =SUM(C57:Q57) -> 6149.533
A58: 45411 | B58: GÁS | C58: 247.339 | D58: 26.489 | E58: 895.181 | F58: 587.563 | G58: 352.877 | H58: 319.707 | I58: 734.815 | J58: 362.421 | K58: 275.615 | L58: 383.313 | M58: 352.122 | N58: 590.42 | O58: 364.954 | P58: 325.969 | Q58: 356.147 | R58: =SUM(C58:Q58) -> 6174.932
A59: 45441 | B59: GÁS | C59: 247.339 | D59: 26.581 | E59: 899.352 | F59: 590.111 | G59: 354.884 | H59: 321.046 | I59: 739.02 | J59: 362.609 | K59: 276.428 | L59: 383.686 | M59: 354.074 | N59: 590.99 | O59: 367.18 | P59: 325.969 | Q59: 357.912 | R59: =SUM(C59:Q59) -> 6197.181
A60: 45471 | B60: GÁS | C60: 247.339 | D60: 26.617 | E60: 902.724 | F60: 593.347 | G60: 356.44 | H60: 323.034 | I60: 742.841 | J60: 363.137 | K60: 277.934 | L60: 384.475 | M60: 355.991 | N60: 591.572 | O60: 368.626 | P60: 325.969 | Q60: 359.887 | R60: =SUM(C60:Q60) -> 6219.933
A61: 45501 | B61: GÁS | C61: 247.339 | D61: 26.648 | E61: 908.485 | F61: 596.267 | G61: 358.669 | H61: 325.189 | I61: 747.182 | J61: 364.036 | K61: 279.952 | L61: 385.193 | M61: 358.344 | N61: 592.173 | O61: 370.003 | P61: 325.969 | Q61: 361.526 | R61: =SUM(C61:Q61) -> 6246.975
A62: 45532 | B62: GÁS | C62: 247.339 | D62: 26.673 | E62: 914.935 | F62: 599.395 | G62: 361.064 | H62: 327.479 | I62: 752.224 | J62: 365.203 | K62: 281.808 | L62: 385.551 | M62: 361.465 | N62: 592.835 | O62: 371.71 | P62: 326.166 | Q62: 362.695 | R62: =SUM(C62:Q62) -> 6276.542
A63: 45563 | B63: GÁS | C63: 247.339 | D63: 26.749 | E63: 919.097 | F63: 602.202 | G63: 363.211 | H63: 329.188 | I63: 756.279 | J63: 366.286 | K63: 283.307 | L63: 385.996 | M63: 364.213 | N63: 593.433 | O63: 373.719 | P63: 326.567 | Q63: 364.136 | R63: =SUM(C63:Q63) -> 6301.722
A64: 45593 | B64: GÁS | C64: 247.339 | D64: 26.838 | E64: 922.079 | F64: 604.774 | G64: 365.826 | H64: 331.45 | I64: 760.143 | J64: 367.489 | K64: 284.486 | L64: 386.3 | M64: 366.923 | N64: 594.333 | O64: 374.996 | P64: 326.577 | Q64: 365.382 | R64: =SUM(C64:Q64) -> 6324.935
A65: 45624 | B65: GÁS | C65: 247.339 | D65: 26.88 | E65: 924.482 | F65: 608.003 | G65: 368.221 | H65: 333.415 | I65: 764.384 | J65: 368.486 | K65: 285.899 | L65: 387.104 | M65: 369.181 | N65: 595.227 | O65: 376.696 | P65: 326.577 | Q65: 367.225 | R65: =SUM(C65:Q65) -> 6349.119
A66: 45654 | B66: GÁS | C66: 247.339 | D66: 26.939 | E66: 929.304 | F66: 610.824 | G66: 370.915 | H66: 335.183 | I66: 768.314 | J66: 369.255 | K66: 287.374 | L66: 387.96 | M66: 370.999 | N66: 595.653 | O66: 378.181 | P66: 326.577 | Q66: 368.694 | R66: =SUM(C66:Q66) -> 6373.511
... A81: 46109 | B81: GÁS | C81: 247.339 | D81: 27.376 | E81: 989.347 | F81: 658.665 | G81: 402.255 | H81: 359.326 | I81: 837.636 | J81: 385.871 | K81: 307.803 | L81: 395.883 | M81: 394.264 | N81: 607.169 | O81: 434.643 | P81: 328.112 | Q81: 395.253 | R81: =SUM(C81:Q81) -> 6770.942
B82: (A) DIF. C/LEIT. ANT. | C82: =C81-C80 -> 0 | D82: =D81-D80 -> 0 | E82: =E81-E80 -> 2.741 | F82: =F81-F80 -> 4.059 | G82: =G81-G80 -> 2.429 | H82: =H81-H80 -> 1.414 | I82: =I81-I80 -> 4.82 | J82: =J81-J80 -> 1.213 | ... Q82: =Q81-Q80 -> 2.44 | R82: =SUM(C82:Q82) -> 25.826
B83: (B) DIF. ANT. | C83: =C80-C79 -> 0 | D83: =D80-D79 -> 0.015 | E83: =E80-E79 -> 4.487 | F83: =F80-F79 -> 3.78 | G83: =G80-G79 -> 1.534 | H83: =H80-H79 -> 1.642 | I83: =I80-I79 -> 4.851 | J83: =J80-J79 -> 1.19 | ... Q83: =Q80-Q79 -> 1.873 | R83: =SUM(C83:Q83) -> 26.068
B84: A (-) B | C84: =C82-C83 -> 0 | D84: =D82-D83 -> -0.015 | E84: =E82-E83 -> -1.746 | F84: =F82-F83 -> 0.279 | G84: =G82-G83 -> 0.895 | H84: =H82-H83 -> -0.228 | I84: =I82-I83 -> -0.031 | J84: =J82-J83 -> 0.023 | ... Q84: =Q82-Q83 -> 0.567 | R84: =SUM(C84:Q84) -> -0.242
B85: A (-) B ANTERIOR | C85: =(C80-C79)-(C79-C78) -> 0 | D85: =(D80-D79)-(D79-D78) -> 0.015 | E85: =(E80-E79)-(E79-E78) -> -0.196 | F85: =(F80-F79)-(F79-F78) -> 0.44 | G85: =(G80-G79)-(G79-G78) -> -0.786 | H85: =(H80-H79)-(H79-H78) -> 0.471 | I85: =(I80-I79)-(I79-I78) -> -0.043 | J85: =(J80-J79)-(J79-J78) -> 0.378 | ... Q85: =(Q80-Q79)-(Q79-Q78) -> 0.235 | R85: =SUM(C85:Q85) -> 0.164
B86: A (-) B ANTEANTERIOR | C86: =(C79-C78)-(C78-C77) -> 0 | D86: =(D79-D78)-(D78-D77) -> -0.012 | E86: =(E79-E78)-(E78-E77) -> 0.431 | F86: =(F79-F78)-(F78-F77) -> 0.027 | G86: =(G79-G78)-(G78-G77) -> 0.624 | H86: =(H79-H78)-(H78-H77) -> -0.304 | I86: =(I79-I78)-(I78-I77) -> 1.227 | J86: =(J79-J78)-(J78-J77) -> -0.289 | ... Q86: =(Q79-Q78)-(Q78-Q77) -> -0.617 | R86: =SUM(C86:Q86) -> -0.019
A99: XXXX | B99: LINHAS OCULTAS (ANTIGA TABELA "LANÇAMENTOS", USADA ATÉ 08/2025 NA PLANILHA PARA CONDÔMINOS) | H99: LINHAS OCULTAS (ANTIGA TABELA "LANÇAMENTOS", USADA ATÉ 08/2025 NA PLANILHA PARA CONDÔMINOS) | P99: LINHAS OCULTAS (ANTIGA TABELA "LANÇAMENTOS", USADA ATÉ 08/2025 NA PLANILHA PARA CONDÔMINOS)
A100: LANÇAMENTOS - AGOSTO/2025 | I100: MANTER ESTA TABELA, SOMENTE ATUALIZANDO-A MENSALMENTE COM OS DADOS DA TABELA "LANÇAMENTOS" DA PLANILHA "LANÇTºS, VRS. DEVIDOS" (ANOTAÇÕES DE 06 E 14/07/2025)
A101: DATA | B101: DESCRIÇÃO | G101: VALOR
A102: =A214 -> 45880 | B102: CONSERVADORA CAMPOS DE OLIVEIRA | G102: =G214 -> 1342.94
A103: =A215 -> 45880 | B103: FUNDO DE RESERVA (R$ 150,00 POR APTº) | G103: =G215-G215 -> 0
A104: =A216 -> 44967 | B104: DESPESAS BANCÁRIAS (BRADESCO, PIX DE ENCERRAMENTO) | G104: =G216 -> 0
A105: =A217 -> 45884 | B105: MANUTENÇÃO ELEVADOR - THYSSENKRUPP | G105: =G217 -> 1231.11
A106: =A217 -> 45884 | B106: CONTA DE ÁGUA DO CONDOMÍNIO | G106: =C145 -> 236.41
A107: =A219 -> 45887 | B107: CONTA DE LUZ DO CONDOMÍNIO (CEMIG) | G107: =G219 -> 440.76
A108: =A220 -> 45889 | B108: MINISTÉRIO DA FAZENDA- RET. FEDERAL INSS/PIS/COFINS/CSLL | G108: =G220 -> 226.01
A109: =A221 -> 45104 | B109: GÁS ABASTECIMENTO | G109: =G221-G221 -> 0
A110: =A222 -> 45833 | B110: AÇÃO CONTRA COPASA, CUSTAS DE RECURSO JUDICIAL | G110: =G222 -> 0
A111: =A223 -> 45834 | B111: ATA DE ELEIÇÃO DE NOVO SÍNDICO, REGISTRO NO CARTÓRIO | G111: =G223 -> 0
A112: =A224 -> 45870 | B112: LÂMPADAS 9W DE LED, 6 | G112: =G224 -> 24.6
A113: =A225 -> 45845 | B113: CADEADO E 2 CHAVES-RESERVA PARA CX. CORREIO DA GARAGEM | G113: =G225 -> 28.9
A114: =A226 -> 45692 | B114: LIVRO "REGISTRO DE OCORRÊNCIA DE ELEVADOR" | G114: =G226 -> 0
A115: =A227 -> 45803 | B115: SEGURO DO PRÉDIO, PARCELA 6ª/6 | G115: =G227 -> 0
A116: =A228 -> 45789 | B116: RECARGA ANUAL E REPARO DOS EXTINTORES | G116: =G228 -> 0
A117: =A229 -> 45897 | B117: HONORÁRIOS DA CONTADORA - MAYRA S. P. OLIVEIRA | G117: =G229 -> 151.6
A118: =A230 -> 45870 | B118: INTERNET PARA TRANSMISSÃO DE IMAGENS DAS CÂMERAS | G118: =G230 -> 65
G119: =G231 -> 0
G120: =G232 -> 0
G121: =G233 -> 0
G122: =G234 -> 0
A123: TOTAL LANÇAMENTOS | G123: =SUM(G102:G122) -> 3747.33
A124: RATEIO PARCIAL | G124: =ROUND(G123/14,2) -> 267.67
A125: RATEIO PARCIAL DO SÍNDICO (RP/13) | G125: =ROUND(G124/13,2) -> 20.59 | I125: ESTE DEMONSTRATIVO ESTÁ SENDO ATUALIZADO E "ARQUIVADO" NA TABELA "RATEIO MENSAL (INFORMAÇÕES ADICIONAIS AOS LANÇAMENTOS NA PLANILHA PARA CONDÔMINOS)" DA PLANILHA "LANÇTºS, VRS. DEVIDOS" (ANOTAÇÃO DE 14/07/2025)
A126: FUNDO DE RESERVA | G126: 150
...

Sheet LANÇTºS
A1: =AY1 -> LANÇAMENTOS, TABELA CRIADA EM 07/07/2025 (OS ITENS "RATEIO PARCIAL", "RATEIO PARCIAL DO SÍNDICO (RP/13)" E "RATEIO FINAL" NÃO SÃO NECESSÁRIOS AQUI, POIS SÃO FÓRMULAS QUE DEPENDEM DIRETAMENTE DOS VALORES AQUI INFORMADOS, BASTANDO USAR A BASE DA PLANILHA ATUAL) | AU1: PREENCHTº AZUL: A CONFIRMAR | AY1: LANÇAMENTOS, TABELA CRIADA EM 07/07/2025 (OS ITENS "RATEIO PARCIAL", "RATEIO PARCIAL DO SÍNDICO (RP/13)" E "RATEIO FINAL" NÃO SÃO NECESSÁRIOS AQUI, POIS SÃO FÓRMULAS QUE DEPENDEM DIRETAMENTE DOS VALORES AQUI INFORMADOS, BASTANDO USAR A BASE DA PLANILHA ATUAL) | AZ1: COMPARAÇÃO DAS DESCRIÇÕES (DESTACAR OS ITENS QUE NÃO EXISTEM NA PRESENTE REF. OU NAS REF. ANTERIORES, PARA ZERÁ-LOS. ACRESCENTAR OS ITENS AINDA FALTOSOS NA REF. ATUAL, SEMPRE ZERANDO "VALOR" E "DATA" NAS REF. ANTERIORES)
A2: =AY2 -> DESCRIÇÃO | B2: REF. | C2: VALOR | D2: DATA | E2: INFORMAR NA PLAN. P/CONDÔM. | F2: REF. | G2: VALOR | H2: DATA | I2: INFORMAR NA PLAN. P/CONDÔM. | J2: REF. | K2: VALOR | L2: DATA | M2: INFORMAR NA PLAN. P/CONDÔM. | N2: REF. | O2: VALOR | P2: DATA | Q2: INFORMAR NA PLAN. P/CONDÔM. | R2: REF. | S2: VALOR | T2: DATA | U2: INFORMAR NA PLAN. P/CONDÔM. | V2: REF. | W2: VALOR | X2: DATA | Y2: INFORMAR NA PLAN. P/CONDÔM. | Z2: REF. | AA2: VALOR | AB2: DATA | AC2: INFORMAR NA PLAN. P/CONDÔM. | AD2: REF. | AE2: VALOR | AF2: DATA | AG2: INFORMAR NA PLAN. P/CONDÔM. | AH2: REF. | AI2: VALOR | AJ2: DATA | AK2: INFORMAR NA PLAN. P/CONDÔM. (+ DESCRIÇÃO COMPLEMENTAR) | AL2: REF. | AM2: VALOR | AN2: DATA | AO2: INFORMAR NA PLAN. P/CONDÔM. (+ DESCRIÇÃO COMPLEMENTAR) | AP2: REF. | AQ2: VALOR | AR2: DATA | AS2: INFORMAR NA PLAN. P/CONDÔM. (+ DESCRIÇÃO COMPLEMENTAR) | AT2: REF. | AU2: VALOR | AV2: DATA | AW2: INFORMAR NA PLAN. P/CONDÔM. (+ DESCRIÇÃO COMPLEMENTAR) | AY2: DESCRIÇÃO
A3: =AY3 -> CONSERVADORA CAMPOS DE OLIVEIRA | B3: 45778 | C3: 1342.94 | D3: 45789 | E3: SIM | F3: 45809 | G3: 1342.94 | H3: 45818 | I3: SIM | J3: 45839 | K3: 1342.94 | L3: 45848 | M3: SIM | N3: 45870 | O3: 1342.94 | P3: 45880 | Q3: SIM | R3: 45901 | S3: 1342.94 | T3: 45910 | U3: SIM | V3: 45931 | W3: 1342.94 | X3: 45940 | Y3: SIM | Z3: 45962 | AA3: 1342.94 | AB3: 45971 | AC3: SIM | AD3: 45992 | AE3: 1342.94 | AF3: 46001 | AG3: SIM | AH3: 46023 | AI3: 1342.94 | AJ3: 46034 | AK3: SIM | AL3: 46054 | AM3: 1443.66 | AN3: 46063 | AO3: SIM | AP3: 46082 | AQ3: 1443.66 | AR3: 46091 | AS3: SIM | AT3: 46113 | AU3: 1443.66 | AV3: 46122 | AW3: SIM | AY3: CONSERVADORA CAMPOS DE OLIVEIRA | AZ3: =A3=AY3 -> TRUE
A4: =AY4 -> MANUTENÇÃO ELEVADOR - THYSSENKRUPP | B4: 45778 | C4: 1138.65 | D4: 45792 | E4: SIM | F4: 45809 | G4: 1334.14 | H4: 45824 | I4: SIM | J4: 45839 | K4: 1231.11 | L4: 45853 | M4: SIM | N4: 45870 | O4: 1231.11 | P4: 45888 | Q4: SIM | R4: 45901 | S4: 1231.11 | T4: 45915 | U4: SIM | V4: 45931 | W4: 1231.11 | X4: 45945 | Y4: SIM | Z4: 45962 | AA4: 1231.11 | AB4: 45978 | AC4: SIM | AD4: 45992 | AE4: 1231.11 | AF4: 46006 | AG4: SIM | AH4: 46023 | AI4: 1231.11 | AJ4: 46037 | AK4: SIM | AL4: 46054 | AM4: 1231.11 | AN4: 46068 | AO4: SIM | AP4: 46082 | AQ4: 1231.11 | AR4: 46097 | AS4: SIM | AT4: 46113 | AU4: 1231.11 | AV4: 46127 | AW4: SIM | AY4: MANUTENÇÃO ELEVADOR - THYSSENKRUPP | AZ4: =A4=AY4 -> TRUE
A5: =AY5 -> CONTA DE ÁGUA DO CONDOMÍNIO (A SER RATEADA ENTRE OS CONDÔMINOS) | B5: 45778 | C5: ='VRS. DEVIDOS E OUTROS'!C4 -> 0 | D5: NÃO | E5: NÃO - O CONSUMO DO CONDOMÍNIO REFERENTE À LEITURA DE 24/04/25 FOI CONSIDERADO NULO PARA O FIM DA PRESENTE APURAÇÃO (JÁ QUE O CONSUMO TOTAL DOS CONDÔMINOS SUPEROU O CONSUMO INFORMADO NA CONTA DA COPASA), EM VISTA DO AJUSTE QUE FOI FEITO EM 04/04/25 NA CONTA ANTERIOR, APURADA ANTERIORMENTE COM BASE NA MÉDIA DE CONSUMO | F5: 45809 | G5: ='VRS. DEVIDOS E OUTROS'!C11 -> 429.47 | H5: ='MEDIÇÕES E TABELAS'!AW30 -> 45824 | I5: SIM - VALOR A SER RATEADO ENTRE OS CONDÔMINOS | J5: 45839 | K5: ='VRS. DEVIDOS E OUTROS'!C18 -> 0 | L5: NÃO | M5: NÃO - O CONSUMO DO CONDOMÍNIO REFERENTE À LEITURA DE 24/06/25 FOI CONSIDERADO NULO PARA O FIM DA PRESENTE APURAÇÃO (JÁ QUE O CONSUMO TOTAL DOS CONDÔMINOS SUPEROU O CONSUMO INFORMADO NA CONTA DA COPASA), PARECE QUE FOI FEITA LEITURA ERRADA PELA COPASA NO HIDRÔMETRO... | N5: 45870 | O5: ='VRS. DEVIDOS E OUTROS'!C25 -> 0 | P5: NÃO | Q5: NÃO - O TOTAL DA LEITURA DE 24/06/25 FOI USADO (E DEPOIS ZERADO) PARA A PRESENTE APURAÇÃO DO CONSUMO DO CONDOMÍNIO, UMA VEZ QUE A LEITURA ATUAL NA CONTA DA COPASA (DE 22/07/25) ESTÁ INCORRETA (PARA MENOR!!!), E QUE NÃO FOI ATENDIDA ATÉ O DIA 08/08/25 MINHA SOLICITAÇÃO DE CORREÇÃO DA LEITURA JUNTO À COPASA. | R5: 45901 | S5: ='MEDIÇÕES E TABELAS'!AQ34 -> 102.13 | T5: ='MEDIÇÕES E TABELAS'!AW33 -> 45915 | U5: SIM - VALOR A SER RATEADO ENTRE OS CONDÔMINOS | V5: 45931 | W5: ='MEDIÇÕES E TABELAS'!AQ37 -> 348.46 | X5: ='MEDIÇÕES E TABELAS'!AW36 -> 45945 | Y5: SIM - VALOR A SER RATEADO ENTRE OS CONDÔMINOS | Z5: 45962 | AA5: ='MEDIÇÕES E TABELAS'!AQ38 -> 351.47 | AB5: ='MEDIÇÕES E TABELAS'!AW37 -> 45978 | AC5: 45978 | AD5: 45992 | AE5: ='MEDIÇÕES E TABELAS'!AQ39 -> 346.4 | AF5: ='MEDIÇÕES E TABELAS'!AW38 -> 46006 | AG5: SIM | AH5: 46023 | AI5: ='MEDIÇÕES E TABELAS'!AQ40 -> 0 | AJ5: ='MEDIÇÕES E TABELAS'!AW39 -> 46037 | AK5: NÃO | AL5: 46054 | AM5: ='MEDIÇÕES E TABELAS'!AQ41 -> 0 | AN5: ='MEDIÇÕES E TABELAS'!AW40 -> 46071 | AO5: NÃO | AP5: 46082 | AQ5: ='MEDIÇÕES E TABELAS'!AQ42 -> 0 | AR5: ='MEDIÇÕES E TABELAS'!AW41 -> 46099 | AS5: NÃO | AT5: 46113 | AU5: ='MEDIÇÕES E TABELAS'!AQ43 -> 236.41 | AV5: ='MEDIÇÕES E TABELAS'!AW42 -> 46127 | AW5: SIM | AY5: CONTA DE ÁGUA DO CONDOMÍNIO (A SER RATEADA ENTRE OS CONDÔMINOS) | AZ5: =A5=AY5 -> TRUE
A6: =AY6 -> CONTA DE LUZ DO CONDOMÍNIO (CEMIG) | B6: 45778 | C6: 311.36 | D6: 45796 | E6: SIM | F6: 45809 | G6: 333.58 | H6: 45825 | I6: SIM | J6: 45839 | K6: 378.75 | L6: 45855 | M6: SIM | N6: 45870 | O6: 440.76 | P6: 45887 | Q6: SIM | R6: 45901 | S6: 487.7 | T6: 45917 | U6: SIM | V6: 45931 | W6: 467.79 | X6: 45947 | Y6: SIM | Z6: 45962 | AA6: 475.91 | AB6: 45978 | AC6: SIM | AD6: 45992 | AE6: 399.98 | AF6: 46008 | AG6: SIM | AH6: 46023 | AI6: 429.59 | AJ6: 46041 | AK6: SIM | AL6: 46054 | AM6: 470.4 | AN6: 46070 | AO6: SIM | AP6: 46082 | AQ6: 404.07 | AR6: 46098 | AS6: SIM | AT6: 46113 | AU6: 429.96 | AV6: 46129 | AW6: SIM | AY6: CONTA DE LUZ DO CONDOMÍNIO (CEMIG) | AZ6: =A6=AY6 -> TRUE
A7: =AY7 -> RETENÇÕES FEDERAIS / MUNICIPAIS DE TRIBUTOS A RECOLHER | B7: 45778 | C7: 221.5 | D7: 45797 | E7: SIM | F7: 45809 | G7: 226.01 | H7: 45828 | I7: SIM | J7: 45839 | K7: 226.01 | L7: 45856 | M7: SIM | N7: 45870 | O7: 226.01 | P7: 45889 | Q7: SIM | R7: 45901 | S7: 226.01 | T7: 45919 | U7: SIM | V7: 45931 | W7: =226.01+21.16+19.23 -> 266.4 | X7: 45950 | Y7: SIM | Z7: 45962 | AA7: 226.01 | AB7: 45981 | AC7: SIM | AD7: 45992 | AE7: 226.01 | AF7: 46010 | AG7: SIM | AH7: 46023 | AI7: =226.01+45 -> 271.01 | AJ7: 10 E 20/01/26 | AK7: SIM | AL7: 46054 | AM7: 238.46 | AN7: 46073 | AO7: SIM - O VALOR CORRETO É $226,01, E NÃO $238,46, ESTE ÚLTIMO CALCULADO COM BASE NO REAJUSTE DA MENSALIDADE DA CONSERVADORA, QUE SÓ VIGORARÁ A PARTIR DA COMPETÊNCIA 02/2026, COM RECOLHTº EM 03/2026 | AP7: 46082 | AQ7: 238.45 | AR7: 46101 | AS7: SIM | AT7: 46113 | AU7: 238.45 | AV7: 46132 | AW7: SIM | AY7: RETENÇÕES FEDERAIS / MUNICIPAIS DE TRIBUTOS A RECOLHER | AZ7: =A7=AY7 -> TRUE
A8: =AY8 -> SEGURO DO PRÉDIO | B8: 45778 | C8: 224.69 | D8: 45772 | E8: SIM - PARC. 5ª/6 | F8: 45809 | G8: 224.69 | H8: 45803 | I8: SIM - PARC. 6ª/6 | J8: 45839 | K8: 0 | L8: NÃO | M8: NÃO | N8: 45870 | O8: 0 | P8: NÃO | Q8: NÃO | R8: 45901 | S8: 0 | T8: NÃO | U8: NÃO | V8: 45931 | W8: 0 | X8: NÃO | Y8: NÃO | Z8: 45962 | AA8: 0 | AB8: NÃO | AC8: NÃO | AD8: 45992 | AE8: 0 | AF8: NÃO | AG8: NÃO | AH8: 46023 | AI8: 259.07 | AJ8: 46017 | AK8: SIM - PARCELA 1ª/6 | AL8: 46054 | AM8: 259.78 | AN8: 46051 | AO8: SIM - PARCELA 2ª/6 | AP8: 46082 | AQ8: 259.06 | AR8: 46078 | AS8: SIM - PARCELA 3ª/6 | AT8: 46113 | AU8: 259.06 | AV8: 46106 | AW8: SIM - PARCELA 4ª/6 | AY8: SEGURO DO PRÉDIO | AZ8: =A8=AY8 -> TRUE
A9: =AY9 -> RECARGA ANUAL E REPARO DOS EXTINTORES | B9: 45778 | C9: 608 | D9: 45789 | E9: SIM | F9: 45809 | G9: 0 | H9: NÃO | I9: NÃO | J9: 45839 | K9: 0 | L9: NÃO | M9: NÃO | N9: 45870 | O9: 0 | P9: NÃO | Q9: NÃO | R9: 45901 | S9: 0 | T9: NÃO | U9: NÃO | V9: 45931 | W9: 0 | X9: NÃO | Y9: NÃO | Z9: 45962 | AA9: 0 | AB9: NÃO | AC9: NÃO | AD9: 45992 | AE9: 0 | AF9: NÃO | AG9: NÃO | AH9: 46023 | AI9: 0 | AJ9: NÃO | AK9: NÃO | AL9: 46054 | AM9: 0 | AN9: NÃO | AO9: NÃO | AP9: 46082 | AQ9: 0 | AR9: NÃO | AS9: NÃO | AT9: 46113 | AU9: 0 | AV9: NÃO | AW9: NÃO | AY9: RECARGA ANUAL E REPARO DOS EXTINTORES | AZ9: =A9=AY9 -> TRUE
A10: =AY10 -> HONORÁRIOS DA CONTADORA - MAYRA S. P. OLIVEIRA | B10: 45778 | C10: 151.6 | D10: 45805 | E10: SIM | F10: 45809 | G10: 151.6 | H10: 45836 | I10: SIM | J10: 45839 | K10: 151.6 | L10: 45866 | M10: SIM | N10: 45870 | O10: 151.6 | P10: 45897 | Q10: SIM | R10: 45901 | S10: 151.6 | T10: 45929 | U10: SIM | V10: 45931 | W10: 151.6 | X10: 45958 | Y10: SIM | Z10: 45962 | AA10: 151.6 | AB10: 45989 | AC10: SIM | AD10: 45992 | AE10: 151.6 | AF10: 46020 | AG10: SIM | AH10: 46023 | AI10: 151.6 | AJ10: 46050 | AK10: SIM | AL10: 46054 | AM10: 163 | AN10: 46080 | AO10: SIM | AP10: 46082 | AQ10: 162 | AR10: 46111 | AS10: SIM | AT10: 46113 | AU10: 162 | AV10: 46140 | AW10: SIM | AY10: HONORÁRIOS DA CONTADORA - MAYRA S. P. OLIVEIRA | AZ10: =A10=AY10 -> TRUE
A11: =AY11 -> INTERNET PARA TRANSMISSÃO DE IMAGENS DAS CÂMERAS | B11: 45778 | C11: 65 | D11: 45778 | E11: SIM | F11: 45809 | G11: 65 | H11: 45810 | I11: SIM | J11: 45839 | K11: 65 | L11: 45839 | M11: SIM | N11: 45870 | O11: 65 | P11: 45870 | Q11: SIM | R11: 45901 | S11: 65 | T11: 45901 | U11: SIM | V11: 45931 | W11: 65 | X11: 45931 | Y11: SIM | Z11: 45962 | AA11: 65 | AB11: 45962 | AC11: SIM | AD11: 45992 | AE11: 65 | AF11: 45993 | AG11: SIM | AH11: 46023 | AI11: 65 | AJ11: 46024 | AK11: SIM | AL11: 46054 | AM11: 65 | AN11: 46055 | AO11: SIM | AP11: 46082 | AQ11: 65 | AR11: 46083 | AS11: SIM | AT11: 46113 | AU11: 65 | AV11: 46113 | AW11: SIM | AY11: INTERNET PARA TRANSMISSÃO DE IMAGENS DAS CÂMERAS | AZ11: =A11=AY11 -> TRUE
A12: =AY12 -> CADEADO | B12: 45778 | C12: 0 | D12: NÃO | E12: NÃO | F12: 45809 | G12: 0 | H12: NÃO | I12: NÃO | J12: 45839 | K12: 0 | L12: NÃO | M12: NÃO | N12: 45870 | O12: 14.9 | P12: 45845 | Q12: SIM - PARA CX. CORREIO DA GARAGEM | R12: 45901 | S12: 0 | T12: NÃO | U12: NÃO | V12: 45931 | W12: 0 | X12: NÃO | Y12: NÃO | Z12: 45962 | AA12: 0 | AB12: NÃO | AC12: NÃO | AD12: 45992 | AE12: 0 | AF12: NÃO | AG12: NÃO | AH12: 46023 | AI12: 0 | AJ12: NÃO | AK12: NÃO | AL12: 46054 | AM12: 0 | AN12: NÃO | AO12: NÃO | AP12: 46082 | AQ12: 0 | AR12: NÃO | AS12: NÃO | AT12: 46113 | AU12: 0 | AV12: NÃO | AW12: NÃO | AY12: CADEADO | AZ12: =A12=AY12 -> TRUE
A13: =AY13 -> CHAVES RESERVA | B13: 45778 | C13: 0 | D13: NÃO | E13: NÃO | F13: 45809 | G13: 0 | H13: NÃO | I13: NÃO | J13: 45839 | K13: 0 | L13: NÃO | M13: NÃO | N13: 45870 | O13: 14 | P13: 45845 | Q13: SIM - 2, PARA CADEADO DA CX. CORREIO DA GARAGEM | R13: 45901 | S13: 0 | T13: NÃO | U13: NÃO | V13: 45931 | W13: 0 | X13: NÃO | Y13: NÃO | Z13: 45962 | AA13: 0 | AB13: NÃO | AC13: NÃO | AD13: 45992 | AE13: 0 | AF13: NÃO | AG13: NÃO | AH13: 46023 | AI13: 0 | AJ13: NÃO | AK13: NÃO | AL13: 46054 | AM13: 0 | AN13: NÃO | AO13: NÃO | AP13: 46082 | AQ13: 0 | AR13: NÃO | AS13: NÃO | AT13: 46113 | AU13: 0 | AV13: NÃO | AW13: NÃO | AY13: CHAVES RESERVA | AZ13: =A13=AY13 -> TRUE
A14: =AY14 -> LÂMPADAS 9W DE LED | B14: 45778 | C14: 0 | D14: NÃO | E14: NÃO | F14: 45809 | G14: 0 | H14: NÃO | I14: NÃO | J14: 45839 | K14: 0 | L14: NÃO | M14: NÃO | N14: 45870 | O14: 24.6 | P14: 45870 | Q14: SIM - 6 UNIDADES | R14: 45901 | S14: 0 | T14: NÃO | U14: NÃO | V14: 45931 | W14: 0 | X14: NÃO | Y14: NÃO | Z14: 45962 | AA14: 0 | AB14: NÃO | AC14: NÃO | AD14: 45992 | AE14: 0 | AF14: NÃO | AG14: NÃO | AH14: 46023 | AI14: 0 | AJ14: NÃO | AK14: NÃO | AL14: 46054 | AM14: 0 | AN14: NÃO | AO14: NÃO | AP14: 46082 | AQ14: 0 | AR14: NÃO | AS14: NÃO | AT14: 46113 | AU14: 0 | AV14: NÃO | AW14: NÃO | AY14: LÂMPADAS 9W DE LED | AZ14: =A14=AY14 -> TRUE
A15: =AY15 -> SERVIÇOS DE SERRALHEIRO NO PORTÃO DA GARAGEM | B15: 45778 | C15: 0 | D15: NÃO | E15: NÃO | F15: 45809 | G15: 0 | H15: NÃO | I15: NÃO | J15: 45839 | K15: 0 | L15: NÃO | M15: NÃO | N15: 45870 | O15: 0 | P15: NÃO | Q15: NÃO | R15: 45901 | S15: 700 | T15: 45887 | U15: SIM - E NO PORTEIRO ELETRÔNICO | V15: 45931 | W15: 0 | X15: NÃO | Y15: NÃO | Z15: 45962 | AA15: 0 | AB15: NÃO | AC15: NÃO | AD15: 45992 | AE15: 0 | AF15: NÃO | AG15: NÃO | AH15: 46023 | AI15: 0 | AJ15: NÃO | AK15: NÃO | AL15: 46054 | AM15: 0 | AN15: NÃO | AO15: NÃO | AP15: 46082 | AQ15: 0 | AR15: NÃO | AS15: NÃO | AT15: 46113 | AU15: 0 | AV15: NÃO | AW15: NÃO | AY15: SERVIÇOS DE SERRALHEIRO NO PORTÃO DA GARAGEM | AZ15: =A15=AY15 -> TRUE
A16: =AY16 -> MATERIAL PARA PINTURA | B16: 45778 | C16: 0 | D16: NÃO | E16: NÃO | F16: 45809 | G16: 0 | H16: NÃO | I16: NÃO | J16: 45839 | K16: 0 | L16: NÃO | M16: NÃO | N16: 45870 | O16: 0 | P16: NÃO | Q16: NÃO | R16: 45901 | S16: 0 | T16: NÃO | U16: NÃO | V16: 45931 | W16: 74.95 | X16: 45908 | Y16: SIM - EM PARTE DO PORTÃO DA GARAGEM E ELEVADOR | Z16: 45962 | AA16: 0 | AB16: NÃO | AC16: NÃO | AD16: 45992 | AE16: 0 | AF16: NÃO | AG16: NÃO | AH16: 46023 | AI16: 0 | AJ16: NÃO | AK16: NÃO | AL16: 46054 | AM16: 0 | AN16: NÃO | AO16: NÃO | AP16: 46082 | AQ16: 0 | AR16: NÃO | AS16: NÃO | AT16: 46113 | AU16: 0 | AV16: NÃO | AW16: NÃO | AY16: MATERIAL PARA PINTURA | AZ16: =A16=AY16 -> TRUE
A17: =AY17 -> ATA DE ELEIÇÃO DE NOVO SÍNDICO, REGISTRO NO CARTÓRIO | B17: 45778 | C17: 0 | D17: NÃO | E17: NÃO | F17: 45809 | G17: 0 | H17: NÃO | I17: NÃO | J17: 45839 | K17: 120.9 | L17: 45834 | M17: SIM | N17: 45870 | O17: 0 | P17: NÃO | Q17: NÃO | R17: 45901 | S17: 0 | T17: NÃO | U17: NÃO | V17: 45931 | W17: 0 | X17: NÃO | Y17: NÃO | Z17: 45962 | AA17: 0 | AB17: NÃO | AC17: NÃO | AD17: 45992 | AE17: 0 | AF17: NÃO | AG17: NÃO | AH17: 46023 | AI17: 0 | AJ17: NÃO | AK17: NÃO | AL17: 46054 | AM17: 0 | AN17: NÃO | AO17: NÃO | AP17: 46082 | AQ17: 0 | AR17: NÃO | AS17: NÃO | AT17: 46113 | AU17: 0 | AV17: NÃO | AW17: NÃO | AY17: ATA DE ELEIÇÃO DE NOVO SÍNDICO, REGISTRO NO CARTÓRIO | AZ17: =A17=AY17 -> TRUE
A18: =AY18 -> AÇÃO CONTRA COPASA, CUSTAS DE RECURSO JUDICIAL | B18: 45778 | C18: 0 | D18: NÃO | E18: NÃO | F18: 45809 | G18: 0 | H18: NÃO | I18: NÃO | J18: 45839 | K18: 477.87 | L18: 45833 | M18: SIM | N18: 45870 | O18: 0 | P18: NÃO | Q18: NÃO | R18: 45901 | S18: 0 | T18: NÃO | U18: NÃO | V18: 45931 | W18: 0 | X18: NÃO | Y18: NÃO | Z18: 45962 | AA18: 0 | AB18: NÃO | AC18: NÃO | AD18: 45992 | AE18: 0 | AF18: NÃO | AG18: NÃO | AH18: 46023 | AI18: 0 | AJ18: NÃO | AK18: NÃO | AL18: 46054 | AM18: 0 | AN18: NÃO | AO18: NÃO | AP18: 46082 | AQ18: 0 | AR18: NÃO | AS18: NÃO | AT18: 46113 | AU18: 0 | AV18: NÃO | AW18: NÃO | AY18: AÇÃO CONTRA COPASA, CUSTAS DE RECURSO JUDICIAL | AZ18: =A18=AY18 -> TRUE
A19: =AY19 -> XEROX PROJ.ELÉTRICO P/RENOV.AUTO DE VISTORIA/CORPO DE BOMBEIROS | B19: 45778 | C19: 0 | D19: NÃO | E19: NÃO | F19: 45809 | G19: 0 | H19: NÃO | I19: NÃO | J19: 45839 | K19: 0 | L19: NÃO | M19: NÃO | N19: 45870 | O19: 0 | P19: NÃO | Q19: NÃO | R19: 45901 | S19: 0 | T19: NÃO | U19: NÃO | V19: 45931 | W19: 36.9 | X19: 45923 | Y19: SIM | Z19: 45962 | AA19: 0 | AB19: NÃO | AC19: NÃO | AD19: 45992 | AE19: 0 | AF19: NÃO | AG19: NÃO | AH19: 46023 | AI19: 0 | AJ19: NÃO | AK19: NÃO | AL19: 46054 | AM19: 0 | AN19: NÃO | AO19: NÃO | AP19: 46082 | AQ19: 0 | AR19: NÃO | AS19: NÃO | AT19: 46113 | AU19: 0 | AV19: NÃO | AW19: NÃO | AY19: XEROX PROJ.ELÉTRICO P/RENOV.AUTO DE VISTORIA/CORPO DE BOMBEIROS | AZ19: =A19=AY19 -> TRUE
A20: =AY20 -> CONSERTO DA CERCA ELÉTRICA | B20: 45778 | C20: 0 | D20: NÃO | E20: NÃO | F20: 45809 | G20: 0 | H20: NÃO | I20: NÃO | J20: 45839 | K20: 0 | L20: NÃO | M20: NÃO | N20: 45870 | O20: 0 | P20: NÃO | Q20: NÃO | R20: 45901 | S20: 0 | T20: NÃO | U20: NÃO | V20: 45931 | W20: 0 | X20: NÃO | Y20: NÃO | Z20: 45962 | AA20: 0 | AB20: NÃO | AC20: NÃO | AD20: 45992 | AE20: 120 | AF20: 45968 | AG20: SIM | AH20: 46023 | AI20: 0 | AJ20: NÃO | AK20: NÃO | AL20: 46054 | AM20: 0 | AN20: NÃO | AO20: NÃO | AP20: 46082 | AQ20: 0 | AR20: NÃO | AS20: NÃO | AT20: 46113 | AU20: 0 | AV20: NÃO | AW20: NÃO | AY20: CONSERTO DA CERCA ELÉTRICA | AZ20: =A20=AY20 -> TRUE
A21: =AY21 -> LUMINÁRIA DE EMERGÊNCIA | B21: 45778 | C21: 0 | D21: NÃO | E21: NÃO | F21: 45809 | G21: 0 | H21: NÃO | I21: NÃO | J21: 45839 | K21: 0 | L21: NÃO | M21: NÃO | N21: 45870 | O21: 0 | P21: NÃO | Q21: NÃO | R21: 45901 | S21: 0 | T21: NÃO | U21: NÃO | V21: 45931 | W21: 0 | X21: NÃO | Y21: NÃO | Z21: 45962 | AA21: 0 | AB21: NÃO | AC21: NÃO | AD21: 45992 | AE21: 17.9 | AF21: 45993 | AG21: SIM - 1 UNIDADE | AH21: 46023 | AI21: 0 | AJ21: NÃO | AK21: NÃO | AL21: 46054 | AM21: 0 | AN21: NÃO | AO21: NÃO | AP21: 46082 | AQ21: 0 | AR21: NÃO | AS21: NÃO | AT21: 46113 | AU21: 0 | AV21: NÃO | AW21: NÃO | AY21: LUMINÁRIA DE EMERGÊNCIA | AZ21: =A21=AY21 -> TRUE
A22: =AY22 -> RECUPERAÇÃO DA PAREDE DAS VAGAS 402 E 601 FUNDOS | B22: 45778 | C22: 0 | D22: NÃO | E22: NÃO | F22: 45809 | G22: 0 | H22: NÃO | I22: NÃO | J22: 45839 | K22: 0 | L22: NÃO | M22: NÃO | N22: 45870 | O22: 0 | P22: NÃO | Q22: NÃO | R22: 45901 | S22: 0 | T22: NÃO | U22: NÃO | V22: 45931 | W22: 0 | X22: NÃO | Y22: NÃO | Z22: 45962 | AA22: 0 | AB22: NÃO | AC22: NÃO | AD22: 45992 | AE22: 124 | AF22: 45993 | AG22: SIM - MATERIAL | AH22: 46023 | AI22: 0 | AJ22: NÃO | AK22: NÃO | AL22: 46054 | AM22: 0 | AN22: NÃO | AO22: NÃO | AP22: 46082 | AQ22: 0 | AR22: NÃO | AS22: NÃO | AT22: 46113 | AU22: 0 | AV22: NÃO | AW22: NÃO | AY22: RECUPERAÇÃO DA PAREDE DAS VAGAS 402 E 601 FUNDOS | AZ22: =A22=AY22 -> TRUE
A23: =AY23 -> COPIAR/COLAR ESTA LINHA PARA NOVA DESPESA. ACIMA DESTA LINHA: INFORMAR NA PLANILHA P/CONDÔMINOS.; ABAIXO: NÃO INFORMAR NA PLANILHA P/CONDÔMINOS (DESCONTAR NO FUNDO DE RESERVA) | B23: 45778 | C23: 0 | D23: NÃO | E23: NÃO | F23: 45809 | G23: 0 | H23: NÃO | I23: NÃO | J23: 45839 | K23: 0 | L23: NÃO | M23: NÃO | N23: 45870 | O23: 0 | P23: NÃO | Q23: NÃO | R23: 45901 | S23: 0 | T23: NÃO | U23: NÃO | V23: 45931 | W23: 0 | X23: NÃO | Y23: NÃO | Z23: 45962 | AA23: 0 | AB23: NÃO | AC23: NÃO | AD23: 45992 | AE23: 0 | AF23: NÃO | AG23: NÃO | AH23: 46023 | AI23: 0 | AJ23: NÃO | AK23: NÃO | AL23: 46054 | AM23: 0 | AN23: NÃO | AO23: NÃO | AP23: 46082 | AQ23: 0 | AR23: NÃO | AS23: NÃO | AT23: 46113 | AU23: 0 | AV23: NÃO | AW23: NÃO | AY23: COPIAR/COLAR ESTA LINHA PARA NOVA DESPESA. ACIMA DESTA LINHA: INFORMAR NA PLANILHA P/CONDÔMINOS.; ABAIXO: NÃO INFORMAR NA PLANILHA P/CONDÔMINOS (DESCONTAR NO FUNDO DE RESERVA) | AZ23: =A23=AY23 -> TRUE
A24: =AY24 -> CONTA DE ÁGUA DO CONDOMÍNIO, VALOR TOTAL A PAGAR | B24: 45778 | C24: ='MEDIÇÕES E TABELAS'!AZ30 -> 3043.18 | D24: ='MEDIÇÕES E TABELAS'!AW30 -> 45824 | E24: NÃO | F24: 45809 | G24: ='MEDIÇÕES E TABELAS'!AZ31 -> 4380.41 | H24: ='MEDIÇÕES E TABELAS'!AW31 -> 45853 | I24: NÃO | J24: 45839 | K24: ='MEDIÇÕES E TABELAS'!AZ32 -> 3870.33 | L24: ='MEDIÇÕES E TABELAS'!AW32 -> 45887 | M24: NÃO | N24: 45870 | O24: ='MEDIÇÕES E TABELAS'!AZ33 -> 650.78 | P24: ='MEDIÇÕES E TABELAS'!AW33 -> 45915 | Q24: NÃO | R24: 45901 | S24: ='MEDIÇÕES E TABELAS'!AZ36 -> 5204.82 | T24: ='MEDIÇÕES E TABELAS'!AW36 -> 45945 | U24: NÃO | V24: 45931 | W24: ='MEDIÇÕES E TABELAS'!AZ37 -> 3715.89 | X24: ='MEDIÇÕES E TABELAS'!AW37 -> 45978 | Y24: NÃO | Z24: 45962 | AA24: ='MEDIÇÕES E TABELAS'!AZ38 -> 3062.91 | AB24: ='MEDIÇÕES E TABELAS'!AW38 -> 46006 | AC24: NÃO | AD24: 45992 | AE24: ='MEDIÇÕES E TABELAS'!AZ39 -> 3466.72 | AF24: ='MEDIÇÕES E TABELAS'!AW39 -> 46037 | AG24: NÃO | AH24: 46023 | AI24: ='MEDIÇÕES E TABELAS'!AZ40 -> 2101.43 | AJ24: ='MEDIÇÕES E TABELAS'!AW40 -> 46071 | AK24: NÃO | AL24: 46054 | AM24: ='MEDIÇÕES E TABELAS'!AZ41 -> 997.74 | AN24: ='MEDIÇÕES E TABELAS'!AW41 -> 46099 | AO24: NÃO | AP24: 46082 | AQ24: ='MEDIÇÕES E TABELAS'!AZ42 -> 1010.35 | AR24: ='MEDIÇÕES E TABELAS'!AW42 -> 46127 | AS24: NÃO | AT24: 46113 | AU24: ='MEDIÇÕES E TABELAS'!AZ43 -> 2943.7 | AV24: ='MEDIÇÕES E TABELAS'!AW43 -> 46157 | AW24: NÃO | AY24: CONTA DE ÁGUA DO CONDOMÍNIO, VALOR TOTAL A PAGAR | AZ24: =A24=AY24 -> TRUE
A25: =AY25 -> GÁS ABASTECIMENTO (RETIRAR VALOR DO SALDO BANCÁRIO, E NÃO DO FUNDO DE RESERVA. É COBRADO DE CADA CONDÔMINO POR RATEIO, CONF. PLANILHA "VALORES DEVIDOS POR UNIDADE") | B25: 45778 | C25: 0 | D25: NÃO | E25: NÃO | F25: 45809 | G25: 4277.19 | H25: 45835 | I25: NÃO | J25: 45839 | K25: 0 | L25: NÃO | M25: NÃO | N25: 45870 | O25: 0 | P25: NÃO | Q25: NÃO | R25: 45901 | S25: 0 | T25: NÃO | U25: NÃO | V25: 45931 | W25: 0 | X25: NÃO | Y25: NÃO | Z25: 45962 | AA25: 0 | AB25: NÃO | AC25: NÃO | AD25: 45992 | AE25: 0 | AF25: NÃO | AG25: NÃO | AH25: 46023 | AI25: 0 | AJ25: NÃO | AK25: NÃO | AL25: 46054 | AM25: 4846.5 | AN25: 46031 | AO25: NÃO | AP25: 46082 | AQ25: 0 | AR25: NÃO | AS25: NÃO | AT25: 46113 | AU25: 0 | AV25: NÃO | AW25: NÃO | AY25: GÁS ABASTECIMENTO (RETIRAR VALOR DO SALDO BANCÁRIO, E NÃO DO FUNDO DE RESERVA. É COBRADO DE CADA CONDÔMINO POR RATEIO, CONF. PLANILHA "VALORES DEVIDOS POR UNIDADE") | AZ25: =A25=AY25 -> TRUE
A26: =AY26 -> RECUPERAÇÃO DO TETO E DO GESSO DE PARTE DO APTº 201 DO CONDOMÍNIO | B26: 45778 | C26: 0 | D26: NÃO | E26: NÃO | F26: 45809 | G26: 638.94 | H26: 45810 | I26: NÃO - FOI ABATIDO DO FUNDO DE RESERVA | J26: 45839 | K26: 0 | L26: NÃO | M26: NÃO | N26: 45870 | O26: 0 | P26: NÃO | Q26: NÃO | R26: 45901 | S26: 0 | T26: NÃO | U26: NÃO | V26: 45931 | W26: 0 | X26: NÃO | Y26: NÃO | Z26: 45962 | AA26: 0 | AB26: NÃO | AC26: NÃO | AD26: 45992 | AE26: 0 | AF26: NÃO | AG26: NÃO | AH26: 46023 | AI26: 0 | AJ26: NÃO | AK26: NÃO | AL26: 46054 | AM26: 0 | AN26: NÃO | AO26: NÃO | AP26: 46082 | AQ26: 0 | AR26: NÃO | AS26: NÃO | AT26: 46113 | AU26: 0 | AV26: NÃO | AW26: NÃO | AY26: RECUPERAÇÃO DO TETO E DO GESSO DE PARTE DO APTº 201 DO CONDOMÍNIO | AZ26: =A26=AY26 -> TRUE
A27: =AY27 -> GASTOS COM ATUALIZAÇÃO DO SISTEMA DE CÂMERAS E INTERFONES | B27: 45778 | C27: 0 | D27: NÃO | E27: NÃO | F27: 45809 | G27: 5800 | H27: 45820 | I27: NÃO - FOI ABATIDO DO FUNDO DE RESERVA- VER ARQUIVO "CÂMERAS E INTERFONES CLAUDINEY ENTRADA PIX CC INTER" DA PASTA "H\Outr\Aptº PE\Condomínio Neápolis" | J27: 45839 | K27: 0 | L27: NÃO | M27: NÃO | N27: 45870 | O27: =8500+1282.54+200 -> 9982.54 | P27: 07 E 11/07, 11/08/25 | Q27: NÃO - FOI ABATIDO DO FUNDO DE RESERVA- VER ARQUIVOS "CÂMERAS E INTERFONES CLAUDINEY PAGTº 20250707 PIX CC INTER" E "MONITOR DE CÂMERAS PARA HALL DO 1º ANDAR 20250711 RECIBO", DA PASTA "H\Outr\Aptº PE\Condomínio Neápolis" | R27: 45901 | S27: 0 | T27: NÃO | U27: NÃO | V27: 45931 | W27: 0 | X27: NÃO | Y27: NÃO | Z27: 45962 | AA27: 0 | AB27: NÃO | AC27: NÃO | AD27: 45992 | AE27: 0 | AF27: NÃO | AG27: NÃO | AH27: 46023 | AI27: 0 | AJ27: NÃO | AK27: NÃO | AL27: 46054 | AM27: 0 | AN27: NÃO | AO27: NÃO | AP27: 46082 | AQ27: 0 | AR27: NÃO | AS27: NÃO | AT27: 46113 | AU27: 0 | AV27: NÃO | AW27: NÃO | AY27: GASTOS COM ATUALIZAÇÃO DO SISTEMA DE CÂMERAS E INTERFONES | AZ27: =A27=AY27 -> TRUE
A28: =AY28 -> SINALIZAÇÃO HORIZONTAL NA RUA EM FRENTE À GARAGEM | B28: 45778 | C28: 0 | D28: NÃO | E28: NÃO | F28: 45809 | G28: 0 | H28: NÃO | I28: NÃO | J28: 45839 | K28: 0 | L28: NÃO | M28: NÃO | N28: 45870 | O28: 0 | P28: NÃO | Q28: NÃO | R28: 45901 | S28: 0 | T28: NÃO | U28: NÃO | V28: 45931 | W28: 509.11 | X28: 45919 | Y28: NÃO - FOI ABATIDO DO FUNDO DE RESERVA | Z28: 45962 | AA28: 0 | AB28: NÃO | AC28: NÃO | AD28: 45992 | AE28: 0 | AF28: NÃO | AG28: NÃO | AH28: 46023 | AI28: 0 | AJ28: NÃO | AK28: NÃO | AL28: 46054 | AM28: 0 | AN28: NÃO | AO28: NÃO | AP28: 46082 | AQ28: 0 | AR28: NÃO | AS28: NÃO | AT28: 46113 | AU28: 0 | AV28: NÃO | AW28: NÃO | AY28: SINALIZAÇÃO HORIZONTAL NA RUA EM FRENTE À GARAGEM | AZ28: =A28=AY28 -> TRUE
A29: =AY29 -> CONSULTORIA E A.R.T. P/RENOV.AUTO DE VISTORIA/CORPO DE BOMBEIROS | B29: 45778 | C29: 0 | D29: NÃO | E29: NÃO | F29: 45809 | G29: 0 | H29: NÃO | I29: NÃO | J29: 45839 | K29: 0 | L29: NÃO | M29: NÃO | N29: 45870 | O29: 0 | P29: NÃO | Q29: NÃO | R29: 45901 | S29: 0 | T29: NÃO | U29: NÃO | V29: 45931 | W29: 0 | X29: NÃO | Y29: NÃO | Z29: 45962 | AA29: =103.03+700 -> 803.03 | AB29: 15 E 24/10/25 | AC29: NÃO | AD29: 45992 | AE29: 0 | AF29: NÃO | AG29: NÃO | AH29: 46023 | AI29: 0 | AJ29: NÃO | AK29: NÃO | AL29: 46054 | AM29: 0 | AN29: NÃO | AO29: NÃO | AP29: 46082 | AQ29: 0 | AR29: NÃO | AS29: NÃO | AT29: 46113 | AU29: 0 | AV29: NÃO | AW29: NÃO | AY29: CONSULTORIA E A.R.T. P/RENOV.AUTO DE VISTORIA/CORPO DE BOMBEIROS | AZ29: =A29=AY29 -> TRUE
A30: =AY30 -> DESENTUPIMENTO DO ESGOTO DO PRÉDIO | B30: 45778 | C30: 0 | D30: NÃO | E30: NÃO | F30: 45809 | G30: 0 | H30: NÃO | I30: NÃO | J30: 45839 | K30: 0 | L30: NÃO | M30: NÃO | N30: 45870 | O30: 0 | P30: NÃO | Q30: NÃO | R30: 45901 | S30: 0 | T30: NÃO | U30: NÃO | V30: 45931 | W30: 0 | X30: NÃO | Y30: NÃO | Z30: 45962 | AA30: 0 | AB30: NÃO | AC30: NÃO | AD30: 45992 | AE30: 660 | AF30: 45995 | AG30: NÃO | AH30: 46023 | AI30: 0 | AJ30: NÃO | AK30: NÃO | AL30: 46054 | AM30: 0 | AN30: NÃO | AO30: NÃO | AP30: 46082 | AQ30: 0 | AR30: NÃO | AS30: NÃO | AT30: 46113 | AU30: 0 | AV30: NÃO | AW30: NÃO | AY30: DESENTUPIMENTO DO ESGOTO DO PRÉDIO | AZ30: =A30=AY30 -> TRUE
A31: =AY31 -> PORTA DE VIDRO, 1º ANDAR | B31: 45778 | C31: 0 | D31: NÃO | E31: NÃO | F31: 45809 | G31: 0 | H31: NÃO | I31: NÃO | J31: 45839 | K31: 0 | L31: NÃO | M31: NÃO | N31: 45870 | O31: 0 | P31: NÃO | Q31: NÃO | R31: 45901 | S31: 0 | T31: NÃO | U31: NÃO | V31: 45931 | W31: 0 | X31: NÃO | Y31: NÃO | Z31: 45962 | AA31: 0 | AB31: NÃO | AC31: NÃO | AD31: 45992 | AE31: 0 | AF31: NÃO | AG31: NÃO | AH31: 46023 | AI31: 855 | AJ31: 46008 | AK31: NÃO - MANUTENÇÃO E INSTALAÇÃO DE MOLA | AL31: 46054 | AM31: 0 | AN31: NÃO | AO31: NÃO | AP31: 46082 | AQ31: 0 | AR31: NÃO | AS31: NÃO | AT31: 46113 | AU31: 0 | AV31: NÃO | AW31: NÃO | AY31: PORTA DE VIDRO, 1º ANDAR | AZ31: =A31=AY31 -> TRUE
A32: =AY32 -> COPIAR/COLAR ESTA LINHA PARA NOVA DESPESA | B32: 45778 | C32: 0 | D32: NÃO | E32: NÃO | F32: 45809 | G32: 0 | H32: NÃO | I32: NÃO | J32: 45839 | K32: 0 | L32: NÃO | M32: NÃO | N32: 45870 | O32: 0 | P32: NÃO | Q32: NÃO | R32: 45901 | S32: 0 | T32: NÃO | U32: NÃO | V32: 45931 | W32: 0 | X32: NÃO | Y32: NÃO | Z32: 45962 | AA32: 0 | AB32: NÃO | AC32: NÃO | AD32: 45992 | AE32: 0 | AF32: NÃO | AG32: NÃO | AH32: 46023 | AI32: 0 | AJ32: NÃO | AK32: NÃO | AL32: 46054 | AM32: 0 | AN32: NÃO | AO32: NÃO | AP32: 46082 | AQ32: 0 | AR32: NÃO | AS32: NÃO | AT32: 46113 | AU32: 0 | AV32: NÃO | AW32: NÃO | AY32: COPIAR/COLAR ESTA LINHA PARA NOVA DESPESA | AZ32: =A32=AY32 -> TRUE
A33: =AY33 -> PAGAMENTO SERVIÇO DO SÍNDICO - TEM FÓRMULA DE "IGUAL", NÃO PRECISA PREENCHER | B33: 45778 | C33: ='VRS. DEVIDOS E OUTROS'!C94+'VRS. DEVIDOS E OUTROS'!Q4+'VRS. DEVIDOS E OUTROS'!Q6 -> 544.41 | D33: =D11 -> 45778 | E33: NÃO | F33: 45809 | G33: ='VRS. DEVIDOS E OUTROS'!C95+'VRS. DEVIDOS E OUTROS'!Q11+'VRS. DEVIDOS E OUTROS'!Q13 -> 589.49 | H33: =H11 -> 45810 | I33: NÃO | J33: 45839 | K33: ='VRS. DEVIDOS E OUTROS'!C96+'VRS. DEVIDOS E OUTROS'!Q18+'VRS. DEVIDOS E OUTROS'!Q20 -> 487.8 | L33: =L11 -> 45839 | M33: NÃO | N33: 45870 | O33: ='VRS. DEVIDOS E OUTROS'!C97+'VRS. DEVIDOS E OUTROS'!Q25+'VRS. DEVIDOS E OUTROS'!Q27 -> 545.62 | P33: =P11 -> 45870 | Q33: NÃO | R33: 45901 | S33: ='MEDIÇÕES E TABELAS'!AS34 -> 570.56 | T33: =T11 -> 45901 | U33: NÃO | V33: 45931 | W33: ='MEDIÇÕES E TABELAS'!AS37 -> 478.07 | X33: =X11 -> 45931 | Y33: NÃO | Z33: 45962 | AA33: ='MEDIÇÕES E TABELAS'!AS38 -> 435.18 | AB33: =AB11 -> 45962 | AC33: NÃO | AD33: 45992 | AE33: ='MEDIÇÕES E TABELAS'!AS39 -> 490.06 | AF33: =AF11 -> 45993 | AG33: NÃO | AH33: 46023 | AI33: ='MEDIÇÕES E TABELAS'!AS40 -> 526.58 | AJ33: =AJ11 -> 46024 | AK33: NÃO | AL33: 46054 | AM33: ='MEDIÇÕES E TABELAS'!AS41 -> 463.48 | AN33: =AN11 -> 46055 | AO33: NÃO | AP33: 46082 | AQ33: ='MEDIÇÕES E TABELAS'!AS42 -> 454.67 | AR33: =AR11 -> 46083 | AS33: NÃO | AT33: 46113 | AU33: ='MEDIÇÕES E TABELAS'!AS43 -> 564.68 | AV33: =AV11 -> 46113 | AW33: NÃO | AY33: PAGAMENTO SERVIÇO DO SÍNDICO - TEM FÓRMULA DE "IGUAL", NÃO PRECISA PREENCHER | AZ33: =A33=AY33 -> TRUE
A34: =AY34 -> FUNDO DE RESERVA - TEM FÓRMULA DE "IGUAL", NÃO PRECISA PREENCHER | B34: 45778 | C34: 150 | D34: =D11 -> 45778 | E34: SIM | F34: 45809 | G34: =C34 -> 150 | H34: =H11 -> 45810 | I34: SIM - TEM FÓRMULA DE "IGUAL", NÃO PRECISA PREENCHER | J34: 45839 | K34: =G34 -> 150 | L34: =L11 -> 45839 | M34: SIM - TEM FÓRMULA DE "IGUAL", NÃO PRECISA PREENCHER | N34: 45870 | O34: =K34 -> 150 | P34: =P11 -> 45870 | Q34: SIM - TEM FÓRMULA DE "IGUAL", NÃO PRECISA PREENCHER | R34: 45901 | S34: =O34 -> 150 | T34: =T11 -> 45901 | U34: SIM - TEM FÓRMULA DE "IGUAL", NÃO PRECISA PREENCHER | V34: 45931 | W34: =S34 -> 150 | X34: =X11 -> 45931 | Y34: SIM - TEM FÓRMULA DE "IGUAL", NÃO PRECISA PREENCHER | Z34: 45962 | AA34: =W34 -> 150 | AB34: =AB11 -> 45962 | AC34: SIM - TEM FÓRMULA DE "IGUAL", NÃO PRECISA PREENCHER | AD34: 45992 | AE34: =AA34 -> 150 | AF34: =AF11 -> 45993 | AG34: SIM | AH34: 46023 | AI34: =AE34 -> 150 | AJ34: =AJ11 -> 46024 | AK34: SIM | AL34: 46054 | AM34: =AI34 -> 150 | AN34: =AN11 -> 46055 | AO34: SIM | AP34: 46082 | AQ34: =AM34 -> 150 | AR34: =AR11 -> 46083 | AS34: SIM | AT34: 46113 | AU34: =AQ34 -> 150 | AV34: =AV11 -> 46113 | AW34: SIM | AY34: FUNDO DE RESERVA - TEM FÓRMULA DE "IGUAL", NÃO PRECISA PREENCHER | AZ34: =A34=AY34 -> TRUE
A37: =AY37 -> TOTAL A INFORMAR NA PLAN. P/CONDÔM. (SERVE APENAS PARA COMPARAR COM O TOTAL DOS LANÇAMENTOS DAQUELA PLANILHA) | C37: =SUM(C3:C23) -> 4063.74 | G37: =SUM(G3:G23) -> 4107.43 | K37: =SUM(K3:K23) -> 3994.18 | O37: =SUM(O3:O23) -> 3510.92 | S37: =SUM(S3:S23) -> 4306.49 | W37: =SUM(W3:W23) -> 3985.15 | AA37: =SUM(AA3:AA23) -> 3844.04 | AE37: =SUM(AE3:AE23) -> 4024.94 | AI37: =SUM(AI3:AI23) -> 3750.32 | AM37: =SUM(AM3:AM23) -> 3871.41 | AQ37: =SUM(AQ3:AQ23) -> 3803.35 | AU37: =SUM(AU3:AU23) -> 4065.65 | AY37: TOTAL A INFORMAR NA PLAN. P/CONDÔM. (SERVE APENAS PARA COMPARAR COM O TOTAL DOS LANÇAMENTOS DAQUELA PLANILHA)
A38: =AY38 -> O TOTAL DA LINHA ACIMA COINCIDE COM OS LANÇAMENTOS DA PLANILHA "PLAN P COND" | B38: =AZ38 -> PARA INSERIR COR NA FÓRMULA: PÁGINA INICIAL / FORMATAÇÃO CONDICIONAL / REGRAS DE REALCE DAS CÉLULAS / É IGUAL A... (VERDADEIRO OU FALSO, UM DE CADA VEZ) / FORMATAR PERSONALIZADO | AQ38: =AQ37='PLAN P COND'!G27 -> FALSE | AU38: =AU37='PLAN P COND'!G27 -> TRUE | AY38: O TOTAL DA LINHA ACIMA COINCIDE COM OS LANÇAMENTOS DA PLANILHA "PLAN P COND" | AZ38: PARA INSERIR COR NA FÓRMULA: PÁGINA INICIAL / FORMATAÇÃO CONDICIONAL / REGRAS DE REALCE DAS CÉLULAS / É IGUAL A... (VERDADEIRO OU FALSO, UM DE CADA VEZ) / FORMATAR PERSONALIZADO
A39: =AY39 -> OBS.: COM FÓRMULAS PARA PREENCHIMENTO DOS DOIS VALORES DE ÁGUA | AY39: OBS.: COM FÓRMULAS PARA PREENCHIMENTO DOS DOIS VALORES DE ÁGUA
A42: DEPOIS DE PRONTA: COPIAR/COLAR A TABELA TODA ABAIXO DA EXISTENTE, E A SEGUIR COPIAR/COLAR ESPECIAL TEXTO A TABELA TODA EM CIMA DA QUE JÁ FOI COLADA (ASSIM OS VALORES SERÃO FIXADOS CONFORME OS EXISTENTES NA TABELA ORIGINAL, MAS SEM FÓRMULAS)
A44: TABELA SUPERIOR X TABELA INFERIOR | AU44: PREENCHTº AZUL: A CONFIRMAR | AY44: LANÇAMENTOS, TABELA CRIADA EM 07/07/2025 (OS ITENS "RATEIO PARCIAL", "RATEIO PARCIAL DO SÍNDICO (RP/13)" E "RATEIO FINAL" NÃO SÃO NECESSÁRIOS AQUI, POIS SÃO FÓRMULAS QUE DEPENDEM DIRETAMENTE DOS VALORES AQUI INFORMADOS, BASTANDO USAR A BASE DA PLANILHA ATUAL) | AZ44: COMPARAÇÃO DAS DESCRIÇÕES (DESTACAR OS ITENS QUE NÃO EXISTEM NA PRESENTE REF. OU NAS REF. ANTERIORES, PARA ZERÁ-LOS. ACRESCENTAR OS ITENS AINDA FALTOSOS NA REF. ATUAL, SEMPRE ZERANDO "VALOR" E "DATA" NAS REF. ANTERIORES)
A45: SEM VALOR | B45: REF. | C45: VALOR | D45: DATA | E45: INFORMAR NA PLAN. P/CONDÔM. | F45: REF. | G45: VALOR | H45: DATA | I45: INFORMAR NA PLAN. P/CONDÔM. | J45: REF. | K45: VALOR | L45: DATA | M45: INFORMAR NA PLAN. P/CONDÔM. | N45: REF. | O45: VALOR | P45: DATA | Q45: INFORMAR NA PLAN. P/CONDÔM. | R45: REF. | S45: VALOR | T45: DATA | U45: INFORMAR NA PLAN. P/CONDÔM. | V45: REF. | W45: VALOR | X45: DATA | Y45: INFORMAR NA PLAN. P/CONDÔM. | Z45: REF. | AA45: VALOR | AB45: DATA | AC45: INFORMAR NA PLAN. P/CONDÔM. | AD45: REF. | AE45: VALOR | AF45: DATA | AG45: INFORMAR NA PLAN. P/CONDÔM. | AH45: REF. | AI45: VALOR | AJ45: DATA | AK45: INFORMAR NA PLAN. P/CONDÔM. (+ DESCRIÇÃO COMPLEMENTAR) | AL45: REF. | AM45: VALOR | AN45: DATA | AO45: INFORMAR NA PLAN. P/CONDÔM. (+ DESCRIÇÃO COMPLEMENTAR) | AP45: REF. | AQ45: VALOR | AR45: DATA | AS45: INFORMAR NA PLAN. P/CONDÔM. (+ DESCRIÇÃO COMPLEMENTAR) | AT45: REF. | AU45: VALOR | AV45: DATA | AW45: INFORMAR NA PLAN. P/CONDÔM. (+ DESCRIÇÃO COMPLEMENTAR) | AY45: DESCRIÇÃO
A46: =SUM(B3:AY3)=SUM(B46:AY46) -> TRUE | B46: 45778 | C46: 1342.94 | D46: 45789 | E46: SIM | F46: 45809 | G46: 1342.94 | H46: 45818 | I46: SIM | J46: 45839 | K46: 1342.94 | L46: 45848 | M46: SIM | N46: 45870 | O46: 1342.94 | P46: 45880 | Q46: SIM | R46: 45901 | S46: 1342.94 | T46: 45910 | U46: SIM | V46: 45931 | W46: 1342.94 | X46: 45940 | Y46: SIM | Z46: 45962 | AA46: 1342.94 | AB46: 45971 | AC46: SIM | AD46: 45992 | AE46: 1342.94 | AF46: 46001 | AG46: SIM | AH46: 46023 | AI46: 1342.94 | AJ46: 46034 | AK46: SIM | AL46: 46054 | AM46: 1443.66 | AN46: 46063 | AO46: SIM | AP46: 46082 | AQ46: 1443.66 | AR46: 46091 | AS46: SIM | AT46: 46113 | AU46: 1443.66 | AV46: 46122 | AW46: SIM | AY46: CONSERVADORA CAMPOS DE OLIVEIRA | AZ46: TRUE
A47: =SUM(B4:AY4)=SUM(B47:AY47) -> TRUE | B47: 45778 | C47: 1138.65 | D47: 45792 | E47: SIM | F47: 45809 | G47: 1334.14 | H47: 45824 | I47: SIM | J47: 45839 | K47: 1231.11 | L47: 45853 | M47: SIM | N47: 45870 | O47: 1231.11 | P47: 45888 | Q47: SIM | R47: 45901 | S47: 1231.11 | T47: 45915 | U47: SIM | V47: 45931 | W47: 1231.11 | X47: 45945 | Y47: SIM | Z47: 45962 | AA47: 1231.11 | AB47: 45978 | AC47: SIM | AD47: 45992 | AE47: 1231.11 | AF47: 46006 | AG47: SIM | AH47: 46023 | AI47: 1231.11 | AJ47: 46037 | AK47: SIM | AL47: 46054 | AM47: 1231.11 | AN47: 46068 | AO47: SIM | AP47: 46082 | AQ47: 1231.11 | AR47: 46097 | AS47: SIM | AT47: 46113 | AU47: 1231.11 | AV47: 46127 | AW47: SIM | AY47: MANUTENÇÃO ELEVADOR - THYSSENKRUPP | AZ47: TRUE
A48: =SUM(B5:AY5)=SUM(B48:AY48) -> TRUE | B48: 45778 | C48: 0 | D48: NÃO | E48: NÃO - O CONSUMO DO CONDOMÍNIO REFERENTE À LEITURA DE 24/04/25 FOI CONSIDERADO NULO PARA O FIM DA PRESENTE APURAÇÃO (JÁ QUE O CONSUMO TOTAL DOS CONDÔMINOS SUPEROU O CONSUMO INFORMADO NA CONTA DA COPASA), EM VISTA DO AJUSTE QUE FOI FEITO EM 04/04/25 NA CONTA ANTERIOR, APURADA ANTERIORMENTE COM BASE NA MÉDIA DE CONSUMO | F48: 45809 | G48: 429.47 | H48: 45824 | I48: SIM - VALOR A SER RATEADO ENTRE OS CONDÔMINOS | J48: 45839 | K48: 0 | L48: NÃO | M48: NÃO - O CONSUMO DO CONDOMÍNIO REFERENTE À LEITURA DE 24/06/25 FOI CONSIDERADO NULO PARA O FIM DA PRESENTE APURAÇÃO (JÁ QUE O CONSUMO TOTAL DOS CONDÔMINOS SUPEROU O CONSUMO INFORMADO NA CONTA DA COPASA), PARECE QUE FOI FEITA LEITURA ERRADA PELA COPASA NO HIDRÔMETRO... | N48: 45870 | O48: 0 | P48: NÃO | Q48: NÃO - O TOTAL DA LEITURA DE 24/06/25 FOI USADO (E DEPOIS ZERADO) PARA A PRESENTE APURAÇÃO DO CONSUMO DO CONDOMÍNIO, UMA VEZ QUE A LEITURA ATUAL NA CONTA DA COPASA (DE 22/07/25) ESTÁ INCORRETA (PARA MENOR!!!), E QUE NÃO FOI ATENDIDA ATÉ O DIA 08/08/25 MINHA SOLICITAÇÃO DE CORREÇÃO DA LEITURA JUNTO À COPASA. | R48: 45901 | S48: 102.13 | T48: 45915 | U48: SIM - VALOR A SER RATEADO ENTRE OS CONDÔMINOS | V48: 45931 | W48: 348.46 | X48: 45945 | Y48: SIM - VALOR A SER RATEADO ENTRE OS CONDÔMINOS | Z48: 45962 | AA48: 351.47 | AB48: 45978 | AC48: 45978 | AD48: 45992 | AE48: 346.4 | AF48: 46006 | AG48: SIM | AH48: 46023 | AI48: 0 | AJ48: 46037 | AK48: NÃO | AL48: 46054 | AM48: 0 | AN48: 46071 | AO48: NÃO | AP48: 46082 | AQ48: 0 | AR48: 46099 | AS48: NÃO | AT48: 46113 | AU48: 236.41 | AV48: 46127 | AW48: SIM | AY48: CONTA DE ÁGUA DO CONDOMÍNIO (A SER RATEADA ENTRE OS CONDÔMINOS) | AZ48: TRUE
A49: =SUM(B6:AY6)=SUM(B49:AY49) -> TRUE | B49: 45778 | C49: 311.36 | D49: 45796 | E49: SIM | F49: 45809 | G49: 333.58 | H49: 45825 | I49: SIM | J49: 45839 | K49: 378.75 | L49: 45855 | M49: SIM | N49: 45870 | O49: 440.76 | P49: 45887 | Q49: SIM | R49: 45901 | S49: 487.7 | T49: 45917 | U49: SIM | V49: 45931 | W49: 467.79 | X49: 45947 | Y49: SIM | Z49: 45962 | AA49: 475.91 | AB49: 45978 | AC49: SIM | AD49: 45992 | AE49: 399.98 | AF49: 46008 | AG49: SIM | AH49: 46023 | AI49: 429.59 | AJ49: 46041 | AK49: SIM | AL49: 46054 | AM49: 470.4 | AN49: 46070 | AO49: SIM | AP49: 46082 | AQ49: 404.07 | AR49: 46098 | AS49: SIM | AT49: 46113 | AU49: 429.96 | AV49: 46129 | AW49: SIM | AY49: CONTA DE LUZ DO CONDOMÍNIO (CEMIG) | AZ49: TRUE
A50: =SUM(B7:AY7)=SUM(B50:AY50) -> TRUE | B50: 45778 | C50: 221.5 | D50: 45797 | E50: SIM | F50: 45809 | G50: 226.01 | H50: 45828 | I50: SIM | J50: 45839 | K50: 226.01 | L50: 45856 | M50: SIM | N50: 45870 | O50: 226.01 | P50: 45889 | Q50: SIM | R50: 45901 | S50: 226.01 | T50: 45919 | U50: SIM | V50: 45931 | W50: 266.4 | X50: 45950 | Y50: SIM | Z50: 45962 | AA50: 226.01 | AB50: 45981 | AC50: SIM | AD50: 45992 | AE50: 226.01 | AF50: 46010 | AG50: SIM | AH50: 46023 | AI50: 271.01 | AJ50: 10 E 20/01/26 | AK50: SIM | AL50: 46054 | AM50: 238.46 | AN50: 46073 | AO50: SIM - O VALOR CORRETO É $226,01, E NÃO $238,46, ESTE ÚLTIMO CALCULADO COM BASE NO REAJUSTE DA MENSALIDADE DA CONSERVADORA, QUE SÓ VIGORARÁ A PARTIR DA COMPETÊNCIA 02/2026, COM RECOLHTº EM 03/2026 | AP50: 46082 | AQ50: 238.45 | AR50: 46101 | AS50: SIM | AT50: 46113 | AU50: 238.45 | AV50: 46132 | AW50: SIM | AY50: RETENÇÕES FEDERAIS / MUNICIPAIS DE TRIBUTOS A RECOLHER | AZ50: TRUE
A51: =SUM(B8:AY8)=SUM(B51:AY51) -> TRUE | B51: 45778 | C51: 224.69 | D51: 45772 | E51: SIM - PARC. 5ª/6 | F51: 45809 | G51: 224.69 | H51: 45803 | I51: SIM - PARC. 6ª/6 | J51: 45839 | K51: 0 | L51: NÃO | M51: NÃO | N51: 45870 | O51: 0 | P51: NÃO | Q51: NÃO | R51: 45901 | S51: 0 | T51: NÃO | U51: NÃO | V51: 45931 | W51: 0 | X51: NÃO | Y51: NÃO | Z51: 45962 | AA51: 0 | AB51: NÃO | AC51: NÃO | AD51: 45992 | AE51: 0 | AF51: NÃO | AG51: NÃO | AH51: 46023 | AI51: 259.07 | AJ51: 46017 | AK51: SIM - PARCELA 1ª/6 | AL51: 46054 | AM51: 259.78 | AN51: 46051 | AO51: SIM - PARCELA 2ª/6 | AP51: 46082 | AQ51: 259.06 | AR51: 46078 | AS51: SIM - PARCELA 3ª/6 | AT51: 46113 | AU51: 259.06 | AV51: 46106 | AW51: SIM - PARCELA 4ª/6 | AY51: SEGURO DO PRÉDIO | AZ51: TRUE
A52: =SUM(B9:AY9)=SUM(B52:AY52) -> TRUE | B52: 45778 | C52: 608 | D52: 45789 | E52: SIM | F52: 45809 | G52: 0 | H52: NÃO | I52: NÃO | J52: 45839 | K52: 0 | L52: NÃO | M52: NÃO | N52: 45870 | O52: 0 | P52: NÃO | Q52: NÃO | R52: 45901 | S52: 0 | T52: NÃO | U52: NÃO | V52: 45931 | W52: 0 | X52: NÃO | Y52: NÃO | Z52: 45962 | AA52: 0 | AB52: NÃO | AC52: NÃO | AD52: 45992 | AE52: 0 | AF52: NÃO | AG52: NÃO | AH52: 46023 | AI52: 0 | AJ52: NÃO | AK52: NÃO | AL52: 46054 | AM52: 0 | AN52: NÃO | AO52: NÃO | AP52: 46082 | AQ52: 0 | AR52: NÃO | AS52: NÃO | AT52: 46113 | AU52: 0 | AV52: NÃO | AW52: NÃO | AY52: RECARGA ANUAL E REPARO DOS EXTINTORES | AZ52: TRUE
A53: =SUM(B10:AY10)=SUM(B53:AY53) -> TRUE | B53: 45778 | C53: 151.6 | D53: 45805 | E53: SIM | F53: 45809 | G53: 151.6 | H53: 45836 | I53: SIM | J53: 45839 | K53: 151.6 | L53: 45866 | M53: SIM | N53: 45870 | O53: 151.6 | P53: 45897 | Q53: SIM | R53: 45901 | S53: 151.6 | T53: 45929 | U53: SIM | V53: 45931 | W53: 151.6 | X53: 45958 | Y53: SIM | Z53: 45962 | AA53: 151.6 | AB53: 45989 | AC53: SIM | AD53: 45992 | AE53: 151.6 | AF53: 46020 | AG53: SIM | AH53: 46023 | AI53: 151.6 | AJ53: 46050 | AK53: SIM | AL53: 46054 | AM53: 163 | AN53: 46080 | AO53: SIM | AP53: 46082 | AQ53: 162 | AR53: 46111 | AS53: SIM | AT53: 46113 | AU53: 162 | AV53: 46140 | AW53: SIM | AY53: HONORÁRIOS DA CONTADORA - MAYRA S. P. OLIVEIRA | AZ53: TRUE
A54: =SUM(B11:AY11)=SUM(B54:AY54) -> TRUE | B54: 45778 | C54: 65 | D54: 45778 | E54: SIM | F54: 45809 | G54: 65 | H54: 45810 | I54: SIM | J54: 45839 | K54: 65 | L54: 45839 | M54: SIM | N54: 45870 | O54: 65 | P54: 45870 | Q54: SIM | R54: 45901 | S54: 65 | T54: 45901 | U54: SIM | V54: 45931 | W54: 65 | X54: 45931 | Y54: SIM | Z54: 45962 | AA54: 65 | AB54: 45962 | AC54: SIM | AD54: 45992 | AE54: 65 | AF54: 45993 | AG54: SIM | AH54: 46023 | AI54: 65 | AJ54: 46024 | AK54: SIM | AL54: 46054 | AM54: 65 | AN54: 46055 | AO54: SIM | AP54: 46082 | AQ54: 65 | AR54: 46083 | AS54: SIM | AT54: 46113 | AU54: 65 | AV54: 46113 | AW54: SIM | AY54: INTERNET PARA TRANSMISSÃO DE IMAGENS DAS CÂMERAS | AZ54: TRUE
A55: =SUM(B12:AY12)=SUM(B55:AY55) -> TRUE | B55: 45778 | C55: 0 | D55: NÃO | E55: NÃO | F55: 45809 | G55: 0 | H55: NÃO | I55: NÃO | J55: 45839 | K55: 0 | L55: NÃO | M55: NÃO | N55: 45870 | O55: 14.9 | P55: 45845 | Q55: SIM - PARA CX. CORREIO DA GARAGEM | R55: 45901 | S55: 0 | T55: NÃO | U55: NÃO | V55: 45931 | W55: 0 | X55: NÃO | Y55: NÃO | Z55: 45962 | AA55: 0 | AB55: NÃO | AC55: NÃO | AD55: 45992 | AE55: 0 | AF55: NÃO | AG55: NÃO | AH55: 46023 | AI55: 0 | AJ55: NÃO | AK55: NÃO | AL55: 46054 | AM55: 0 | AN55: NÃO | AO55: NÃO | AP55: 46082 | AQ55: 0 | AR55: NÃO | AS55: NÃO | AT55: 46113 | AU55: 0 | AV55: NÃO | AW55: NÃO | AY55: CADEADO | AZ55: TRUE
A56: =SUM(B13:AY13)=SUM(B56:AY56) -> TRUE | B56: 45778 | C56: 0 | D56: NÃO | E56: NÃO | F56: 45809 | G56: 0 | H56: NÃO | I56: NÃO | J56: 45839 | K56: 0 | L56: NÃO | M56: NÃO | N56: 45870 | O56: 14 | P56: 45845 | Q56: SIM - 2, PARA CADEADO DA CX. CORREIO DA GARAGEM | R56: 45901 | S56: 0 | T56: NÃO | U56: NÃO | V56: 45931 | W56: 0 | X56: NÃO | Y56: NÃO | Z56: 45962 | AA56: 0 | AB56: NÃO | AC56: NÃO | AD56: 45992 | AE56: 0 | AF56: NÃO | AG56: NÃO | AH56: 46023 | AI56: 0 | AJ56: NÃO | AK56: NÃO | AL56: 46054 | AM56: 0 | AN56: NÃO | AO56: NÃO | AP56: 46082 | AQ56: 0 | AR56: NÃO | AS56: NÃO | AT56: 46113 | AU56: 0 | AV56: NÃO | AW56: NÃO | AY56: CHAVES RESERVA | AZ56: TRUE
A57: =SUM(B14:AY14)=SUM(B57:AY57) -> TRUE | B57: 45778 | C57: 0 | D57: NÃO | E57: NÃO | F57: 45809 | G57: 0 | H57: NÃO | I57: NÃO | J57: 45839 | K57: 0 | L57: NÃO | M57: NÃO | N57: 45870 | O57: 24.6 | P57: 45870 | Q57: SIM - 6 UNIDADES | R57: 45901 | S57: 0 | T57: NÃO | U57: NÃO | V57: 45931 | W57: 0 | X57: NÃO | Y57: NÃO | Z57: 45962 | AA57: 0 | AB57: NÃO | AC57: NÃO | AD57: 45992 | AE57: 0 | AF57: NÃO | AG57: NÃO | AH57: 46023 | AI57: 0 | AJ57: NÃO | AK57: NÃO | AL57: 46054 | AM57: 0 | AN57: NÃO | AO57: NÃO | AP57: 46082 | AQ57: 0 | AR57: NÃO | AS57: NÃO | AT57: 46113 | AU57: 0 | AV57: NÃO | AW57: NÃO | AY57: LÂMPADAS 9W DE LED | AZ57: TRUE
A58: =SUM(B15:AY15)=SUM(B58:AY58) -> TRUE | B58: 45778 | C58: 0 | D58: NÃO | E58: NÃO | F58: 45809 | G58: 0 | H58: NÃO | I58: NÃO | J58: 45839 | K58: 0 | L58: NÃO | M58: NÃO | N58: 45870 | O58: 0 | P58: NÃO | Q58: NÃO | R58: 45901 | S58: 700 | T58: 45887 | U58: SIM - E NO PORTEIRO ELETRÔNICO | V58: 45931 | W58: 0 | X58: NÃO | Y58: NÃO | Z58: 45962 | AA58: 0 | AB58: NÃO | AC58: NÃO | AD58: 45992 | AE58: 0 | AF58: NÃO | AG58: NÃO | AH58: 46023 | AI58: 0 | AJ58: NÃO | AK58: NÃO | AL58: 46054 | AM58: 0 | AN58: NÃO | AO58: NÃO | AP58: 46082 | AQ58: 0 | AR58: NÃO | AS58: NÃO | AT58: 46113 | AU58: 0 | AV58: NÃO | AW58: NÃO | AY58: SERVIÇOS DE SERRALHEIRO NO PORTÃO DA GARAGEM | AZ58: TRUE
A59: =SUM(B16:AY16)=SUM(B59:AY59) -> TRUE | B59: 45778 | C59: 0 | D59: NÃO | E59: NÃO | F59: 45809 | G59: 0 | H59: NÃO | I59: NÃO | J59: 45839 | K59: 0 | L59: NÃO | M59: NÃO | N59: 45870 | O59: 0 | P59: NÃO | Q59: NÃO | R59: 45901 | S59: 0 | T59: NÃO | U59: NÃO | V59: 45931 | W59: 74.95 | X59: 45908 | Y59: SIM - EM PARTE DO PORTÃO DA GARAGEM E ELEVADOR | Z59: 45962 | AA59: 0 | AB59: NÃO | AC59: NÃO | AD59: 45992 | AE59: 0 | AF59: NÃO | AG59: NÃO | AH59: 46023 | AI59: 0 | AJ59: NÃO | AK59: NÃO | AL59: 46054 | AM59: 0 | AN59: NÃO | AO59: NÃO | AP59: 46082 | AQ59: 0 | AR59: NÃO | AS59: NÃO | AT59: 46113 | AU59: 0 | AV59: NÃO | AW59: NÃO | AY59: MATERIAL PARA PINTURA | AZ59: TRUE
A60: =SUM(B17:AY17)=SUM(B60:AY60) -> TRUE | B60: 45778 | C60: 0 | D60: NÃO | E60: NÃO | F60: 45809 | G60: 0 | H60: NÃO | I60: NÃO | J60: 45839 | K60: 120.9 | L60: 45834 | M60: SIM | N60: 45870 | O60: 0 | P60: NÃO | Q60: NÃO | R60: 45901 | S60: 0 | T60: NÃO | U60: NÃO | V60: 45931 | W60: 0 | X60: NÃO | Y60: NÃO | Z60: 45962 | AA60: 0 | AB60: NÃO | AC60: NÃO | AD60: 45992 | AE60: 0 | AF60: NÃO | AG60: NÃO | AH60: 46023 | AI60: 0 | AJ60: NÃO | AK60: NÃO | AL60: 46054 | AM60: 0 | AN60: NÃO | AO60: NÃO | AP60: 46082 | AQ60: 0 | AR60: NÃO | AS60: NÃO | AT60: 46113 | AU60: 0 | AV60: NÃO | AW60: NÃO | AY60: ATA DE ELEIÇÃO DE NOVO SÍNDICO, REGISTRO NO CARTÓRIO | AZ60: TRUE
A61: =SUM(B18:AY18)=SUM(B61:AY61) -> TRUE | B61: 45778 | C61: 0 | D61: NÃO | E61: NÃO | F61: 45809 | G61: 0 | H61: NÃO | I61: NÃO | J61: 45839 | K61: 477.87 | L61: 45833 | M61: SIM | N61: 45870 | O61: 0 | P61: NÃO | Q61: NÃO | R61: 45901 | S61: 0 | T61: NÃO | U61: NÃO | V61: 45931 | W61: 0 | X61: NÃO | Y61: NÃO | Z61: 45962 | AA61: 0 | AB61: NÃO | AC61: NÃO | AD61: 45992 | AE61: 0 | AF61: NÃO | AG61: NÃO | AH61: 46023 | AI61: 0 | AJ61: NÃO | AK61: NÃO | AL61: 46054 | AM61: 0 | AN61: NÃO | AO61: NÃO | AP61: 46082 | AQ61: 0 | AR61: NÃO | AS61: NÃO | AT61: 46113 | AU61: 0 | AV61: NÃO | AW61: NÃO | AY61: AÇÃO CONTRA COPASA, CUSTAS DE RECURSO JUDICIAL | AZ61: TRUE
A62: =SUM(B19:AY19)=SUM(B62:AY62) -> TRUE | B62: 45778 | C62: 0 | D62: NÃO | E62: NÃO | F62: 45809 | G62: 0 | H62: NÃO | I62: NÃO | J62: 45839 | K62: 0 | L62: NÃO | M62: NÃO | N62: 45870 | O62: 0 | P62: NÃO | Q62: NÃO | R62: 45901 | S62: 0 | T62: NÃO | U62: NÃO | V62: 45931 | W62: 36.9 | X62: 45923 | Y62: SIM | Z62: 45962 | AA62: 0 | AB62: NÃO | AC62: NÃO | AD62: 45992 | AE62: 0 | AF62: NÃO | AG62: NÃO | AH62: 46023 | AI62: 0 | AJ62: NÃO | AK62: NÃO | AL62: 46054 | AM62: 0 | AN62: NÃO | AO62: NÃO | AP62: 46082 | AQ62: 0 | AR62: NÃO | AS62: NÃO | AT62: 46113 | AU62: 0 | AV62: NÃO | AW62: NÃO | AY62: XEROX PROJ.ELÉTRICO P/RENOV.AUTO DE VISTORIA/CORPO DE BOMBEIROS | AZ62: TRUE
A63: =SUM(B20:AY20)=SUM(B63:AY63) -> TRUE | B63: 45778 | C63: 0 | D63: NÃO | E63: NÃO | F63: 45809 | G63: 0 | H63: NÃO | I63: NÃO | J63: 45839 | K63: 0 | L63: NÃO | M63: NÃO | N63: 45870 | O63: 0 | P63: NÃO | Q63: NÃO | R63: 45901 | S63: 0 | T63: NÃO | U63: NÃO | V63: 45931 | W63: 0 | X63: NÃO | Y63: NÃO | Z63: 45962 | AA63: 0 | AB63: NÃO | AC63: NÃO | AD63: 45992 | AE63: 120 | AF63: 45968 | AG63: SIM | AH63: 46023 | AI63: 0 | AJ63: NÃO | AK63: NÃO | AL63: 46054 | AM63: 0 | AN63: NÃO | AO63: NÃO | AP63: 46082 | AQ63: 0 | AR63: NÃO | AS63: NÃO | AT63: 46113 | AU63: 0 | AV63: NÃO | AW63: NÃO | AY63: CONSERTO DA CERCA ELÉTRICA | AZ63: TRUE
A64: =SUM(B21:AY21)=SUM(B64:AY64) -> TRUE | B64: 45778 | C64: 0 | D64: NÃO | E64: NÃO | F64: 45809 | G64: 0 | H64: NÃO | I64: NÃO | J64: 45839 | K64: 0 | L64: NÃO | M64: NÃO | N64: 45870 | O64: 0 | P64: NÃO | Q64: NÃO | R64: 45901 | S64: 0 | T64: NÃO | U64: NÃO | V64: 45931 | W64: 0 | X64: NÃO | Y64: NÃO | Z64: 45962 | AA64: 0 | AB64: NÃO | AC64: NÃO | AD64: 45992 | AE64: 17.9 | AF64: 45993 | AG64: SIM - 1 UNIDADE | AH64: 46023 | AI64: 0 | AJ64: NÃO | AK64: NÃO | AL64: 46054 | AM64: 0 | AN64: NÃO | AO64: NÃO | AP64: 46082 | AQ64: 0 | AR64: NÃO | AS64: NÃO | AT64: 46113 | AU64: 0 | AV64: NÃO | AW64: NÃO | AY64: LUMINÁRIA DE EMERGÊNCIA | AZ64: TRUE
A65: =SUM(B22:AY22)=SUM(B65:AY65) -> TRUE | B65: 45778 | C65: 0 | D65: NÃO | E65: NÃO | F65: 45809 | G65: 0 | H65: NÃO | I65: NÃO | J65: 45839 | K65: 0 | L65: NÃO | M65: NÃO | N65: 45870 | O65: 0 | P65: NÃO | Q65: NÃO | R65: 45901 | S65: 0 | T65: NÃO | U65: NÃO | V65: 45931 | W65: 0 | X65: NÃO | Y65: NÃO | Z65: 45962 | AA65: 0 | AB65: NÃO | AC65: NÃO | AD65: 45992 | AE65: 124 | AF65: 45993 | AG65: SIM - MATERIAL | AH65: 46023 | AI65: 0 | AJ65: NÃO | AK65: NÃO | AL65: 46054 | AM65: 0 | AN65: NÃO | AO65: NÃO | AP65: 46082 | AQ65: 0 | AR65: NÃO | AS65: NÃO | AT65: 46113 | AU65: 0 | AV65: NÃO | AW65: NÃO | AY65: RECUPERAÇÃO DA PAREDE DAS VAGAS 402 E 601 FUNDOS | AZ65: TRUE
A66: =SUM(B23:AY23)=SUM(B66:AY66) -> TRUE | B66: 45778 | C66: 0 | D66: NÃO | E66: NÃO | F66: 45809 | G66: 0 | H66: NÃO | I66: NÃO | J66: 45839 | K66: 0 | L66: NÃO | M66: NÃO | N66: 45870 | O66: 0 | P66: NÃO | Q66: NÃO | R66: 45901 | S66: 0 | T66: NÃO | U66: NÃO | V66: 45931 | W66: 0 | X66: NÃO | Y66: NÃO | Z66: 45962 | AA66: 0 | AB66: NÃO | AC66: NÃO | AD66: 45992 | AE66: 0 | AF66: NÃO | AG66: NÃO | AH66: 46023 | AI66: 0 | AJ66: NÃO | AK66: NÃO | AL66: 46054 | AM66: 0 | AN66: NÃO | AO66: NÃO | AP66: 46082 | AQ66: 0 | AR66: NÃO | AS66: NÃO | AT66: 46113 | AU66: 0 | AV66: NÃO | AW66: NÃO | AY66: COPIAR/COLAR ESTA LINHA PARA NOVA DESPESA. ACIMA DESTA LINHA: INFORMAR NA PLANILHA P/CONDÔMINOS.; ABAIXO: NÃO INFORMAR NA PLANILHA P/CONDÔMINOS (DESCONTAR NO FUNDO DE RESERVA) | AZ66: TRUE
A67: =SUM(B24:AY24)=SUM(B67:AY67) -> TRUE | B67: 45778 | C67: 3043.18 | D67: 45824 | E67: NÃO | F67: 45809 | G67: 4380.41 | H67: 45853 | I67: NÃO | J67: 45839 | K67: 3870.33 | L67: 45887 | M67: NÃO | N67: 45870 | O67: 650.78 | P67: 45915 | Q67: NÃO | R67: 45901 | S67: 5204.82 | T67: 45945 | U67: NÃO | V67: 45931 | W67: 3715.89 | X67: 45978 | Y67: NÃO | Z67: 45962 | AA67: 3062.91 | AB67: 46006 | AC67: NÃO | AD67: 45992 | AE67: 3466.72 | AF67: 46037 | AG67: NÃO | AH67: 46023 | AI67: 2101.43 | AJ67: 46071 | AK67: NÃO | AL67: 46054 | AM67: 997.74 | AN67: 46099 | AO67: NÃO | AP67: 46082 | AQ67: 1010.35 | AR67: 46127 | AS67: NÃO | AT67: 46113 | AU67: 2943.7 | AV67: 46157 | AW67: NÃO | AY67: CONTA DE ÁGUA DO CONDOMÍNIO, VALOR TOTAL A PAGAR | AZ67: TRUE
A68: =SUM(B25:AY25)=SUM(B68:AY68) -> TRUE | B68: 45778 | C68: 0 | D68: NÃO | E68: NÃO | F68: 45809 | G68: 4277.19 | H68: 45835 | I68: NÃO | J68: 45839 | K68: 0 | L68: NÃO | M68: NÃO | N68: 45870 | O68: 0 | P68: NÃO | Q68: NÃO | R68: 45901 | S68: 0 | T68: NÃO | U68: NÃO | V68: 45931 | W68: 0 | X68: NÃO | Y68: NÃO | Z68: 45962 | AA68: 0 | AB68: NÃO | AC68: NÃO | AD68: 45992 | AE68: 0 | AF68: NÃO | AG68: NÃO | AH68: 46023 | AI68: 0 | AJ68: NÃO | AK68: NÃO | AL68: 46054 | AM68: 4846.5 | AN68: 46031 | AO68: NÃO | AP68: 46082 | AQ68: 0 | AR68: NÃO | AS68: NÃO | AT68: 46113 | AU68: 0 | AV68: NÃO | AW68: NÃO | AY68: GÁS ABASTECIMENTO (RETIRAR VALOR DO SALDO BANCÁRIO, E NÃO DO FUNDO DE RESERVA. É COBRADO DE CADA CONDÔMINO POR RATEIO, CONF. PLANILHA "VALORES DEVIDOS POR UNIDADE") | AZ68: TRUE
A69: =SUM(B26:AY26)=SUM(B69:AY69) -> TRUE | B69: 45778 | C69: 0 | D69: NÃO | E69: NÃO | F69: 45809 | G69: 638.94 | H69: 45810 | I69: NÃO - FOI ABATIDO DO FUNDO DE RESERVA | J69: 45839 | K69: 0 | L69: NÃO | M69: NÃO | N69: 45870 | O69: 0 | P69: NÃO | Q69: NÃO | R69: 45901 | S69: 0 | T69: NÃO | U69: NÃO | V69: 45931 | W69: 0 | X69: NÃO | Y69: NÃO | Z69: 45962 | AA69: 0 | AB69: NÃO | AC69: NÃO | AD69: 45992 | AE69: 0 | AF69: NÃO | AG69: NÃO | AH69: 46023 | AI69: 0 | AJ69: NÃO | AK69: NÃO | AL69: 46054 | AM69: 0 | AN69: NÃO | AO69: NÃO | AP69: 46082 | AQ69: 0 | AR69: NÃO | AS69: NÃO | AT69: 46113 | AU69: 0 | AV69: NÃO | AW69: NÃO | AY69: RECUPERAÇÃO DO TETO E DO GESSO DE PARTE DO APTº 201 DO CONDOMÍNIO | AZ69: TRUE
A70: =SUM(B27:AY27)=SUM(B70:AY70) -> TRUE | B70: 45778 | C70: 0 | D70: NÃO | E70: NÃO | F70: 45809 | G70: 5800 | H70: 45820 | I70: NÃO - FOI ABATIDO DO FUNDO DE RESERVA- VER ARQUIVO "CÂMERAS E INTERFONES CLAUDINEY ENTRADA PIX CC INTER" DA PASTA "H\Outr\Aptº PE\Condomínio Neápolis" | J70: 45839 | K70: 0 | L70: NÃO | M70: NÃO | N70: 45870 | O70: 9982.54 | P70: 07 E 11/07, 11/08/25 | Q70: NÃO - FOI ABATIDO DO FUNDO DE RESERVA- VER ARQUIVOS "CÂMERAS E INTERFONES CLAUDINEY PAGTº 20250707 PIX CC INTER" E "MONITOR DE CÂMERAS PARA HALL DO 1º ANDAR 20250711 RECIBO", DA PASTA "H\Outr\Aptº PE\Condomínio Neápolis" | R70: 45901 | S70: 0 | T70: NÃO | U70: NÃO | V70: 45931 | W70: 0 | X70: NÃO | Y70: NÃO | Z70: 45962 | AA70: 0 | AB70: NÃO | AC70: NÃO | AD70: 45992 | AE70: 0 | AF70: NÃO | AG70: NÃO | AH70: 46023 | AI70: 0 | AJ70: NÃO | AK70: NÃO | AL70: 46054 | AM70: 0 | AN70: NÃO | AO70: NÃO | AP70: 46082 | AQ70: 0 | AR70: NÃO | AS70: NÃO | AT70: 46113 | AU70: 0 | AV70: NÃO | AW70: NÃO | AY70: GASTOS COM ATUALIZAÇÃO DO SISTEMA DE CÂMERAS E INTERFONES | AZ70: TRUE
A71: =SUM(B28:AY28)=SUM(B71:AY71) -> TRUE | B71: 45778 | C71: 0 | D71: NÃO | E71: NÃO | F71: 45809 | G71: 0 | H71: NÃO | I71: NÃO | J71: 45839 | K71: 0 | L71: NÃO | M71: NÃO | N71: 45870 | O71: 0 | P71: NÃO | Q71: NÃO | R71: 45901 | S71: 0 | T71: NÃO | U71: NÃO | V71: 45931 | W71: 509.11 | X71: 45919 | Y71: NÃO - FOI ABATIDO DO FUNDO DE RESERVA | Z71: 45962 | AA71: 0 | AB71: NÃO | AC71: NÃO | AD71: 45992 | AE71: 0 | AF71: NÃO | AG71: NÃO | AH71: 46023 | AI71: 0 | AJ71: NÃO | AK71: NÃO | AL71: 46054 | AM71: 0 | AN71: NÃO | AO71: NÃO | AP71: 46082 | AQ71: 0 | AR71: NÃO | AS71: NÃO | AT71: 46113 | AU71: 0 | AV71: NÃO | AW71: NÃO | AY71: SINALIZAÇÃO HORIZONTAL NA RUA EM FRENTE À GARAGEM | AZ71: TRUE
A72: =SUM(B29:AY29)=SUM(B72:AY72) -> TRUE | B72: 45778 | C72: 0 | D72: NÃO | E72: NÃO | F72: 45809 | G72: 0 | H72: NÃO | I72: NÃO | J72: 45839 | K72: 0 | L72: NÃO | M72: NÃO | N72: 45870 | O72: 0 | P72: NÃO | Q72: NÃO | R72: 45901 | S72: 0 | T72: NÃO | U72: NÃO | V72: 45931 | W72: 0 | X72: NÃO | Y72: NÃO | Z72: 45962 | AA72: 803.03 | AB72: 15 E 24/10/25 | AC72: NÃO | AD72: 45992 | AE72: 0 | AF72: NÃO | AG72: NÃO | AH72: 46023 | AI72: 0 | AJ72: NÃO | AK72: NÃO | AL72: 46054 | AM72: 0 | AN72: NÃO | AO72: NÃO | AP72: 46082 | AQ72: 0 | AR72: NÃO | AS72: NÃO | AT72: 46113 | AU72: 0 | AV72: NÃO | AW72: NÃO | AY72: CONSULTORIA E A.R.T. P/RENOV.AUTO DE VISTORIA/CORPO DE BOMBEIROS | AZ72: TRUE
A73: =SUM(B30:AY30)=SUM(B73:AY73) -> TRUE | B73: 45778 | C73: 0 | D73: NÃO | E73: NÃO | F73: 45809 | G73: 0 | H73: NÃO | I73: NÃO | J73: 45839 | K73: 0 | L73: NÃO | M73: NÃO | N73: 45870 | O73: 0 | P73: NÃO | Q73: NÃO | R73: 45901 | S73: 0 | T73: NÃO | U73: NÃO | V73: 45931 | W73: 0 | X73: NÃO | Y73: NÃO | Z73: 45962 | AA73: 0 | AB73: NÃO | AC73: NÃO | AD73: 45992 | AE73: 660 | AF73: 45995 | AG73: NÃO | AH73: 46023 | AI73: 0 | AJ73: NÃO | AK73: NÃO | AL73: 46054 | AM73: 0 | AN73: NÃO | AO73: NÃO | AP73: 46082 | AQ73: 0 | AR73: NÃO | AS73: NÃO | AT73: 46113 | AU73: 0 | AV73: NÃO | AW73: NÃO | AY73: DESENTUPIMENTO DO ESGOTO DO PRÉDIO | AZ73: TRUE
A74: =SUM(B31:AY31)=SUM(B74:AY74) -> TRUE | B74: 45778 | C74: 0 | D74: NÃO | E74: NÃO | F74: 45809 | G74: 0 | H74: NÃO | I74: NÃO | J74: 45839 | K74: 0 | L74: NÃO | M74: NÃO | N74: 45870 | O74: 0 | P74: NÃO | Q74: NÃO | R74: 45901 | S74: 0 | T74: NÃO | U74: NÃO | V74: 45931 | W74: 0 | X74: NÃO | Y74: NÃO | Z74: 45962 | AA74: 0 | AB74: NÃO | AC74: NÃO | AD74: 45992 | AE74: 0 | AF74: NÃO | AG74: NÃO | AH74: 46023 | AI74: 855 | AJ74: 46008 | AK74: NÃO - MANUTENÇÃO E INSTALAÇÃO DE MOLA | AL74: 46054 | AM74: 0 | AN74: NÃO | AO74: NÃO | AP74: 46082 | AQ74: 0 | AR74: NÃO | AS74: NÃO | AT74: 46113 | AU74: 0 | AV74: NÃO | AW74: NÃO | AY74: PORTA DE VIDRO, 1º ANDAR | AZ74: TRUE
A75: =SUM(B32:AY32)=SUM(B75:AY75) -> TRUE | B75: 45778 | C75: 0 | D75: NÃO | E75: NÃO | F75: 45809 | G75: 0 | H75: NÃO | I75: NÃO | J75: 45839 | K75: 0 | L75: NÃO | M75: NÃO | N75: 45870 | O75: 0 | P75: NÃO | Q75: NÃO | R75: 45901 | S75: 0 | T75: NÃO | U75: NÃO | V75: 45931 | W75: 0 | X75: NÃO | Y75: NÃO | Z75: 45962 | AA75: 0 | AB75: NÃO | AC75: NÃO | AD75: 45992 | AE75: 0 | AF75: NÃO | AG75: NÃO | AH75: 46023 | AI75: 0 | AJ75: NÃO | AK75: NÃO | AL75: 46054 | AM75: 0 | AN75: NÃO | AO75: NÃO | AP75: 46082 | AQ75: 0 | AR75: NÃO | AS75: NÃO | AT75: 46113 | AU75: 0 | AV75: NÃO | AW75: NÃO | AY75: COPIAR/COLAR ESTA LINHA PARA NOVA DESPESA | AZ75: TRUE
A76: =SUM(B33:AY33)=SUM(B76:AY76) -> TRUE | B76: 45778 | C76: 544.41 | D76: 45778 | E76: NÃO | F76: 45809 | G76: 589.49 | H76: 45810 | I76: NÃO | J76: 45839 | K76: 487.8 | L76: 45839 | M76: NÃO | N76: 45870 | O76: 545.62 | P76: 45870 | Q76: NÃO | R76: 45901 | S76: 570.56 | T76: 45901 | U76: NÃO | V76: 45931 | W76: 478.07 | X76: 45931 | Y76: NÃO | Z76: 45962 | AA76: 435.18 | AB76: 45962 | AC76: NÃO | AD76: 45992 | AE76: 490.06 | AF76: 45993 | AG76: NÃO | AH76: 46023 | AI76: 526.58 | AJ76: 46024 | AK76: NÃO | AL76: 46054 | AM76: 463.48 | AN76: 46055 | AO76: NÃO | AP76: 46082 | AQ76: 454.67 | AR76: 46083 | AS76: NÃO | AT76: 46113 | AU76: 564.68 | AV76: 46113 | AW76: NÃO | AY76: PAGAMENTO SERVIÇO DO SÍNDICO - TEM FÓRMULA DE "IGUAL", NÃO PRECISA PREENCHER | AZ76: TRUE
A77: =SUM(B34:AY34)=SUM(B77:AY77) -> TRUE | B77: 45778 | C77: 150 | D77: 45778 | E77: SIM | F77: 45809 | G77: 150 | H77: 45810 | I77: SIM - TEM FÓRMULA DE "IGUAL", NÃO PRECISA PREENCHER | J77: 45839 | K77: 150 | L77: 45839 | M77: SIM - TEM FÓRMULA DE "IGUAL", NÃO PRECISA PREENCHER | N77: 45870 | O77: 150 | P77: 45870 | Q77: SIM - TEM FÓRMULA DE "IGUAL", NÃO PRECISA PREENCHER | R77: 45901 | S77: 150 | T77: 45901 | U77: SIM - TEM FÓRMULA DE "IGUAL", NÃO PRECISA PREENCHER | V77: 45931 | W77: 150 | X77: 45931 | Y77: SIM - TEM FÓRMULA DE "IGUAL", NÃO PRECISA PREENCHER | Z77: 45962 | AA77: 150 | AB77: 45962 | AC77: SIM - TEM FÓRMULA DE "IGUAL", NÃO PRECISA PREENCHER | AD77: 45992 | AE77: 150 | AF77: 45993 | AG77: SIM | AH77: 46023 | AI77: 150 | AJ77: 46024 | AK77: SIM | AL77: 46054 | AM77: 150 | AN77: 46055 | AO77: SIM | AP77: 46082 | AQ77: 150 | AR77: 46083 | AS77: SIM | AT77: 46113 | AU77: 150 | AV77: 46113 | AW77: SIM | AY77: FUNDO DE RESERVA - TEM FÓRMULA DE "IGUAL", NÃO PRECISA PREENCHER | AZ77: TRUE
A80: =SUM(B37:AY37)=SUM(B80:AY80) -> TRUE | C80: 4063.74 | G80: 4107.43 | K80: 3994.18 | O80: 3510.92 | S80: 4306.49 | W80: 3985.15 | AA80: 3844.04 | AE80: 4024.94 | AI80: 3750.32 | AM80: 3871.41 | AQ80: 3803.35 | AU80: 4065.65 | AY80: TOTAL A INFORMAR NA PLAN. P/CONDÔM. (SERVE APENAS PARA COMPARAR COM O TOTAL DOS LANÇAMENTOS DAQUELA PLANILHA)
A81: O TOTAL DA LINHA ACIMA COINCIDE COM OS LANÇAMENTOS DA PLANILHA "PLAN P COND" | B81: PARA INSERIR COR NA FÓRMULA: PÁGINA INICIAL / FORMATAÇÃO CONDICIONAL / REGRAS DE REALCE DAS CÉLULAS / É IGUAL A... (VERDADEIRO OU FALSO, UM DE CADA VEZ) / FORMATAR PERSONALIZADO | AQ81: FALSE | AU81: TRUE | AY81: O TOTAL DA LINHA ACIMA COINCIDE COM OS LANÇAMENTOS DA PLANILHA "PLAN P COND" | AZ81: PARA INSERIR COR NA FÓRMULA: PÁGINA INICIAL / FORMATAÇÃO CONDICIONAL / REGRAS DE REALCE DAS CÉLULAS / É IGUAL A... (VERDADEIRO OU FALSO, UM DE CADA VEZ) / FORMATAR PERSONALIZADO
A82: OBS.: COM FÓRMULAS PARA PREENCHIMENTO DOS DOIS VALORES DE ÁGUA | AY82: OBS.: COM FÓRMULAS PARA PREENCHIMENTO DOS DOIS VALORES DE ÁGUA

Sheet VRS. DEVIDOS E OUTROS
A1: VALORES DEVIDOS POR UNIDADE, TABELA CRIADA EM 07/07/2025 | E1: COPIAR/COLAR ESPECIAL (TRANSPOR) AQUI OS DADOS DA TABELA "VALORES DEVIDOS POR UNIDADE" DA PLANILHA "MEDIÇÕES E TABELAS", ATÉ A COLUNA REFERENTE AO APTº 802 | W1: TAB. ESQUERDA X DIREITA | Y1: VALORES DEVIDOS POR UNIDADE, TABELA CRIADA EM 07/07/2025 | AC1: COPIAR/COLAR ESPECIAL (TRANSPOR) AQUI OS DADOS DA TABELA "VALORES DEVIDOS POR UNIDADE" DA PLANILHA "MEDIÇÕES E TABELAS", ATÉ A COLUNA REFERENTE AO APTº 802
A2: REF. | B2: ITEM/UNIDADE | C2: CONDOMÍNIO | D2: 201 | E2: 202 | F2: 301 | G2: 302 | H2: 401 | I2: 402 | J2: 501 | K2: 502 | L2: 601 | M2: 602 | N2: 701 | O2: 702 | P2: 801 | Q2: 802 | R2: TOTAL/MÊS (R$) | S2: Nº OFÍCIO | T2: DATA OFÍCIO | U2: DATA-LIMITE P/PAGTº | W2: =SUM(A2:U2)=SUM(Y2:AS2) -> TRUE | Y2: REF. | Z2: ITEM/UNIDADE | AA2: CONDOMÍNIO | AB2: 201 | AC2: 202 | AD2: 301 | AE2: 302 | AF2: 401 | AG2: 402 | AH2: 501 | AI2: 502 | AJ2: 601 | AK2: 602 | AL2: 701 | AM2: 702 | AN2: 801 | AO2: 802 | AP2: TOTAL/MÊS (R$) | AQ2: Nº OFÍCIO | AR2: DATA OFÍCIO | AS2: DATA-LIMITE P/PAGTº
A3: 45778 | B3: COPASA CONSUMO M³ | C3: 0 | D3: 23.72 | E3: 42.058 | F3: 20.333 | G3: 27.45 | H3: 20.201 | I3: 32.951 | J3: 15.228 | K3: 12.144 | L3: 7.419 | M3: 22.798 | N3: 15.958 | O3: 6.894 | P3: 5.998 | Q3: 15.122 | R3: DESPREZAR | S3: =A3 -> 45778 | T3: 45778 | U3: 45786 | W3: =SUM(A3:U3)=SUM(Y3:AS3) -> TRUE | Y3: 45778 | Z3: COPASA CONSUMO M³ | AA3: 0 | AB3: 23.72 | AC3: 42.058 | AD3: 20.333 | AE3: 27.45 | AF3: 20.201 | AG3: 32.951 | AH3: 15.228 | AI3: 12.144 | AJ3: 7.419 | AK3: 22.798 | AL3: 15.958 | AM3: 6.894 | AN3: 5.998 | AO3: 15.122 | AP3: DESPREZAR | AQ3: 45778 | AR3: 45778 | AS3: 45786
A4: 45778 | B4: COPASA ÁGUA/ESGOTO (R$) | C4: 0 | D4: 256.5 | E4: 388.53 | F4: 232.11 | G4: 283.36 | H4: 231.16 | I4: 322.96 | J4: 195.36 | K4: 173.15 | L4: 139.13 | M4: 249.86 | N4: 200.61 | O4: 135.35 | P4: 128.9 | Q4: 194.59 | R4: DESPREZAR | S4: =A4 -> 45778 | T4: 45778 | U4: 45786 | W4: =SUM(A4:U4)=SUM(Y4:AS4) -> TRUE | Y4: 45778 | Z4: COPASA ÁGUA/ESGOTO (R$) | AA4: 0 | AB4: 256.5 | AC4: 388.53 | AD4: 232.11 | AE4: 283.36 | AF4: 231.16 | AG4: 322.96 | AH4: 195.36 | AI4: 173.15 | AJ4: 139.13 | AK4: 249.86 | AL4: 200.61 | AM4: 135.35 | AN4: 128.9 | AO4: 194.59 | AP4: DESPREZAR | AQ4: 45778 | AR4: 45778 | AS4: 45786
A5: 45778 | B5: GÁS CONSUMO M³ | C5: 0 | D5: 0.064 | E5: 4.058 | F5: 4.072 | G5: 2.869 | H5: 1.566 | I5: 4.645 | J5: 1.127 | K5: 1.203 | L5: 0.222 | M5: 1.949 | N5: 0.859 | O5: 3.338 | P5: 0.003 | Q5: 1.715 | R5: DESPREZAR | S5: =A5 -> 45778 | T5: 45778 | U5: 45786 | W5: =SUM(A5:U5)=SUM(Y5:AS5) -> TRUE | Y5: 45778 | Z5: GÁS CONSUMO M³ | AA5: 0 | AB5: 0.064 | AC5: 4.058 | AD5: 4.072 | AE5: 2.869 | AF5: 1.566 | AG5: 4.645 | AH5: 1.127 | AI5: 1.203 | AJ5: 0.222 | AK5: 1.949 | AL5: 0.859 | AM5: 3.338 | AN5: 0.003 | AO5: 1.715 | AP5: DESPREZAR | AQ5: 45778 | AR5: 45778 | AS5: 45786
A6: 45778 | B6: GÁS VALOR (R$) | C6: 0 | D6: 2.22 | E6: 140.91 | F6: 141.4 | G6: 99.63 | H6: 54.38 | I6: 161.3 | J6: 39.14 | K6: 41.77 | L6: 7.71 | M6: 67.68 | N6: 29.83 | O6: 115.91 | P6: 0.1 | Q6: 59.55 | R6: DESPREZAR | S6: =A6 -> 45778 | T6: 45778 | U6: 45786 | W6: =SUM(A6:U6)=SUM(Y6:AS6) -> TRUE | Y6: 45778 | Z6: GÁS VALOR (R$) | AA6: 0 | AB6: 2.22 | AC6: 140.91 | AD6: 141.4 | AE6: 99.63 | AF6: 54.38 | AG6: 161.3 | AH6: 39.14 | AI6: 41.77 | AJ6: 7.71 | AK6: 67.68 | AL6: 29.83 | AM6: 115.91 | AN6: 0.1 | AO6: 59.55 | AP6: DESPREZAR | AQ6: 45778 | AR6: 45778 | AS6: 45786
A7: 45778 | B7: RATEIO (R$) | C7: 0 | D7: 462.6 | E7: 462.6 | F7: 462.6 | G7: 462.6 | H7: 462.6 | I7: 462.6 | J7: 462.6 | K7: 462.6 | L7: 462.6 | M7: 462.6 | N7: 462.6 | O7: 462.6 | P7: 462.6 | Q7: 462.6 | R7: DESPREZAR | S7: =A7 -> 45778 | T7: 45778 | U7: 45786 | W7: =SUM(A7:U7)=SUM(Y7:AS7) -> TRUE | Y7: 45778 | Z7: RATEIO (R$) | AA7: 0 | AB7: 462.6 | AC7: 462.6 | AD7: 462.6 | AE7: 462.6 | AF7: 462.6 | AG7: 462.6 | AH7: 462.6 | AI7: 462.6 | AJ7: 462.6 | AK7: 462.6 | AL7: 462.6 | AM7: 462.6 | AN7: 462.6 | AO7: 462.6 | AP7: DESPREZAR | AQ7: 45778 | AR7: 45778 | AS7: 45786
A8: 45778 | B8: TOTAL A PAGAR(R$) ARRED. | C8: 0 | D8: 722 | E8: 993 | F8: 837 | G8: 846 | H8: 749 | I8: 947 | J8: 698 | K8: 678 | L8: 610 | M8: 781 | N8: 694 | O8: 714 | P8: 592 | Q8: 717 | R8: =SUM(C8:P8)+LANÇTºS!C34 -> 10011 | S8: =A8 -> 45778 | T8: 45778 | U8: 45786 | W8: =SUM(A8:U8)=SUM(Y8:AS8) -> TRUE | Y8: 45778 | Z8: TOTAL A PAGAR(R$) ARRED. | AA8: 0 | AB8: 722 | AC8: 993 | AD8: 837 | AE8: 846 | AF8: 749 | AG8: 947 | AH8: 698 | AI8: 678 | AJ8: 610 | AK8: 781 | AL8: 694 | AM8: 714 | AN8: 592 | AO8: 717 | AP8: 10011 | AQ8: 45778 | AR8: 45778 | AS8: 45786
A9: 45778 | B9: TOTAL A PAGAR(R$) SEM ARRED. | C9: 0 | D9: =SUM(D4+D6+D7) -> 721.32 | E9: =SUM(E4+E6+E7) -> 992.04 | F9: =SUM(F4+F6+F7) -> 836.11 | G9: =SUM(G4+G6+G7) -> 845.59 | H9: =SUM(H4+H6+H7) -> 748.14 | I9: =SUM(I4+I6+I7) -> 946.86 | J9: =SUM(J4+J6+J7) -> 697.1 | K9: =SUM(K4+K6+K7) -> 677.52 | ... Q9: =SUM(Q4+Q6+Q7) -> 716.74 | R9: =SUM(C9:P9)+LANÇTºS!C34 -> 10002.76 | S9: =A9 -> 45778 | T9: 45778 | U9: 45786 | W9: =SUM(A9:U9)=SUM(Y9:AS9) -> TRUE | Y9: 45778 | Z9: TOTAL A PAGAR(R$) SEM ARRED. | AA9: 0 | AB9: 721.32 | AC9: 992.04 | AD9: 836.11 | AE9: 845.59 | AF9: 748.14 | AG9: 946.86 | AH9: 697.1 | AI9: 677.52 | AJ9: 609.44 | AK9: 780.14 | AL9: 693.04 | AM9: 713.86 | AN9: 591.6 | AO9: 716.74 | AP9: 10002.76 | AQ9: 45778 | AR9: 45778 | AS9: 45786
A10: 45809 | B10: COPASA CONSUMO M³ | C10: 37.284 | D10: 26.381 | E10: 47.542 | F10: 20.594 | G10: 26.897 | H10: 22.582 | I10: 40.303 | J10: 13.752 | K10: 14.073 | L10: 4.473 | M10: 17.373 | N10: 13.533 | O10: 6.148 | P10: 4.692 | Q10: 13.373 | R10: DESPREZAR | S10: =A10 -> 45809 | T10: 45809 | U10: 45818 | W10: =SUM(A10:U10)=SUM(Y10:AS10) -> TRUE | Y10: 45809 | Z10: COPASA CONSUMO M³ | AA10: 37.284 | AB10: 26.381 | AC10: 47.542 | AD10: 20.594 | AE10: 26.897 | AF10: 22.582 | AG10: 40.303 | AH10: 13.752 | AI10: 14.073 | AJ10: 4.473 | AK10: 17.373 | AL10: 13.533 | AM10: 6.148 | AN10: 4.692 | AO10: 13.373 | AP10: DESPREZAR | AQ10: 45809 | AR10: 45809 | AS10: 45818
A11: 45809 | B11: COPASA ÁGUA/ESGOTO (R$) | C11: 429.47 | D11: 339.18 | E11: 512.06 | F11: 291.9 | G11: 343.39 | H11: 308.14 | I11: 452.92 | J11: 236 | K11: 238.62 | L11: 160.19 | M11: 265.58 | N11: 234.21 | O11: 173.87 | P11: 161.98 | Q11: 232.9 | R11: DESPREZAR | S11: =A11 -> 45809 | T11: 45809 | U11: 45818 | W11: =SUM(A11:U11)=SUM(Y11:AS11) -> TRUE | Y11: 45809 | Z11: COPASA ÁGUA/ESGOTO (R$) | AA11: 429.47 | AB11: 339.18 | AC11: 512.06 | AD11: 291.9 | AE11: 343.39 | AF11: 308.14 | AG11: 452.92 | AH11: 236 | AI11: 238.62 | AJ11: 160.19 | AK11: 265.58 | AL11: 234.21 | AM11: 173.87 | AN11: 161.98 | AO11: 232.9 | AP11: DESPREZAR | AQ11: 45809 | AR11: 45809 | AS11: 45818
A12: 45809 | B12: GÁS CONSUMO M³ | C12: 0 | D12: 0.02 | E12: 3.794 | F12: 2.99 | G12: 2.077 | H12: 1.428 | I12: 4.705 | J12: 0.936 | K12: 1.414 | L12: 0.585 | M12: 1.458 | N12: 0.576 | O12: 3.584 | P12: 0 | Q12: 1.82 | R12: DESPREZAR | S12: =A12 -> 45809 | T12: 45809 | U12: 45818 | W12: =SUM(A12:U12)=SUM(Y12:AS12) -> TRUE | Y12: 45809 | Z12: GÁS CONSUMO M³ | AA12: 0 | AB12: 0.02 | AC12: 3.794 | AD12: 2.99 | AE12: 2.077 | AF12: 1.428 | AG12: 4.705 | AH12: 0.936 | AI12: 1.414 | AJ12: 0.585 | AK12: 1.458 | AL12: 0.576 | AM12: 3.584 | AN12: 0 | AO12: 1.82 | AP12: DESPREZAR | AQ12: 45809 | AR12: 45809 | AS12: 45818
A13: 45809 | B13: GÁS VALOR (R$) | C13: 0 | D13: 0.69 | E13: 131.75 | F13: 103.83 | G13: 72.12 | H13: 49.59 | I13: 163.38 | J13: 32.5 | K13: 49.1 | L13: 20.31 | M13: 50.63 | N13: 20 | O13: 124.45 | P13: 0 | Q13: 63.2 | R13: DESPREZAR | S13: =A13 -> 45809 | T13: 45809 | U13: 45818 | W13: =SUM(A13:U13)=SUM(Y13:AS13) -> TRUE | Y13: 45809 | Z13: GÁS VALOR (R$) | AA13: 0 | AB13: 0.69 | AC13: 131.75 | AD13: 103.83 | AE13: 72.12 | AF13: 49.59 | AG13: 163.38 | AH13: 32.5 | AI13: 49.1 | AJ13: 20.31 | AK13: 50.63 | AL13: 20 | AM13: 124.45 | AN13: 0 | AO13: 63.2 | AP13: DESPREZAR | AQ13: 45809 | AR13: 45809 | AS13: 45818
A14: 45809 | B14: RATEIO (R$) | C14: 0 | D14: 465.96 | E14: 465.96 | F14: 465.96 | G14: 465.96 | H14: 465.96 | I14: 465.96 | J14: 465.96 | K14: 465.96 | L14: 465.96 | M14: 465.96 | N14: 465.96 | O14: 465.96 | P14: 465.96 | Q14: 465.96 | R14: DESPREZAR | S14: =A14 -> 45809 | T14: 45809 | U14: 45818 | W14: =SUM(A14:U14)=SUM(Y14:AS14) -> TRUE | Y14: 45809 | Z14: RATEIO (R$) | AA14: 0 | AB14: 465.96 | AC14: 465.96 | AD14: 465.96 | AE14: 465.96 | AF14: 465.96 | AG14: 465.96 | AH14: 465.96 | AI14: 465.96 | AJ14: 465.96 | AK14: 465.96 | AL14: 465.96 | AM14: 465.96 | AN14: 465.96 | AO14: 465.96 | AP14: DESPREZAR | AQ14: 45809 | AR14: 45809 | AS14: 45818
A15: 45809 | B15: TOTAL A PAGAR(R$) ARRED. | C15: 0 | D15: 806 | E15: 1110 | F15: 862 | G15: 882 | H15: 824 | I15: 1083 | J15: 735 | K15: 754 | L15: 647 | M15: 783 | N15: 721 | O15: 765 | P15: 628 | Q15: 763 | R15: =SUM(C15:P15)+LANÇTºS!G34 -> 10750 | S15: =A15 -> 45809 | T15: 45809 | U15: 45818 | W15: =SUM(A15:U15)=SUM(Y15:AS15) -> TRUE | Y15: 45809 | Z15: TOTAL A PAGAR(R$) ARRED. | AA15: 0 | AB15: 806 | AC15: 1110 | AD15: 862 | AE15: 882 | AF15: 824 | AG15: 1083 | AH15: 735 | AI15: 754 | AJ15: 647 | AK15: 783 | AL15: 721 | AM15: 765 | AN15: 628 | AO15: 763 | AP15: 10750 | AQ15: 45809 | AR15: 45809 | AS15: 45818
A16: 45809 | B16: TOTAL A PAGAR(R$) SEM ARRED. | C16: 0 | D16: =SUM(D11+D13+D14) -> 805.83 | E16: =SUM(E11+E13+E14) -> 1109.77 | F16: =SUM(F11+F13+F14) -> 861.69 | G16: =SUM(G11+G13+G14) -> 881.47 | H16: =SUM(H11+H13+H14) -> 823.69 | I16: =SUM(I11+I13+I14) -> 1082.26 | J16: =SUM(J11+J13+J14) -> 734.46 | K16: =SUM(K11+K13+K14) -> 753.68 | ... Q16: =SUM(Q11+Q13+Q14) -> 762.06 | R16: =SUM(C16:P16)+LANÇTºS!G34 -> 10743.87 | S16: =A16 -> 45809 | T16: 45809 | U16: 45818 | W16: =SUM(A16:U16)=SUM(Y16:AS16) -> TRUE | Y16: 45809 | Z16: TOTAL A PAGAR(R$) SEM ARRED. | AA16: 0 | AB16: 805.83 | AC16: 1109.77 | AD16: 861.69 | AE16: 881.47 | AF16: 823.69 | AG16: 1082.26 | AH16: 734.46 | AI16: 753.68 | AJ16: 646.46 | AK16: 782.17 | AL16: 720.17 | AM16: 764.28 | AN16: 627.94 | AO16: 762.06 | AP16: 10743.87 | AQ16: 45809 | AR16: 45809 | AS16: 45818
A17: 45839 | B17: COPASA CONSUMO M³ | C17: 0 | D17: 25.752 | E17: 45.391 | F17: 18.831 | G17: 28.155 | H17: 24.281 | I17: 63.423 | J17: 16.296 | K17: 13.972 | L17: 5.706 | M17: 19.087 | N17: 15.301 | O17: 6.396 | P17: 3.291 | Q17: 10.814 | R17: DESPREZAR | S17: =A17 -> 45839 | T17: 45839 | U17: 45846 | W17: =SUM(A17:U17)=SUM(Y17:AS17) -> TRUE | Y17: 45839 | Z17: COPASA CONSUMO M³ | AA17: 0 | AB17: 25.752 | AC17: 45.391 | AD17: 18.831 | AE17: 28.155 | AF17: 24.281 | AG17: 63.423 | AH17: 16.296 | AI17: 13.972 | AJ17: 5.706 | AK17: 19.087 | AL17: 15.301 | AM17: 6.396 | AN17: 3.291 | AO17: 10.814 | AP17: DESPREZAR | AQ17: 45839 | AR17: 45839 | AS17: 45846
A18: 45839 | B18: COPASA ÁGUA/ESGOTO (R$) | C18: 0 | D18: 346.21 | E18: 610.25 | F18: 253.17 | G18: 378.52 | H18: 326.44 | I18: 852.68 | J18: 219.08 | K18: 187.84 | L18: 76.71 | M18: 256.61 | N18: 205.71 | O18: 85.99 | P18: 44.24 | Q18: 145.38 | R18: DESPREZAR | S18: =A18 -> 45839 | T18: 45839 | U18: 45846 | W18: =SUM(A18:U18)=SUM(Y18:AS18) -> TRUE | Y18: 45839 | Z18: COPASA ÁGUA/ESGOTO (R$) | AA18: 0 | AB18: 346.21 | AC18: 610.25 | AD18: 253.17 | AE18: 378.52 | AF18: 326.44 | AG18: 852.68 | AH18: 219.08 | AI18: 187.84 | AJ18: 76.71 | AK18: 256.61 | AL18: 205.71 | AM18: 85.99 | AN18: 44.24 | AO18: 145.38 | AP18: DESPREZAR | AQ18: 45839 | AR18: 45839 | AS18: 45846
A19: 45839 | B19: GÁS CONSUMO M³ | C19: 0 | D19: 0.047 | E19: 4.334 | F19: 2.549 | G19: 2.077 | H19: 1.667 | I19: 5.586 | J19: 1.075 | K19: 1.327 | L19: 0.712 | M19: 1.884 | N19: 0.758 | O19: 3.643 | P19: 0 | Q19: 1.516 | R19: DESPREZAR | S19: =A19 -> 45839 | T19: 45839 | U19: 45846 | W19: =SUM(A19:U19)=SUM(Y19:AS19) -> TRUE | Y19: 45839 | Z19: GÁS CONSUMO M³ | AA19: 0 | AB19: 0.047 | AC19: 4.334 | AD19: 2.549 | AE19: 2.077 | AF19: 1.667 | AG19: 5.586 | AH19: 1.075 | AI19: 1.327 | AJ19: 0.712 | AK19: 1.884 | AL19: 0.758 | AM19: 3.643 | AN19: 0 | AO19: 1.516 | AP19: DESPREZAR | AQ19: 45839 | AR19: 45839 | AS19: 45846
A20: 45839 | B20: GÁS VALOR (R$) | C20: 0 | D20: 1.77 | E20: 163.28 | F20: 96.03 | G20: 78.25 | H20: 62.8 | I20: 210.45 | J20: 40.5 | K20: 49.99 | L20: 26.82 | M20: 70.98 | N20: 28.56 | O20: 137.25 | P20: 0 | Q20: 57.12 | R20: DESPREZAR | S20: =A20 -> 45839 | T20: 45839 | U20: 45846 | W20: =SUM(A20:U20)=SUM(Y20:AS20) -> TRUE | Y20: 45839 | Z20: GÁS VALOR (R$) | AA20: 0 | AB20: 1.77 | AC20: 163.28 | AD20: 96.03 | AE20: 78.25 | AF20: 62.8 | AG20: 210.45 | AH20: 40.5 | AI20: 49.99 | AJ20: 26.82 | AK20: 70.98 | AL20: 28.56 | AM20: 137.25 | AN20: 0 | AO20: 57.12 | AP20: DESPREZAR | AQ20: 45839 | AR20: 45839 | AS20: 45846
A21: 45839 | B21: RATEIO (R$) | C21: 0 | D21: 457.25 | E21: 457.25 | F21: 457.25 | G21: 457.25 | H21: 457.25 | I21: 457.25 | J21: 457.25 | K21: 457.25 | L21: 457.25 | M21: 457.25 | N21: 457.25 | O21: 457.25 | P21: 457.25 | Q21: 457.25 | R21: DESPREZAR | S21: =A21 -> 45839 | T21: 45839 | U21: 45846 | W21: =SUM(A21:U21)=SUM(Y21:AS21) -> TRUE | Y21: 45839 | Z21: RATEIO (R$) | AA21: 0 | AB21: 457.25 | AC21: 457.25 | AD21: 457.25 | AE21: 457.25 | AF21: 457.25 | AG21: 457.25 | AH21: 457.25 | AI21: 457.25 | AJ21: 457.25 | AK21: 457.25 | AL21: 457.25 | AM21: 457.25 | AN21: 457.25 | AO21: 457.25 | AP21: DESPREZAR | AQ21: 45839 | AR21: 45839 | AS21: 45846
A22: 45839 | B22: TOTAL A PAGAR(R$) ARRED. | C22: 0 | D22: 806 | E22: 1231 | F22: 807 | G22: 915 | H22: 847 | I22: 1521 | J22: 717 | K22: 696 | L22: 561 | M22: 785 | N22: 692 | O22: 681 | P22: 502 | Q22: 660 | R22: =SUM(C22:P22)+LANÇTºS!K34 -> 10911 | S22: =A22 -> 45839 | T22: 45839 | U22: 45846 | W22: =SUM(A22:U22)=SUM(Y22:AS22) -> TRUE | Y22: 45839 | Z22: TOTAL A PAGAR(R$) ARRED. | AA22: 0 | AB22: 806 | AC22: 1231 | AD22: 807 | AE22: 915 | AF22: 847 | AG22: 1521 | AH22: 717 | AI22: 696 | AJ22: 561 | AK22: 785 | AL22: 692 | AM22: 681 | AN22: 502 | AO22: 660 | AP22: 10911 | AQ22: 45839 | AR22: 45839 | AS22: 45846
A23: 45839 | B23: TOTAL A PAGAR(R$) SEM ARRED. | C23: 0 | D23: =SUM(D18+D20+D21) -> 805.23 | E23: =SUM(E18+E20+E21) -> 1230.78 | F23: =SUM(F18+F20+F21) -> 806.45 | G23: =SUM(G18+G20+G21) -> 914.02 | H23: =SUM(H18+H20+H21) -> 846.49 | I23: =SUM(I18+I20+I21) -> 1520.38 | J23: =SUM(J18+J20+J21) -> 716.83 | K23: =SUM(K18+K20+K21) -> 695.08 | ... Q23: =SUM(Q18+Q20+Q21) -> 659.75 | R23: =SUM(C23:P23)+LANÇTºS!K34 -> 10904.38 | S23: =A23 -> 45839 | T23: 45839 | U23: 45846 | W23: =SUM(A23:U23)=SUM(Y23:AS23) -> TRUE | Y23: 45839 | Z23: TOTAL A PAGAR(R$) SEM ARRED. | AA23: 0 | AB23: 805.23 | AC23: 1230.78 | AD23: 806.45 | AE23: 914.02 | AF23: 846.49 | AG23: 1520.38 | AH23: 716.83 | AI23: 695.08 | AJ23: 560.78 | AK23: 784.84 | AL23: 691.52 | AM23: 680.49 | AN23: 501.49 | AO23: 659.75 | AP23: 10904.38 | AQ23: 45839 | AR23: 45839 | AS23: 45846
A24: 45870 | B24: COPASA CONSUMO M³ | C24: 0 | D24: 14.55 | E24: 30.319 | F24: 18.924 | G24: 27.603 | H24: 27.395 | I24: 56.386 | J24: 15.234 | K24: 14.728 | L24: 3.861 | M24: 12.961 | N24: 16.448 | O24: 6.752 | P24: 5.867 | Q24: 16.04 | R24: DESPREZAR | S24: =A24 -> 45870 | T24: 45876 | U24: 45880 | W24: =SUM(A24:U24)=SUM(Y24:AS24) -> TRUE | Y24: 45870 | Z24: COPASA CONSUMO M³ | AA24: 0 | AB24: 14.55 | AC24: 30.319 | AD24: 18.924 | AE24: 27.603 | AF24: 27.395 | AG24: 56.386 | AH24: 15.234 | AI24: 14.728 | AJ24: 3.861 | AK24: 12.961 | AL24: 16.448 | AM24: 6.752 | AN24: 5.867 | AO24: 16.04 | AP24: DESPREZAR | AQ24: 45870 | AR24: 45876 | AS24: 45880
A25: 45870 | B25: COPASA ÁGUA/ESGOTO (R$) | C25: 0 | D25: 196.36 | E25: 407.09 | F25: 254.85 | G25: 371.29 | H25: 368.04 | I25: 758.28 | J25: 204.94 | K25: 197.74 | L25: 51.23 | M25: 174.21 | N25: 220.9 | O25: 90.02 | P25: 78.25 | Q25: 216.1 | R25: DESPREZAR | S25: =A25 -> 45870 | T25: 45876 | U25: 45880 | W25: =SUM(A25:U25)=SUM(Y25:AS25) -> TRUE | Y25: 45870 | Z25: COPASA ÁGUA/ESGOTO (R$) | AA25: 0 | AB25: 196.36 | AC25: 407.09 | AD25: 254.85 | AE25: 371.29 | AF25: 368.04 | AG25: 758.28 | AH25: 204.94 | AI25: 197.74 | AJ25: 51.23 | AK25: 174.21 | AL25: 220.9 | AM25: 90.02 | AN25: 78.25 | AO25: 216.1 | AP25: DESPREZAR | AQ25: 45870 | AR25: 45876 | AS25: 45880
A26: 45870 | B26: GÁS CONSUMO M³ | C26: 0 | D26: 0.026 | E26: 4.901 | F26: 3.337 | G26: 1.764 | H26: 1.798 | I26: 4.475 | J26: 1.143 | K26: 1.346 | L26: 0.403 | M26: 1.336 | N26: 1.529 | O26: 4.129 | P26: 0.011 | Q26: 2.09 | R26: DESPREZAR | S26: =A26 -> 45870 | T26: 45876 | U26: 45880 | W26: =SUM(A26:U26)=SUM(Y26:AS26) -> TRUE | Y26: 45870 | Z26: GÁS CONSUMO M³ | AA26: 0 | AB26: 0.026 | AC26: 4.901 | AD26: 3.337 | AE26: 1.764 | AF26: 1.798 | AG26: 4.475 | AH26: 1.143 | AI26: 1.346 | AJ26: 0.403 | AK26: 1.336 | AL26: 1.529 | AM26: 4.129 | AN26: 0.011 | AO26: 2.09 | AP26: DESPREZAR | AQ26: 45870 | AR26: 45876 | AS26: 45880
A27: 45870 | B27: GÁS VALOR (R$) | C27: 0 | D27: 0.98 | E27: 184.65 | F27: 125.72 | G27: 66.46 | H27: 67.74 | I27: 168.6 | J27: 43.06 | K27: 50.71 | L27: 15.18 | M27: 50.33 | N27: 57.61 | O27: 155.56 | P27: 0.41 | Q27: 78.74 | R27: DESPREZAR | S27: =A27 -> 45870 | T27: 45876 | U27: 45880 | W27: =SUM(A27:U27)=SUM(Y27:AS27) -> TRUE | Y27: 45870 | Z27: GÁS VALOR (R$) | AA27: 0 | AB27: 0.98 | AC27: 184.65 | AD27: 125.72 | AE27: 66.46 | AF27: 67.74 | AG27: 168.6 | AH27: 43.06 | AI27: 50.71 | AJ27: 15.18 | AK27: 50.33 | AL27: 57.61 | AM27: 155.56 | AN27: 0.41 | AO27: 78.74 | AP27: DESPREZAR | AQ27: 45870 | AR27: 45876 | AS27: 45880
A28: 45870 | B28: RATEIO (R$) | C28: 0 | D28: 420.07 | E28: 420.07 | F28: 420.07 | G28: 420.07 | H28: 420.07 | I28: 420.07 | J28: 420.07 | K28: 420.07 | L28: 420.07 | M28: 420.07 | N28: 420.07 | O28: 420.07 | P28: 420.07 | Q28: 420.07 | R28: DESPREZAR | S28: =A28 -> 45870 | T28: 45876 | U28: 45880 | W28: =SUM(A28:U28)=SUM(Y28:AS28) -> TRUE | Y28: 45870 | Z28: RATEIO (R$) | AA28: 0 | AB28: 420.07 | AC28: 420.07 | AD28: 420.07 | AE28: 420.07 | AF28: 420.07 | AG28: 420.07 | AH28: 420.07 | AI28: 420.07 | AJ28: 420.07 | AK28: 420.07 | AL28: 420.07 | AM28: 420.07 | AN28: 420.07 | AO28: 420.07 | AP28: DESPREZAR | AQ28: 45870 | AR28: 45876 | AS28: 45880
A29: 45870 | B29: TOTAL A PAGAR(R$) ARRED. | C29: 0 | D29: 618 | E29: 1012 | F29: 801 | G29: 858 | H29: 856 | I29: 1347 | J29: 669 | K29: 669 | L29: 487 | M29: 645 | N29: 699 | O29: 666 | P29: 499 | Q29: 715 | R29: =SUM(C29:P29)+LANÇTºS!O34 -> 9976 | S29: =A29 -> 45870 | T29: 45876 | U29: 45880 | W29: =SUM(A29:U29)=SUM(Y29:AS29) -> TRUE | Y29: 45870 | Z29: TOTAL A PAGAR(R$) ARRED. | AA29: 0 | AB29: 618 | AC29: 1012 | AD29: 801 | AE29: 858 | AF29: 856 | AG29: 1347 | AH29: 669 | AI29: 669 | AJ29: 487 | AK29: 645 | AL29: 699 | AM29: 666 | AN29: 499 | AO29: 715 | AP29: 9976 | AQ29: 45870 | AR29: 45876 | AS29: 45880
A30: 45870 | B30: TOTAL A PAGAR(R$) SEM ARRED. | C30: 0 | D30: =SUM(D25+D27+D28) -> 617.41 | E30: =SUM(E25+E27+E28) -> 1011.81 | F30: =SUM(F25+F27+F28) -> 800.64 | G30: =SUM(G25+G27+G28) -> 857.82 | H30: =SUM(H25+H27+H28) -> 855.85 | I30: =SUM(I25+I27+I28) -> 1346.95 | J30: =SUM(J25+J27+J28) -> 668.07 | K30: =SUM(K25+K27+K28) -> 668.52 | ... Q30: =SUM(Q25+Q27+Q28) -> 714.91 | R30: =SUM(C30:P30)+LANÇTºS!O34 -> 9971.12 | S30: =A30 -> 45870 | T30: 45876 | U30: 45880 | W30: =SUM(A30:U30)=SUM(Y30:AS30) -> TRUE | Y30: 45870 | Z30: TOTAL A PAGAR(R$) SEM ARRED. | AA30: 0 | AB30: 617.41 | AC30: 1011.81 | AD30: 800.64 | AE30: 857.82 | AF30: 855.85 | AG30: 1346.95 | AH30: 668.07 | AI30: 668.52 | AJ30: 486.48 | AK30: 644.61 | AL30: 698.58 | AM30: 665.65 | AN30: 498.73 | AO30: 714.91 | AP30: 9971.12 | AQ30: 45870 | AR30: 45876 | AS30: 45880
A31: 45901 | B31: COPASA CONSUMO M³ | C31: 7.357 | D31: 21.915 | E31: 24.036 | F31: 22.415 | G31: 29.597 | H31: 29.731 | I31: 59.282 | J31: 15.803 | K31: 13.932 | L31: 4.716 | M31: 22.479 | N31: 16.55 | O31: 7.645 | P31: 5.036 | Q31: 14.506 | R31: DESPREZAR | S31: =A31 -> 45901 | T31: 45901 | U31: 45910 | W31: =SUM(A31:U31)=SUM(Y31:AS31) -> TRUE | Y31: 45901 | Z31: COPASA CONSUMO M³ | AA31: 7.357 | AB31: 21.915 | AC31: 24.036 | AD31: 22.415 | AE31: 29.597 | AF31: 29.731 | AG31: 59.282 | AH31: 15.803 | AI31: 13.932 | AJ31: 4.716 | AK31: 22.479 | AL31: 16.55 | AM31: 7.645 | AN31: 5.036 | AO31: 14.506 | AP31: DESPREZAR | AQ31: 45901 | AR31: 45901 | AS31: 45910
A32: 45901 | B32: COPASA ÁGUA/ESGOTO (R$) | C32: 102.13 | D32: 298.05 | E32: 326.62 | F32: 305.39 | G32: 402.64 | H32: 405.39 | I32: 807.67 | J32: 216.02 | K32: 189.4 | L32: 64.26 | M32: 305.89 | N32: 225.28 | O32: 104.29 | P32: 68.48 | Q32: 197.32 | R32: DESPREZAR | S32: =A32 -> 45901 | T32: 45901 | U32: 45910 | W32: =SUM(A32:U32)=SUM(Y32:AS32) -> TRUE | Y32: 45901 | Z32: COPASA ÁGUA/ESGOTO (R$) | AA32: 102.13 | AB32: 298.05 | AC32: 326.62 | AD32: 305.39 | AE32: 402.64 | AF32: 405.39 | AG32: 807.67 | AH32: 216.02 | AI32: 189.4 | AJ32: 64.26 | AK32: 305.89 | AL32: 225.28 | AM32: 104.29 | AN32: 68.48 | AO32: 197.32 | AP32: DESPREZAR | AQ32: 45901 | AR32: 45901 | AS32: 45910
A33: 45901 | B33: GÁS CONSUMO M³ | C33: 0 | D33: 0.01 | E33: 4.971 | F33: 3.261 | G33: 1.601 | H33: 1.579 | I33: 5.264 | J33: 1.038 | K33: 1.421 | L33: 0.927 | M33: 2.18 | N33: 0.998 | O33: 5.029 | P33: 0.012 | Q33: 1.742 | R33: DESPREZAR | S33: =A33 -> 45901 | T33: 45901 | U33: 45910 | W33: =SUM(A33:U33)=SUM(Y33:AS33) -> TRUE | Y33: 45901 | Z33: GÁS CONSUMO M³ | AA33: 0 | AB33: 0.01 | AC33: 4.971 | AD33: 3.261 | AE33: 1.601 | AF33: 1.579 | AG33: 5.264 | AH33: 1.038 | AI33: 1.421 | AJ33: 0.927 | AK33: 2.18 | AL33: 0.998 | AM33: 5.029 | AN33: 0.012 | AO33: 1.742 | AP33: DESPREZAR | AQ33: 45901 | AR33: 45901 | AS33: 45910
A34: 45901 | B34: GÁS VALOR (R$) | C34: 0 | D34: 0.38 | E34: 187.28 | F34: 122.86 | G34: 60.32 | H34: 59.49 | I34: 198.32 | J34: 39.11 | K34: 53.54 | L34: 34.92 | M34: 82.13 | N34: 37.6 | O34: 189.47 | P34: 0.45 | Q34: 65.63 | R34: DESPREZAR | S34: =A34 -> 45901 | T34: 45901 | U34: 45910 | W34: =SUM(A34:U34)=SUM(Y34:AS34) -> TRUE | Y34: 45901 | Z34: GÁS VALOR (R$) | AA34: 0 | AB34: 0.38 | AC34: 187.28 | AD34: 122.86 | AE34: 60.32 | AF34: 59.49 | AG34: 198.32 | AH34: 39.11 | AI34: 53.54 | AJ34: 34.92 | AK34: 82.13 | AL34: 37.6 | AM34: 189.47 | AN34: 0.45 | AO34: 65.63 | AP34: DESPREZAR | AQ34: 45901 | AR34: 45901 | AS34: 45910
A35: 45901 | B35: RATEIO (R$) | C35: 0 | D35: 481.27 | E35: 481.27 | F35: 481.27 | G35: 481.27 | H35: 481.27 | I35: 481.27 | J35: 481.27 | K35: 481.27 | L35: 481.27 | M35: 481.27 | N35: 481.27 | O35: 481.27 | P35: 481.27 | Q35: 481.27 | R35: DESPREZAR | S35: =A35 -> 45901 | T35: 45901 | U35: 45910 | W35: =SUM(A35:U35)=SUM(Y35:AS35) -> TRUE | Y35: 45901 | Z35: RATEIO (R$) | AA35: 0 | AB35: 481.27 | AC35: 481.27 | AD35: 481.27 | AE35: 481.27 | AF35: 481.27 | AG35: 481.27 | AH35: 481.27 | AI35: 481.27 | AJ35: 481.27 | AK35: 481.27 | AL35: 481.27 | AM35: 481.27 | AN35: 481.27 | AO35: 481.27 | AP35: DESPREZAR | AQ35: 45901 | AR35: 45901 | AS35: 45910
A36: 45901 | B36: TOTAL A PAGAR(R$) ARRED. | C36: 0 | D36: 780 | E36: 996 | F36: 910 | G36: 945 | H36: 947 | I36: 1488 | J36: 737 | K36: 725 | L36: 581 | M36: 870 | N36: 745 | O36: 776 | P36: 551 | Q36: 745 | R36: =SUM(C36:P36)+E98 -> 11201 | S36: =A36 -> 45901 | T36: 45901 | U36: 45910 | W36: =SUM(A36:U36)=SUM(Y36:AS36) -> TRUE | Y36: 45901 | Z36: TOTAL A PAGAR(R$) ARRED. | AA36: 0 | AB36: 780 | AC36: 996 | AD36: 910 | AE36: 945 | AF36: 947 | AG36: 1488 | AH36: 737 | AI36: 725 | AJ36: 581 | AK36: 870 | AL36: 745 | AM36: 776 | AN36: 551 | AO36: 745 | AP36: 11201 | AQ36: 45901 | AR36: 45901 | AS36: 45910
A37: 45901 | B37: TOTAL A PAGAR(R$) SEM ARRED. | C37: 0 | D37: 779.7 | E37: 995.17 | F37: 909.52 | G37: 944.23 | H37: 946.15 | I37: 1487.26 | J37: 736.4 | K37: 724.21 | L37: 580.45 | M37: 869.29 | N37: 744.15 | O37: 775.03 | P37: 550.2 | Q37: 744.22 | R37: =SUM(C37:P37)+E98 -> 11191.76 | S37: =A37 -> 45901 | T37: 45901 | U37: 45910 | W37: =SUM(A37:U37)=SUM(Y37:AS37) -> TRUE | Y37: 45901 | Z37: TOTAL A PAGAR(R$) SEM ARRED. | AA37: 0 | AB37: 779.7 | AC37: 995.17 | AD37: 909.52 | AE37: 944.23 | AF37: 946.15 | AG37: 1487.26 | AH37: 736.4 | AI37: 724.21 | AJ37: 580.45 | AK37: 869.29 | AL37: 744.15 | AM37: 775.03 | AN37: 550.2 | AO37: 744.22 | AP37: 11191.76 | AQ37: 45901 | AR37: 45901 | AS37: 45910
A38: 45931 | B38: COPASA CONSUMO M³ | C38: 17.412 | D38: 20.42 | E38: 27.548 | F38: 21.158 | G38: 32.57 | H38: 33.442 | I38: 22.563 | J38: 15.966 | K38: 15.133 | L38: 4.109 | M38: 22.042 | N38: 17.985 | O38: 8.531 | P38: 4.311 | Q38: 10.81 | R38: DESPREZAR | S38: =A38 -> 45931 | T38: 45931 | U38: 45940 | W38: =SUM(A38:U38)=SUM(Y38:AS38) -> TRUE | Y38: 45931 | Z38: COPASA CONSUMO M³ | AA38: 17.412 | AB38: 20.42 | AC38: 27.548 | AD38: 21.158 | AE38: 32.57 | AF38: 33.442 | AG38: 22.563 | AH38: 15.966 | AI38: 15.133 | AJ38: 4.109 | AK38: 22.042 | AL38: 17.985 | AM38: 8.531 | AN38: 4.311 | AO38: 10.81 | AP38: DESPREZAR | AQ38: 45931 | AR38: 45931 | AS38: 45940
A39: 45931 | B39: COPASA ÁGUA/ESGOTO (R$) | C39: 348.46 | D39: 267.73 | E39: 361.04 | F39: 278.25 | G39: 426.94 | H39: 438.46 | I39: 295.42 | J39: 209.41 | K39: 198.18 | L39: 54.06 | M39: 289.86 | N39: 236.18 | O39: 112.14 | P39: 57.24 | Q39: 142.52 | R39: DESPREZAR | S39: =A39 -> 45931 | T39: 45931 | U39: 45940 | W39: =SUM(A39:U39)=SUM(Y39:AS39) -> TRUE | Y39: 45931 | Z39: COPASA ÁGUA/ESGOTO (R$) | AA39: 348.46 | AB39: 267.73 | AC39: 361.04 | AD39: 278.25 | AE39: 426.94 | AF39: 438.46 | AG39: 295.42 | AH39: 209.41 | AI39: 198.18 | AJ39: 54.06 | AK39: 289.86 | AL39: 236.18 | AM39: 112.14 | AN39: 57.24 | AO39: 142.52 | AP39: DESPREZAR | AQ39: 45931 | AR39: 45931 | AS39: 45940
A40: 45931 | B40: GÁS CONSUMO M³ | C40: 0 | D40: 0.123 | E40: 4.093 | F40: 3.478 | G40: 1.865 | H40: 1.58 | I40: 4.243 | J40: 1.123 | K40: 1.643 | L40: 0.598 | M40: 2.028 | N40: 0.725 | O40: 4.826 | P40: 0 | Q40: 1.351 | R40: DESPREZAR | S40: =A40 -> 45931 | T40: 45931 | U40: 45940 | W40: =SUM(A40:U40)=SUM(Y40:AS40) -> TRUE | Y40: 45931 | Z40: GÁS CONSUMO M³ | AA40: 0 | AB40: 0.123 | AC40: 4.093 | AD40: 3.478 | AE40: 1.865 | AF40: 1.58 | AG40: 4.243 | AH40: 1.123 | AI40: 1.643 | AJ40: 0.598 | AK40: 2.028 | AL40: 0.725 | AM40: 4.826 | AN40: 0 | AO40: 1.351 | AP40: DESPREZAR | AQ40: 45931 | AR40: 45931 | AS40: 45940
A41: 45931 | B41: GÁS VALOR (R$) | C41: 0 | D41: 4.63 | E41: 154.2 | F41: 131.03 | G41: 70.26 | H41: 59.53 | I41: 159.86 | J41: 42.31 | K41: 61.9 | L41: 22.53 | M41: 76.4 | N41: 27.31 | O41: 181.82 | P41: 0 | Q41: 50.9 | R41: DESPREZAR | S41: =A41 -> 45931 | T41: 45931 | U41: 45940 | W41: =SUM(A41:U41)=SUM(Y41:AS41) -> TRUE | Y41: 45931 | Z41: GÁS VALOR (R$) | AA41: 0 | AB41: 4.63 | AC41: 154.2 | AD41: 131.03 | AE41: 70.26 | AF41: 59.53 | AG41: 159.86 | AH41: 42.31 | AI41: 61.9 | AJ41: 22.53 | AK41: 76.4 | AL41: 27.31 | AM41: 181.82 | AN41: 0 | AO41: 50.9 | AP41: DESPREZAR | AQ41: 45931 | AR41: 45931 | AS41: 45940
A42: 45931 | B42: RATEIO (R$) | C42: 0 | D42: 456.55 | E42: 456.55 | F42: 456.55 | G42: 456.55 | H42: 456.55 | I42: 456.55 | J42: 456.55 | K42: 456.55 | L42: 456.55 | M42: 456.55 | N42: 456.55 | O42: 456.55 | P42: 456.55 | Q42: 456.55 | R42: DESPREZAR | S42: =A42 -> 45931 | T42: 45931 | U42: 45940 | W42: =SUM(A42:U42)=SUM(Y42:AS42) -> TRUE | Y42: 45931 | Z42: RATEIO (R$) | AA42: 0 | AB42: 456.55 | AC42: 456.55 | AD42: 456.55 | AE42: 456.55 | AF42: 456.55 | AG42: 456.55 | AH42: 456.55 | AI42: 456.55 | AJ42: 456.55 | AK42: 456.55 | AL42: 456.55 | AM42: 456.55 | AN42: 456.55 | AO42: 456.55 | AP42: DESPREZAR | AQ42: 45931 | AR42: 45931 | AS42: 45940
A43: 45931 | B43: TOTAL A PAGAR(R$) ARRED. | C43: 0 | D43: 729 | E43: 972 | F43: 866 | G43: 954 | H43: 955 | I43: 912 | J43: 709 | K43: 717 | L43: 534 | M43: 823 | N43: 721 | O43: 751 | P43: 514 | Q43: 650 | R43: =SUM(C43:P43)+E99 -> 10307 | S43: =A43 -> 45931 | T43: 45931 | U43: 45940 | W43: =SUM(A43:U43)=SUM(Y43:AS43) -> TRUE | Y43: 45931 | Z43: TOTAL A PAGAR(R$) ARRED. | AA43: 0 | AB43: 729 | AC43: 972 | AD43: 866 | AE43: 954 | AF43: 955 | AG43: 912 | AH43: 709 | AI43: 717 | AJ43: 534 | AK43: 823 | AL43: 721 | AM43: 751 | AN43: 514 | AO43: 650 | AP43: 10307 | AQ43: 45931 | AR43: 45931 | AS43: 45940
A44: 45931 | B44: TOTAL A PAGAR(R$) SEM ARRED. | C44: 0 | D44: 728.91 | E44: 971.79 | F44: 865.83 | G44: 953.75 | H44: 954.54 | I44: 911.83 | J44: 708.27 | K44: 716.63 | L44: 533.14 | M44: 822.81 | N44: 720.04 | O44: 750.51 | P44: 513.79 | Q44: 649.97 | R44: =SUM(C44:P44)+E99 -> 10301.84 | S44: =A44 -> 45931 | T44: 45931 | U44: 45940 | W44: =SUM(A44:U44)=SUM(Y44:AS44) -> TRUE | Y44: 45931 | Z44: TOTAL A PAGAR(R$) SEM ARRED. | AA44: 0 | AB44: 728.91 | AC44: 971.79 | AD44: 865.83 | AE44: 953.75 | AF44: 954.54 | AG44: 911.83 | AH44: 708.27 | AI44: 716.63 | AJ44: 533.14 | AK44: 822.81 | AL44: 720.04 | AM44: 750.51 | AN44: 513.79 | AO44: 649.97 | AP44: 10301.84 | AQ44: 45931 | AR44: 45931 | AS44: 45940
A45: 45962 | B45: COPASA CONSUMO M³ | C45: 12.106 | D45: 20.173 | E45: 10.409 | F45: 18.708 | G45: 33.741 | H45: 34.406 | I45: 21.869 | J45: 14.157 | K45: 13.134 | L45: 3.344 | M45: 25.558 | N45: 16.892 | O45: 7.872 | P45: 4.001 | Q45: 10.63 | R45: DESPREZAR | S45: =A45 -> 45962 | T45: 45961 | U45: 45971 | W45: =SUM(A45:U45)=SUM(Y45:AS45) -> TRUE | Y45: 45962 | Z45: COPASA CONSUMO M³ | AA45: 12.106 | AB45: 20.173 | AC45: 10.409 | AD45: 18.708 | AE45: 33.741 | AF45: 34.406 | AG45: 21.869 | AH45: 14.157 | AI45: 13.134 | AJ45: 3.344 | AK45: 25.558 | AL45: 16.892 | AM45: 7.872 | AN45: 4.001 | AO45: 10.63 | AP45: DESPREZAR | AQ45: 45962 | AR45: 45961 | AS45: 45971
A46: 45962 | B46: COPASA ÁGUA/ESGOTO (R$) | C46: 351.47 | D46: 232.39 | E46: 119.8 | F46: 215.44 | G46: 389.04 | H46: 397.69 | I46: 252.3 | J46: 163.45 | K46: 152.25 | L46: 38.16 | M46: 295.53 | N46: 194.67 | O46: 91.29 | P46: 46.76 | Q46: 122.67 | R46: DESPREZAR | S46: =A46 -> 45962 | T46: 45961 | U46: 45971 | W46: =SUM(A46:U46)=SUM(Y46:AS46) -> TRUE | Y46: 45962 | Z46: COPASA ÁGUA/ESGOTO (R$) | AA46: 351.47 | AB46: 232.39 | AC46: 119.8 | AD46: 215.44 | AE46: 389.04 | AF46: 397.69 | AG46: 252.3 | AH46: 163.45 | AI46: 152.25 | AJ46: 38.16 | AK46: 295.53 | AL46: 194.67 | AM46: 91.29 | AN46: 46.76 | AO46: 122.67 | AP46: DESPREZAR | AQ46: 45962 | AR46: 45961 | AS46: 45971
A47: 45962 | B47: GÁS CONSUMO M³ | C47: 0 | D47: 0.015 | E47: 1.03 | F47: 2.895 | G47: 1.34 | H47: 1.508 | I47: 3.856 | J47: 1.266 | K47: 1.421 | L47: 0.32 | M47: 1.549 | N47: 0.422 | O47: 3.771 | P47: 0 | Q47: 1.007 | R47: DESPREZAR | S47: =A47 -> 45962 | T47: 45961 | U47: 45971 | W47: =SUM(A47:U47)=SUM(Y47:AS47) -> TRUE | Y47: 45962 | Z47: GÁS CONSUMO M³ | AA47: 0 | AB47: 0.015 | AC47: 1.03 | AD47: 2.895 | AE47: 1.34 | AF47: 1.508 | AG47: 3.856 | AH47: 1.266 | AI47: 1.421 | AJ47: 0.32 | AK47: 1.549 | AL47: 0.422 | AM47: 3.771 | AN47: 0 | AO47: 1.007 | AP47: DESPREZAR | AQ47: 45962 | AR47: 45961 | AS47: 45971
